Workbook
Name billion: #REF!
Name billion: #REF!
Name Diesel_FE_2024: #REF!
Name Diesel_Sales_2024: #REF!
Name Eno_TM: #REF!
Name Eno_TM: #REF!
Name Eno_TM: #REF!
Name Eno_TM: #REF!
Name Eno_TM: #REF!
Name Eno_Tons: #REF!
Name Eno_Tons: #REF!
Name Eno_Tons: #REF!
Name Eno_Tons: #REF!
Name Eno_Tons: #REF!
Name EV_FE_2024: #REF!
Name EV_Sales_2024: #REF!
Name Fuel_Economies: #REF!
Name Gasoline_FE_2024: #REF!
Name Gasoline_Sales_2024: #REF!
Name Hydg_FE_2024: #REF!
Name Hydg_Sales_2024: #REF!
Name LPG_FE_2024: #REF!
Name LPG_Sales_2024: #REF!
Name NG_FE_2024: #REF!
Name NG_Sales_2024: #REF!
Name NTS_YR: #REF!
Name NTS_YR: About!$B$106
Name PHEV_FE_2024: #REF!
Name PHEV_Sales_2024: #REF!
Name Sales: #REF!
Name Sales_2024: #REF!
Name Sales_2025: #REF!
Name Sales_2026: #REF!
Name Sales_2027: #REF!
Name Sales_2028: #REF!
Name Sales_2029: #REF!
Name Standards: #REF!
Name Sum_T2: #REF!
Name Sum_T2: #REF!
Name Sum_T2: #REF!
Name Sum_T2: #REF!
Name Sum_T2: #REF!
Name Sum_TTM: #REF!
Name Sum_TTM: #REF!
Name Sum_TTM: #REF!
Name Sum_TTM: #REF!
Name Sum_TTM: #REF!
Name ti_tbl_50: #REF!
Name ti_tbl_50: #REF!
Name ti_tbl_50: #REF!
Name ti_tbl_50: #REF!
Name ti_tbl_50: #REF!
Name ti_tbl_69: #REF!
Name ti_tbl_69: #REF!
Name ti_tbl_69: #REF!
Name ti_tbl_69: #REF!
Name ti_tbl_69: #REF!
Name trillion: #REF!
Name trillion: #REF!

Sheet About
A1: Active state name: | B1: Mississippi | C1: 46266
A2: Active state code: | B2: =INDEX(Geography!$A$2:$A$49,MATCH($B$1,Geography!$B$2:$B$49,0)) -> MS
A5: BNVFE BAU New Vehicle Fuel Economy
A7: Sources: | B7: See Notes section for which vehicle types use which sources
B8: U.S. Energy Information Administration
B9: 2026
B10: Annual Energy Outlook 2026
B11: Scenario: Alternative Electricity and Transportation
B12: https://www.eia.gov/outlooks/aeo/tables_side_xls.php
B13: Tables 7, 35, 36, 38, 40, 47, 48, 49
B15: Bureau of Transportation Statistics
B16: 2017
B17: National Transportation Statistics
B18: https://www.rita.dot.gov/bts/sites/rita.dot.gov.bts/files/publications/national_transportation_statistics/index.html
B19: Table 1-40
B21: U.S. Coast Guard
B22: 2013
B23: National Recreational Boating Survey 2012
B24: http://www.uscgboating.org/library/recreational-boating-servey/2012survey%20report.pdf
B25: Page 63, Table 40
B27: U.S. Department of Energy
B28: 2015
B29: Fuel Cells Fact Sheet
B30: https://www.energy.gov/sites/prod/files/2015/11/f27/fcto_fuel_cells_fact_sheet.pdf
B32: U.S EPA
B33: 2022
B34: Automotive Trends Data
B35: https://www.epa.gov/automotive-trends/explore-automotive-trends-data#DetailedData
B37: Others as noted on "Calculations Etc" tab
B39: Passenger rail diesel vs. electric efficiency
B40: Environmental and Energy Study Institute
B41: 2018
B42: Electrification of U.S. Railways: Pie in the Sky, or Realistic Goal?
B43: https://www.eesi.org/articles/view/electrification-of-u.s.-railways-pie-in-the-sky-or-realistic-goal
B44: Third paragraph
A46: Notes
A47: This variable gives fuel economy for new vehicles in units of cargo distance per BTU.
A49: passenger LDVs
A50: Sources: AEO 7, AEO 40, CARB LEV III standards, others as noted on "Calculations Etc" tab
A51: The AEO provides new vehicle fuel economy in mpge terms. For each of the 7 EPS technologies, we take a weighted average of EIA's listed new vehicle
A52: fuel economy for all vehicles that would fall under the given technology. We then adjust by EIA's ratio of onroad:tested fuel economy from Table 7 and
A53: convert to thing-miles/BTU by multiplying by the passenger loading used in the file trans/AVLo and the BTU content of a gallon of gasoline.
A55: EIA's NEMS model has higher efficiency values than reported by the EPA, because it it over-complies on efficiency in order to meet EPA standards (since it doesn't have representation of other options to reduce the equivalent g CO2/mile metric from HFC/advanced tech credits). We calculate the delta between EPA and EIA fuel efficiency
A56: values in 2022 and subtract that value from future years.
A58: If a state has adopted CARB LEV III standards, then we take the more stringent of the CARB standard or AEO2026 Table 40 projection when calculating in passenger LDV calcs.
A59: Added a state calculations tab.
A62: freight LDVs and HDVs
... A112: This vehicle type is not used in the U.S. model.
A114: NTS_YR | B114: 2019

Sheet Geography
A1: state_abbr | B1: state_name
A2: AL | B2: Alabama
A3: AR | B3: Arkansas
A4: AZ | B4: Arizona
A5: CA | B5: California
A6: CO | B6: Colorado
A7: CT | B7: Connecticut
A8: DE | B8: Delaware
A9: FL | B9: Florida
A10: GA | B10: Georgia
A11: IA | B11: Iowa
A12: ID | B12: Idaho
... A49: WY | B49: Wyoming

Sheet source data>

Sheet AEO 2023 Table 7
B1: ref2023.d020623a | C1: 2022 | D1: 2023 | E1: 2024 | F1: 2025 | G1: 2026 | H1: 2027 | I1: 2028 | J1: 2029 | K1: 2030 | L1: 2031 | M1: 2032 | N1: 2033 | O1: 2034 | P1: 2035 | Q1: 2036 | R1: 2037 | S1: 2038 | T1: 2039 | U1: 2040 | V1: 2041 | W1: 2042 | X1: 2043 | Y1: 2044 | Z1: 2045 | AA1: 2046 | AB1: 2047 | AC1: 2048 | AD1: 2049 | AE1: 2050
C3: Report | D3: Annual Energy Outlook 2023
C4: Scenario | D4: ref2023 | G4: Reference
C5: Datekey | D5: d020623a
C6: Release Date | E6: March 2023
A10: TKI000 | B10: 7. Transportation Sector Key Indicators and Delivered Energy Consumption | AF10: Average
AF11: Annual
AF12: Change
B13: Key Indicators and Consumption | C13: 2022 | D13: 2023 | E13: 2024 | F13: 2025 | G13: 2026 | H13: 2027 | I13: 2028 | J13: 2029 | K13: 2030 | L13: 2031 | M13: 2032 | N13: 2033 | O13: 2034 | P13: 2035 | Q13: 2036 | R13: 2037 | S13: 2038 | T13: 2039 | U13: 2040 | V13: 2041 | W13: 2042 | X13: 2043 | Y13: 2044 | Z13: 2045 | AA13: 2046 | AB13: 2047 | AC13: 2048 | AD13: 2049 | AE13: 2050 | AF13: 2022–2050
B15: Key Indicators
B16: Travel Indicators
B17: (billion vehicle miles traveled)
A18: TKI000:ba_Light-DutyVeh | B18: Light-Duty Vehicles less than 8,501 pounds | C18: 2843.2981 | D18: 2901.3589 | E18: 2922.5066 | F18: 2933.3601 | G18: 2954.238 | H18: 2981.9343 | I18: 3007.5581 | J18: 3027.573 | K18: 3042.8433 | L18: 3055.7747 | M18: 3066.6516 | N18: 3082.3594 | O18: 3102.4182 | P18: 3120.7375 | Q18: 3135.6208 | R18: 3152.9177 | S18: 3172.4355 | T18: 3192.1006 | U18: 3214.563 | V18: 3237.5806 | W18: 3261.5847 | X18: 3284.8975 | Y18: 3309.0391 | Z18: 3334.7034 | AA18: 3364.5225 | AB18: 3396.5352 | AC18: 3429.5627 | AD18: 3463.0249 | AE18: 3499.543 | AF18: 0.007444
A19: TKI000:ba_CommercialLig | B19: Commercial Light Trucks 1/ | C19: 102.21495 | D19: 103.34346 | E19: 103.55378 | F19: 104.36999 | G19: 105.65627 | H19: 107.00255 | I19: 108.20406 | J19: 109.32984 | K19: 110.21457 | L19: 111.0637 | M19: 112.17591 | N19: 113.26731 | O19: 114.36133 | P19: 115.53986 | Q19: 116.6934 | R19: 117.93478 | S19: 119.26325 | T19: 120.51714 | U19: 121.9657 | V19: 123.54321 | W19: 125.05544 | X19: 126.4902 | Y19: 127.8319 | Z19: 129.14803 | AA19: 130.64792 | AB19: 132.25534 | AC19: 133.71924 | AD19: 135.16911 | AE19: 137.06503 | AF19: 0.010533
A20: TKI000:ba_FreightTrucks | B20: Freight Trucks greater than 10,000 pounds | C20: 321.95499 | D20: 320.72061 | E20: 321.15665 | F20: 324.03918 | G20: 328.45148 | H20: 332.31928 | I20: 335.87875 | J20: 338.621 | K20: 341.15326 | L20: 344.16229 | M20: 348.16583 | N20: 351.54123 | O20: 354.83011 | P20: 358.3447 | Q20: 361.39355 | R20: 364.92679 | S20: 368.38065 | T20: 371.81143 | U20: 375.58807 | V20: 379.58752 | W20: 383.51465 | X20: 387.20883 | Y20: 390.63339 | Z20: 393.83795 | AA20: 397.54263 | AB20: 401.35467 | AC20: 404.65982 | AD20: 408.22446 | AE20: 413.08252 | AF20: 0.008941
B21: (billion passenger miles traveled)
A22: TKI000:buspassmiles | B22: Bus Transportation | C22: 175.47365 | D22: 186.88329 | E22: 193.3692 | F22: 197.39229 | G22: 200.32752 | H22: 202.52968 | I22: 204.21141 | J22: 205.46838 | K22: 206.39357 | L22: 207.0294 | M22: 207.54085 | N22: 207.99565 | O22: 208.43976 | P22: 208.79684 | Q22: 209.10339 | R22: 209.37013 | S22: 209.49379 | T22: 209.54416 | U22: 209.54358 | V22: 209.49118 | W22: 209.41185 | X22: 209.25844 | Y22: 209.10913 | Z22: 208.93102 | AA22: 208.81189 | AB22: 208.60612 | AC22: 208.41769 | AD22: 208.19235 | AE22: 207.99593 | AF22: 0.006091
A23: TKI000:railpassmiles | B23: Passenger Rail | C23: 30.144947 | D23: 32.030231 | E23: 33.06411 | F23: 33.706196 | G23: 34.620327 | H23: 35.443916 | I23: 36.137474 | J23: 36.650322 | K23: 37.00806 | L23: 37.264553 | M23: 37.633518 | N23: 38.06789 | O23: 38.564194 | P23: 38.985653 | Q23: 39.398945 | R23: 39.809189 | S23: 40.237045 | T23: 40.652229 | U23: 41.127975 | V23: 41.567631 | W23: 42.019573 | X23: 42.40731 | Y23: 42.842342 | Z23: 43.266335 | AA23: 43.867863 | AB23: 44.361511 | AC23: 44.905075 | AD23: 45.395485 | AE23: 46.002594 | AF23: 0.01521
B24: (billion seat miles available)
A25: TKI000:ba_Air | B25: Air | C25: 1173.0347 | D25: 1318.6946 | E25: 1361.6111 | F25: 1371.6552 | G25: 1402.928 | H25: 1433.8398 | I25: 1461.4722 | J25: 1484.8291 | K25: 1504.2688 | L25: 1524.7269 | M25: 1552.2568 | N25: 1583.9248 | O25: 1615.3802 | P25: 1647.3462 | Q25: 1682.5896 | R25: 1721.0469 | S25: 1761.139 | T25: 1801.941 | U25: 1848.072 | V25: 1894.2041 | W25: 1941.463 | X25: 1990.3643 | Y25: 2038.4374 | Z25: 2085.6875 | AA25: 2134.0049 | AB25: 2185.897 | AC25: 2238.8362 | AD25: 2292.3555 | AE25: 2350.269 | AF25: 0.02513
B26: (billion ton miles traveled)
A27: TKI000:ba_Rail | B27: Rail | C27: 1620.4949 | D27: 1600.1008 | E27: 1666.9198 | F27: 1628.4084 | G27: 1561.4207 | H27: 1509.6494 | I27: 1489.7312 | J27: 1507.5151 | K27: 1500.1649 | L27: 1506.9524 | M27: 1522.1982 | N27: 1534.7394 | O27: 1543.2374 | P27: 1554.5907 | Q27: 1557.5254 | R27: 1562.4816 | S27: 1568.9661 | T27: 1568.3395 | U27: 1571.7775 | V27: 1585.6112 | W27: 1597.307 | X27: 1600.1909 | Y27: 1601.8328 | Z27: 1602.9988 | AA27: 1608.1294 | AB27: 1618.0824 | AC27: 1630.808 | AD27: 1636.8905 | AE27: 1649.4695 | AF27: 0.000633
A28: TKI000:ba_DomesticShipp | B28: Domestic Shipping | C28: 444.89887 | D28: 450.42761 | E28: 448.61005 | F28: 446.74628 | G28: 445.22772 | H28: 442.84778 | I28: 440.43005 | J28: 437.0246 | K28: 434.03641 | L28: 431.39212 | M28: 429.99737 | N28: 428.16068 | O28: 426.27862 | P28: 424.17816 | Q28: 421.71698 | R28: 419.81464 | S28: 417.56705 | T28: 415.80768 | U28: 414.04514 | V28: 412.52209 | W28: 411.24774 | X28: 409.97736 | Y28: 408.52225 | Z28: 406.63034 | AA28: 405.35852 | AB28: 403.86591 | AC28: 401.97906 | AD28: 400.55664 | AE28: 400.09833 | AF28: -0.003783
B30: Energy Efficiency Indicators | C30: =C41/C38 -> 0.81570903 | D30: =C30/'EPA Auto Trends 2022'!B3 -> 1.0579946
B31: (miles per gallon)
A32: TKI000:ca_AvgCAFEStand | B32: New Light-Duty Vehicle CAFE Standard 2/ | C32: 35.855949 | D32: 36.277985 | E32: 39.337013 | F32: 42.578201 | G32: 47.262627 | H32: 47.227249 | I32: 47.18121 | J32: 47.168774 | K32: 47.163849 | L32: 47.152081 | M32: 47.159279 | N32: 47.152672 | O32: 47.146118 | P32: 47.131687 | Q32: 47.138325 | R32: 47.119869 | S32: 47.100937 | T32: 47.084251 | U32: 47.059879 | V32: 47.032314 | W32: 47.004074 | X32: 46.960155 | Y32: 46.939564 | Z32: 46.91069 | AA32: 46.948238 | AB32: 46.913113 | AC32: 46.90683 | AD32: 46.880138 | AE32: 46.870857 | AF32: 0.009613
A33: TKI000:ca_CarCAFEStand | B33: New Car 2/ | C33: 45.004654 | D33: 45.471119 | E33: 49.460312 | F33: 53.789036 | G33: 59.791531 | H33: 59.80352 | I33: 59.817413 | J33: 59.819332 | K33: 59.821598 | L33: 59.822445 | M33: 59.827473 | N33: 59.828793 | O33: 59.83078 | P33: 59.83112 | Q33: 59.842136 | R33: 59.842136 | S33: 59.842136 | T33: 59.843197 | U33: 59.843197 | V33: 59.843231 | W33: 59.845177 | X33: 59.845177 | Y33: 59.848228 | Z33: 59.848228 | AA33: 59.867775 | AB33: 59.867775 | AC33: 59.867775 | AD33: 59.867775 | AE33: 59.867775 | AF33: 0.010244
A34: TKI000:ca_TwukCAFEStand | B34: New Light Truck 2/ | C34: 32.047302 | D34: 32.608868 | E34: 35.403008 | F34: 38.46349 | G34: 42.755749 | H34: 42.75658 | I34: 42.76173 | J34: 42.76173 | K34: 42.761841 | L34: 42.762085 | M34: 42.762169 | N34: 42.76236 | O34: 42.76239 | P34: 42.76252 | Q34: 42.762554 | R34: 42.762699 | S34: 42.762756 | T34: 42.762825 | U34: 42.762897 | V34: 42.762962 | W34: 42.763016 | X34: 42.763103 | Y34: 42.763103 | Z34: 42.763184 | AA34: 42.763184 | AB34: 42.763294 | AC34: 42.763294 | AD34: 42.763393 | AE34: 42.763393 | AF34: 0.010356
A35: TKI000:ca_NewVehCred | B35: Compliance New Light-Duty Vehicle 3/ | C35: 41.802036 | D35: 43.2672 | E35: 44.448151 | F35: 47.052715 | G35: 48.571758 | H35: 49.79253 | I35: 52.281479 | J35: 53.248959 | K35: 53.962006 | L35: 54.332035 | M35: 54.872646 | N35: 55.329353 | O35: 55.771633 | P35: 56.242725 | Q35: 56.632603 | R35: 56.856194 | S35: 57.030457 | T35: 57.310715 | U35: 57.240421 | V35: 57.306023 | W35: 57.371868 | X35: 57.326744 | Y35: 57.237999 | Z35: 57.125122 | AA35: 57.475964 | AB35: 57.327747 | AC35: 57.273457 | AD35: 57.524818 | AE35: 57.479156 | AF35: 0.011439
A36: TKI000:ca_NewCarCred | B36: New Car 3/ | C36: 56.582645 | D36: 58.322227 | E36: 59.783314 | F36: 64.222374 | G36: 65.997482 | H36: 68.148636 | I36: 72.759445 | J36: 74.876167 | K36: 76.446304 | L36: 77.157303 | M36: 78.145363 | N36: 78.735664 | O36: 79.269257 | P36: 79.864815 | Q36: 80.311752 | R36: 80.510567 | S36: 80.643074 | T36: 81.042244 | U36: 80.790894 | V36: 80.999863 | W36: 81.213394 | X36: 81.251564 | Y36: 81.126785 | Z36: 80.963654 | AA36: 81.962257 | AB36: 81.685669 | AC36: 81.57402 | AD36: 82.338425 | AE36: 82.243484 | AF36: 0.013446
A37: TKI000:ca_NewTwukCred | B37: New Light Truck 3/ | C37: 36.263931 | D37: 37.832123 | E37: 39.014805 | F37: 41.375153 | G37: 42.876762 | H37: 43.911583 | I37: 45.953789 | J37: 46.678478 | K37: 47.207012 | L37: 47.518375 | M37: 47.939487 | N37: 48.362621 | O37: 48.779861 | P37: 49.233047 | Q37: 49.585567 | R37: 49.838345 | S37: 50.048077 | T37: 50.325745 | U37: 50.338009 | V37: 50.426777 | W37: 50.517311 | X37: 50.542614 | Y37: 50.50412 | Z37: 50.459385 | AA37: 50.61805 | AB37: 50.565735 | AC37: 50.535652 | AD37: 50.739391 | AE37: 50.721836 | AF37: 0.012055
A38: TKI000:ca_TestedNewVeh | B38: Tested New Light-Duty Vehicle 4/ | C38: 37.621078 | D38: 38.382416 | E38: 39.075672 | F38: 40.794502 | G38: 41.684994 | H38: 42.387779 | I38: 43.992405 | J38: 44.482399 | K38: 44.828846 | L38: 45.012852 | M38: 45.295109 | N38: 45.54966 | O38: 45.800465 | P38: 46.072914 | Q38: 46.308186 | R38: 46.454895 | S38: 46.573441 | T38: 46.763412 | U38: 46.743324 | V38: 46.781216 | W38: 46.812752 | X38: 46.781078 | Y38: 46.720787 | Z38: 46.649311 | AA38: 46.812588 | AB38: 46.721981 | AC38: 46.686661 | AD38: 46.844208 | AE38: 46.809135 | AF38: 0.007835
A39: TKI000:ca_TestedNewCar | B39: New Car 4/ | C39: 49.658657 | D39: 50.63982 | E39: 51.418789 | F39: 54.041267 | G39: 54.808311 | H39: 55.812794 | I39: 58.414131 | J39: 59.295654 | K39: 59.885937 | L39: 60.128426 | M39: 60.482559 | N39: 60.696911 | O39: 60.896141 | P39: 61.139969 | Q39: 61.34211 | R39: 61.456459 | S39: 61.54549 | T39: 61.791069 | U39: 61.720493 | V39: 61.820892 | W39: 61.909645 | X39: 61.923454 | Y39: 61.848679 | Z39: 61.762375 | AA39: 62.120819 | AB39: 61.989952 | AC39: 61.932671 | AD39: 62.331699 | AE39: 62.272804 | AF39: 0.008117
A40: TKI000:ca_TestedNewTwuk | B40: New Light Truck 4/ | C40: 32.951321 | D40: 33.82571 | E40: 34.570251 | F40: 36.235542 | G40: 37.203815 | H40: 37.859802 | I40: 39.251301 | J40: 39.65464 | K40: 39.942871 | L40: 40.123779 | M40: 40.372108 | N40: 40.635685 | O40: 40.898228 | P40: 41.187042 | Q40: 41.415565 | R40: 41.589336 | S40: 41.735809 | T40: 41.930031 | U40: 41.954327 | V40: 42.014381 | W40: 42.070942 | X40: 42.089371 | Y40: 42.062252 | Z40: 42.034523 | AA40: 42.106945 | AB40: 42.074627 | AC40: 42.053329 | AD40: 42.192116 | AE40: 42.17543 | AF40: 0.008853
A41: TKI000:ca_OnRoadNewVeh | B41: On-Road New Light-Duty Vehicle 5/ | C41: 30.687853 | D41: 31.308468 | E41: 31.873775 | F41: 33.275242 | G41: 34.001518 | H41: 34.574638 | I41: 35.883228 | J41: 36.28281 | K41: 36.56535 | L41: 36.715401 | M41: 36.945652 | N41: 37.153278 | O41: 37.357868 | P41: 37.580082 | Q41: 37.772026 | R41: 37.891651 | S41: 37.988308 | T41: 38.143211 | U41: 38.126759 | V41: 38.157574 | W41: 38.183201 | X41: 38.157219 | Y41: 38.107975 | Z41: 38.049587 | AA41: 38.182838 | AB41: 38.108822 | AC41: 38.080002 | AD41: 38.208389 | AE41: 38.179749 | AF41: 0.007832
A42: TKI000:ca_OnRoadNewCar | B42: New Car 5/ | C42: 40.552002 | D42: 41.353237 | E42: 41.989353 | F42: 44.130909 | G42: 44.75729 | H42: 45.577564 | I42: 47.701855 | J42: 48.421719 | K42: 48.903755 | L42: 49.101772 | M42: 49.390965 | N42: 49.566006 | O42: 49.728703 | P42: 49.927814 | Q42: 50.092888 | R42: 50.186264 | S42: 50.258968 | T42: 50.459515 | U42: 50.401878 | V42: 50.483868 | W42: 50.556343 | X42: 50.567619 | Y42: 50.506557 | Z42: 50.436081 | AA42: 50.72879 | AB42: 50.621925 | AC42: 50.575146 | AD42: 50.901001 | AE42: 50.852905 | AF42: 0.008117
A43: TKI000:ca_OnRoadNewTwuk | B43: New Light Truck 5/ | C43: 26.867123 | D43: 27.580063 | E43: 28.18713 | F43: 29.544939 | G43: 30.334429 | H43: 30.869291 | I43: 32.00386 | J43: 32.332729 | K43: 32.567738 | L43: 32.715244 | M43: 32.917721 | N43: 33.132629 | O43: 33.346695 | P43: 33.582184 | Q43: 33.768513 | R43: 33.910198 | S43: 34.029625 | T43: 34.187984 | U43: 34.207794 | V43: 34.25676 | W43: 34.302879 | X43: 34.317905 | Y43: 34.295792 | Z43: 34.273186 | AA43: 34.332233 | AB43: 34.305882 | AC43: 34.288517 | AD43: 34.40168 | AE43: 34.388073 | AF43: 0.008853
... A47: TKI000:ca_FreightTruck | B47: Freight Truck | C47: 7.472406 | D47: 7.578529 | E47: 7.705323 | F47: 7.84859 | G47: 8.002383 | H47: 8.163677 | I47: 8.321285 | J47: 8.479755 | K47: 8.638294 | L47: 8.79593 | M47: 8.948549 | N47: 9.090997 | O47: 9.222516 | P47: 9.343068 | Q47: 9.453315 | R47: 9.553063 | S47: 9.643444 | T47: 9.72671 | U47: 9.804593 | V47: 9.877275 | W47: 9.942431 | X47: 10.001567 | Y47: 10.055841 | Z47: 10.108454 | AA47: 10.161228 | AB47: 10.213311 | AC47: 10.263764 | AD47: 10.314513 | AE47: 10.365861 | AF47: 0.011758
B48: (seat miles per gallon)
A49: TKI000:ca_Aircraft | B49: Aircraft | C49: 72.717087 | D49: 73.091972 | E49: 73.492531 | F49: 74.018456 | G49: 74.683121 | H49: 75.131767 | I49: 75.59214 | J49: 76.024017 | K49: 76.492363 | L49: 77.014214 | M49: 77.60096 | N49: 78.266678 | O49: 78.981506 | P49: 79.730591 | Q49: 80.48922 | R49: 81.260979 | S49: 82.048454 | T49: 82.814575 | U49: 83.594772 | V49: 84.382309 | W49: 85.171204 | X49: 85.974022 | Y49: 86.764038 | Z49: 87.549927 | AA49: 88.321091 | AB49: 89.091156 | AC49: 89.849762 | AD49: 90.593376 | AE49: 91.328148 | AF49: 0.008172
B50: (ton miles/thousand Btu)
A51: TKI000:ca_Rail | B51: Rail | C51: 3.36634 | D51: 3.369893 | E51: 3.37345 | F51: 3.37701 | G51: 3.380574 | H51: 3.384142 | I51: 3.387713 | J51: 3.391289 | K51: 3.394868 | L51: 3.398451 | M51: 3.402037 | N51: 3.405628 | O51: 3.409222 | P51: 3.41282 | Q51: 3.416422 | R51: 3.420027 | S51: 3.423637 | T51: 3.42725 | U51: 3.430867 | V51: 3.434488 | W51: 3.438113 | X51: 3.441741 | Y51: 3.445373 | Z51: 3.44901 | AA51: 3.452649 | AB51: 3.456293 | AC51: 3.459941 | AD51: 3.463593 | AE51: 3.467248 | AF51: 0.001055
A52: TKI000:ca_DomesticShipp | B52: Domestic Shipping | C52: 4.820226 | D52: 4.838966 | E52: 4.857779 | F52: 4.876665 | G52: 4.895624 | H52: 4.914657 | I52: 4.933764 | J52: 4.952945 | K52: 4.9722 | L52: 4.991531 | M52: 5.010937 | N52: 5.030418 | O52: 5.049975 | P52: 5.069608 | Q52: 5.089317 | R52: 5.109103 | S52: 5.128966 | T52: 5.148906 | U52: 5.168923 | V52: 5.189019 | W52: 5.209192 | X52: 5.229445 | Y52: 5.249775 | Z52: 5.270185 | AA52: 5.290674 | AB52: 5.311243 | AC52: 5.331892 | AD52: 5.352621 | AE52: 5.37343 | AF52: 0.003888
B54: Energy Use by Mode
B55: (quadrillion Btu)
A56: TKI000:da_Light-DutyVeh | B56: Light-Duty Vehicles | C56: 14.541973 | D56: 14.586114 | E56: 14.429692 | F56: 14.201925 | G56: 14.016909 | H56: 13.860763 | I56: 13.679087 | J56: 13.473832 | K56: 13.253083 | L56: 13.044086 | M56: 12.836978 | N56: 12.674039 | O56: 12.534656 | P56: 12.394664 | Q56: 12.251548 | R56: 12.130822 | S56: 12.028416 | T56: 11.933923 | U56: 11.864001 | V56: 11.805396 | W56: 11.762742 | X56: 11.733644 | Y56: 11.725387 | Z56: 11.735775 | AA56: 11.770763 | AB56: 11.824349 | AC56: 11.889715 | AD56: 11.96291 | AE56: 12.054455 | AF56: -0.006678
A57: TKI000:da_CommercialLig | B57: Commercial Light Trucks 1/ | C57: 0.951503 | D57: 0.942558 | E57: 0.92534 | F57: 0.912452 | G57: 0.903111 | H57: 0.894807 | I57: 0.888385 | J57: 0.882995 | K57: 0.877033 | L57: 0.872791 | M57: 0.871791 | N57: 0.871868 | O57: 0.873034 | P57: 0.875074 | Q57: 0.8775 | R57: 0.881023 | S57: 0.885541 | T57: 0.889796 | U57: 0.896146 | V57: 0.903924 | W57: 0.911921 | X57: 0.918675 | Y57: 0.924721 | Z57: 0.93183 | AA57: 0.93994 | AB57: 0.94995 | AC57: 0.95832 | AD57: 0.96721 | AE57: 0.978898 | AF57: 0.001014
A58: TKI000:da_BusTransporta | B58: Bus Transportation | C58: 0.212163 | D58: 0.222312 | E58: 0.226957 | F58: 0.228013 | G58: 0.228798 | H58: 0.229238 | I58: 0.229403 | J58: 0.229156 | K58: 0.228548 | L58: 0.227556 | M58: 0.22653 | N58: 0.226005 | O58: 0.225336 | P58: 0.224473 | Q58: 0.223496 | R58: 0.22194 | S58: 0.220576 | T58: 0.219099 | U58: 0.2175 | V58: 0.215784 | W58: 0.214032 | X58: 0.212017 | Y58: 0.210154 | Z58: 0.208215 | AA58: 0.206535 | AB58: 0.204463 | AC58: 0.20246 | AD58: 0.200282 | AE58: 0.198183 | AF58: -0.002432
A59: TKI000:da_FreightTrucks | B59: Freight Trucks | C59: 5.921126 | D59: 5.815005 | E59: 5.726179 | F59: 5.670887 | G59: 5.636415 | H59: 5.588956 | I59: 5.540693 | J59: 5.48039 | K59: 5.418849 | L59: 5.367491 | M59: 5.336062 | N59: 5.302126 | O59: 5.274123 | P59: 5.25631 | Q59: 5.237802 | R59: 5.232226 | S59: 5.230621 | T59: 5.23229 | U59: 5.241601 | V59: 5.256566 | W59: 5.274461 | X59: 5.292318 | Y59: 5.309026 | Z59: 5.323563 | AA59: 5.344643 | AB59: 5.367305 | AC59: 5.383854 | AD59: 5.403469 | AE59: 5.43954 | AF59: -0.003025
A60: TKI000:da_Rail,Passenge | B60: Rail, Passenger | C60: 0.043913 | D60: 0.045564 | E60: 0.046541 | F60: 0.047205 | G60: 0.0479 | H60: 0.048571 | I60: 0.049133 | J60: 0.049707 | K60: 0.05015 | L60: 0.050599 | M60: 0.05114 | N60: 0.051727 | O60: 0.052369 | P60: 0.052924 | Q60: 0.053457 | R60: 0.053973 | S60: 0.05451 | T60: 0.055034 | U60: 0.055627 | V60: 0.056181 | W60: 0.056754 | X60: 0.057258 | Y60: 0.057816 | Z60: 0.058367 | AA60: 0.059116 | AB60: 0.059751 | AC60: 0.060445 | AD60: 0.061081 | AE60: 0.061848 | AF60: 0.012306
A61: TKI000:da_Rail,Freight | B61: Rail, Freight | C61: 0.481382 | D61: 0.474822 | E61: 0.494129 | F61: 0.482204 | G61: 0.46188 | H61: 0.446095 | I61: 0.439745 | J61: 0.444526 | K61: 0.441892 | L61: 0.443423 | M61: 0.447437 | N61: 0.450648 | O61: 0.452666 | P61: 0.455515 | Q61: 0.455894 | R61: 0.456862 | S61: 0.458275 | T61: 0.457609 | U61: 0.458128 | V61: 0.461673 | W61: 0.464588 | X61: 0.464937 | Y61: 0.464923 | Z61: 0.464771 | AA61: 0.465767 | AB61: 0.468155 | AC61: 0.47134 | AD61: 0.472599 | AE61: 0.475729 | AF61: -0.000422
A62: TKI000:da_Shipping,Dome | B62: Shipping, Domestic | C62: 0.098239 | D62: 0.098921 | E62: 0.098115 | F62: 0.097346 | G62: 0.096686 | H62: 0.095823 | I62: 0.094965 | J62: 0.093891 | K62: 0.092919 | L62: 0.09203 | M62: 0.091401 | N62: 0.090674 | O62: 0.089934 | P62: 0.089169 | Q62: 0.088333 | R62: 0.087615 | S62: 0.086833 | T62: 0.086157 | U62: 0.085474 | V62: 0.084846 | W62: 0.084274 | X62: 0.083705 | Y62: 0.083103 | Z62: 0.082418 | AA62: 0.081856 | AB62: 0.081249 | AC62: 0.080573 | AD62: 0.07999 | AE62: 0.079593 | AF62: -0.007489
A63: TKI000:da_Shipping,Inte | B63: Shipping, International | C63: 0.935028 | D63: 0.88183 | E63: 0.877727 | F63: 0.878604 | G63: 0.87125 | H63: 0.868449 | I63: 0.862689 | J63: 0.859142 | K63: 0.856634 | L63: 0.857136 | M63: 0.857437 | N63: 0.858 | O63: 0.85776 | P63: 0.858218 | Q63: 0.857547 | R63: 0.857614 | S63: 0.857635 | T63: 0.85735 | U63: 0.857245 | V63: 0.857301 | W63: 0.85783 | X63: 0.85782 | Y63: 0.858048 | Z63: 0.858068 | AA63: 0.860633 | AB63: 0.860924 | AC63: 0.859834 | AD63: 0.859122 | AE63: 0.858095 | AF63: -0.003062
A64: TKI000:da_RecreationalB | B64: Recreational Boats | C64: 0.202837 | D64: 0.199163 | E64: 0.195805 | F64: 0.193737 | G64: 0.192813 | H64: 0.191897 | I64: 0.190734 | J64: 0.18921 | K64: 0.187404 | L64: 0.185677 | M64: 0.184467 | N64: 0.18361 | O64: 0.182778 | P64: 0.181998 | Q64: 0.18145 | R64: 0.181106 | S64: 0.180746 | T64: 0.180383 | U64: 0.180295 | V64: 0.180161 | W64: 0.179988 | X64: 0.179814 | Y64: 0.179557 | Z64: 0.179244 | AA64: 0.17895 | AB64: 0.178728 | AC64: 0.178491 | AD64: 0.178228 | AE64: 0.178156 | AF64: -0.004623
A65: TKI000:da_Air | B65: Air | C65: 2.802808 | D65: 3.008168 | E65: 3.051203 | F65: 3.057111 | G65: 3.095898 | H65: 3.134227 | I65: 3.164552 | J65: 3.187108 | K65: 3.202938 | L65: 3.218783 | M65: 3.243937 | N65: 3.270448 | O65: 3.294403 | P65: 3.322924 | Q65: 3.359825 | R65: 3.403895 | S65: 3.450172 | T65: 3.498488 | U65: 3.554644 | V65: 3.608403 | W65: 3.663098 | X65: 3.718625 | Y65: 3.77401 | Z65: 3.827919 | AA65: 3.880434 | AB65: 3.936738 | AC65: 3.993604 | AD65: 4.049651 | AE65: 4.112158 | AF65: 0.013784
A66: TKI000:da_MilitaryUse | B66: Military Use | C66: 0.430832 | D66: 0.433131 | E66: 0.433968 | F66: 0.434628 | G66: 0.435162 | H66: 0.435947 | I66: 0.436506 | J66: 0.436951 | K66: 0.437332 | L66: 0.437576 | M66: 0.437744 | N66: 0.437827 | O66: 0.437858 | P66: 0.437879 | Q66: 0.438004 | R66: 0.438203 | S66: 0.438412 | T66: 0.438631 | U66: 0.438858 | V66: 0.439093 | W66: 0.439335 | X66: 0.439584 | Y66: 0.439839 | Z66: 0.440099 | AA66: 0.440364 | AB66: 0.440633 | AC66: 0.440907 | AD66: 0.441184 | AE66: 0.441465 | AF66: 0.000871
A67: TKI000:da_Lubricants | B67: Lubricants | C67: 0.125945 | D67: 0.125925 | E67: 0.126012 | F67: 0.12605 | G67: 0.126114 | H67: 0.125984 | I67: 0.125853 | J67: 0.125755 | K67: 0.125652 | L67: 0.125546 | M67: 0.125439 | N67: 0.12533 | O67: 0.12525 | P67: 0.125225 | Q67: 0.125255 | R67: 0.125318 | S67: 0.125412 | T67: 0.125527 | U67: 0.125667 | V67: 0.125797 | W67: 0.125925 | X67: 0.126046 | Y67: 0.126166 | Z67: 0.12632 | AA67: 0.126492 | AB67: 0.126661 | AC67: 0.126811 | AD67: 0.126974 | AE67: 0.127159 | AF67: 0.000342
... A70: TKI000:da_Total | B70: Total | C70: 27.986006 | D70: 28.032028 | E70: 27.776655 | F70: 27.4657 | G70: 27.255045 | H70: 27.051918 | I70: 26.819283 | J70: 26.59227 | K70: 26.360722 | L70: 26.162958 | M70: 26.008129 | N70: 25.897749 | O70: 25.802094 | P70: 25.704212 | Q70: 25.598515 | R70: 25.533525 | S70: 25.493338 | T70: 25.449312 | U70: 25.46059 | V70: 25.485914 | W70: 25.531475 | X70: 25.583796 | Y70: 25.657438 | Z70: 25.744152 | AA70: 25.868387 | AB70: 26.019403 | AC70: 26.175444 | AD70: 26.332941 | AE70: 26.540415 | AF70: -0.001892
B72: (million barrels per day oil equivalent)
A73: TKI000:ea_Light-DutyVeh | B73: Light-Duty Vehicles | C73: 7.887402 | D73: 7.912227 | E73: 7.827434 | F73: 7.704175 | G73: 7.603646 | H73: 7.518498 | I73: 7.419035 | J73: 7.306525 | K73: 7.185357 | L73: 7.070691 | M73: 6.957016 | N73: 6.86728 | O73: 6.790267 | P73: 6.712955 | Q73: 6.633772 | R73: 6.566808 | S73: 6.509881 | T73: 6.457382 | U73: 6.418384 | V73: 6.385576 | W73: 6.361585 | X73: 6.345073 | Y73: 6.340106 | Z73: 6.345462 | AA73: 6.36419 | AB73: 6.393152 | AC73: 6.428598 | AD73: 6.468379 | AE73: 6.518199 | AF73: -0.006786
A74: TKI000:ea_CommercialLig | B74: Commercial Light Trucks 1/ | C74: 0.496809 | D74: 0.492193 | E74: 0.483314 | F74: 0.476842 | G74: 0.472221 | H74: 0.467932 | I74: 0.464712 | J74: 0.462053 | K74: 0.459111 | L74: 0.457084 | M74: 0.456754 | N74: 0.456989 | O74: 0.457814 | P74: 0.459091 | Q74: 0.460564 | R74: 0.462619 | S74: 0.465189 | T74: 0.467623 | U74: 0.471176 | V74: 0.475436 | W74: 0.479853 | X74: 0.483793 | Y74: 0.487354 | Z74: 0.491353 | AA74: 0.496003 | AB74: 0.501565 | AC74: 0.506491 | AD74: 0.511462 | AE74: 0.517981 | AF74: 0.001492
A75: TKI000:ea_BusTransporta | B75: Bus Transportation | C75: 0.105213 | D75: 0.110296 | E75: 0.11259 | F75: 0.113083 | G75: 0.113492 | H75: 0.113737 | I75: 0.113843 | J75: 0.113729 | K75: 0.113434 | L75: 0.112917 | M75: 0.112403 | N75: 0.112129 | O75: 0.111806 | P75: 0.111381 | Q75: 0.110915 | R75: 0.110151 | S75: 0.109477 | T75: 0.108762 | U75: 0.107969 | V75: 0.107129 | W75: 0.106288 | X75: 0.105307 | Y75: 0.104391 | Z75: 0.103434 | AA75: 0.102605 | AB75: 0.101578 | AC75: 0.100586 | AD75: 0.099507 | AE75: 0.09846 | AF75: -0.002366
A76: TKI000:ea_FreightTrucks | B76: Freight Trucks | C76: 2.850965 | D76: 2.800434 | E76: 2.758164 | F76: 2.732194 | G76: 2.716136 | H76: 2.693672 | I76: 2.671257 | J76: 2.642962 | K76: 2.614177 | L76: 2.590174 | M76: 2.575932 | N76: 2.560368 | O76: 2.547745 | P76: 2.539845 | Q76: 2.531643 | R76: 2.529634 | S76: 2.5295 | T76: 2.530971 | U76: 2.536117 | V76: 2.544034 | W76: 2.553331 | X76: 2.562598 | Y76: 2.571348 | Z76: 2.579022 | AA76: 2.589984 | AB76: 2.601707 | AC76: 2.610389 | AD76: 2.620612 | AE76: 2.638885 | AF76: -0.002757
A77: TKI000:ea_Rail,Passenge | B77: Rail, Passenger | C77: 0.020781 | D77: 0.021563 | E77: 0.022025 | F77: 0.02234 | G77: 0.022668 | H77: 0.022984 | I77: 0.023251 | J77: 0.023523 | K77: 0.023733 | L77: 0.023945 | M77: 0.024201 | N77: 0.024479 | O77: 0.024783 | P77: 0.025045 | Q77: 0.025298 | R77: 0.025542 | S77: 0.025796 | T77: 0.026044 | U77: 0.026325 | V77: 0.026587 | W77: 0.026858 | X77: 0.027097 | Y77: 0.027361 | Z77: 0.027622 | AA77: 0.027977 | AB77: 0.028278 | AC77: 0.028605 | AD77: 0.028906 | AE77: 0.02927 | AF77: 0.012308
A78: TKI000:ea_Rail,Freight | B78: Rail, Freight | C78: 0.228347 | D78: 0.225234 | E78: 0.234373 | F78: 0.228717 | G78: 0.21906 | H78: 0.211545 | I78: 0.208541 | J78: 0.210806 | K78: 0.209559 | L78: 0.210276 | M78: 0.212178 | N78: 0.213692 | O78: 0.21465 | P78: 0.215989 | Q78: 0.216165 | R78: 0.216616 | S78: 0.21728 | T78: 0.216956 | U78: 0.217194 | V78: 0.218865 | W78: 0.220234 | X78: 0.220387 | Y78: 0.22037 | Z78: 0.220283 | AA78: 0.220747 | AB78: 0.221866 | AC78: 0.223355 | AD78: 0.223935 | AE78: 0.225407 | AF78: -0.000463
A79: TKI000:ea_Shipping,Dome | B79: Shipping, Domestic | C79: 0.046527 | D79: 0.046853 | E79: 0.04647 | F79: 0.04611 | G79: 0.045796 | H79: 0.045385 | I79: 0.044983 | J79: 0.044476 | K79: 0.04402 | L79: 0.0436 | M79: 0.043306 | N79: 0.042963 | O79: 0.042617 | P79: 0.042256 | Q79: 0.041863 | R79: 0.041525 | S79: 0.041158 | T79: 0.04084 | U79: 0.040519 | V79: 0.040222 | W79: 0.03995 | X79: 0.039681 | Y79: 0.039395 | Z79: 0.03907 | AA79: 0.038805 | AB79: 0.038517 | AC79: 0.038196 | AD79: 0.037919 | AE79: 0.037732 | AF79: -0.007455
A80: TKI000:ea_Shipping,Inte | B80: Shipping, International | C80: 0.417032 | D80: 0.39771 | E80: 0.396229 | F80: 0.396613 | G80: 0.393975 | H80: 0.392997 | I80: 0.390956 | J80: 0.389709 | K80: 0.388847 | L80: 0.389075 | M80: 0.389247 | N80: 0.389507 | O80: 0.389481 | P80: 0.389698 | Q80: 0.389505 | R80: 0.389575 | S80: 0.389634 | T80: 0.389581 | U80: 0.389597 | V80: 0.38967 | W80: 0.389917 | X80: 0.389969 | Y80: 0.390113 | Z80: 0.390178 | AA80: 0.391183 | AB80: 0.391349 | AC80: 0.391006 | AD80: 0.3908 | AE80: 0.390489 | AF80: -0.002346
A81: TKI000:ea_RecreationalB | B81: Recreational Boats | C81: 0.110006 | D81: 0.108038 | E81: 0.106242 | F81: 0.105144 | G81: 0.104667 | H81: 0.104195 | I81: 0.103587 | J81: 0.102784 | K81: 0.101827 | L81: 0.100913 | M81: 0.100279 | N81: 0.099838 | O81: 0.099409 | P81: 0.099009 | Q81: 0.098731 | R81: 0.098564 | S81: 0.098387 | T81: 0.098209 | U81: 0.098181 | V81: 0.098125 | W81: 0.098049 | X81: 0.097971 | Y81: 0.097849 | Z81: 0.097695 | AA81: 0.097552 | AB81: 0.097448 | AC81: 0.097337 | AD81: 0.097211 | AE81: 0.097188 | AF81: -0.004415
A82: TKI000:ea_Air | B82: Air | C82: 1.355634 | D82: 1.454865 | E82: 1.475662 | F82: 1.478519 | G82: 1.497263 | H82: 1.515786 | I82: 1.530442 | J82: 1.541344 | K82: 1.548995 | L82: 1.556654 | M82: 1.568811 | N82: 1.581624 | O82: 1.593202 | P82: 1.606986 | Q82: 1.624819 | R82: 1.646116 | S82: 1.668479 | T82: 1.691828 | U82: 1.718965 | V82: 1.744943 | W82: 1.771373 | X82: 1.798206 | Y82: 1.82497 | Z82: 1.851021 | AA82: 1.876398 | AB82: 1.903606 | AC82: 1.931086 | AD82: 1.95817 | AE82: 1.988375 | AF82: 0.013774
A83: TKI000:ea_MilitaryUse | B83: Military Use | C83: 0.207325 | D83: 0.208431 | E83: 0.20883 | F83: 0.209148 | G83: 0.209402 | H83: 0.209774 | I83: 0.210045 | J83: 0.210259 | K83: 0.210443 | L83: 0.21056 | M83: 0.210641 | N83: 0.21068 | O83: 0.210697 | P83: 0.210706 | Q83: 0.210766 | R83: 0.210862 | S83: 0.210964 | T83: 0.211069 | U83: 0.211179 | V83: 0.211292 | W83: 0.211409 | X83: 0.211529 | Y83: 0.211652 | Z83: 0.211777 | AA83: 0.211906 | AB83: 0.212036 | AC83: 0.212167 | AD83: 0.2123 | AE83: 0.212437 | AF83: 0.00087
A84: TKI000:ea_Lubricants | B84: Lubricants | C84: 0.059492 | D84: 0.059483 | E84: 0.059524 | F84: 0.059542 | G84: 0.059572 | H84: 0.059511 | I84: 0.059449 | J84: 0.059403 | K84: 0.059354 | L84: 0.059304 | M84: 0.059253 | N84: 0.059202 | O84: 0.059164 | P84: 0.059152 | Q84: 0.059166 | R84: 0.059196 | S84: 0.05924 | T84: 0.059295 | U84: 0.059361 | V84: 0.059422 | W84: 0.059483 | X84: 0.05954 | Y84: 0.059597 | Z84: 0.059669 | AA84: 0.059751 | AB84: 0.05983 | AC84: 0.059901 | AD84: 0.059978 | AE84: 0.060066 | AF84: 0.000342
... A87: TKI000:ea_Total | B87: Total | C87: 14.370443 | D87: 14.403465 | E87: 14.271711 | F87: 14.108815 | G87: 13.997396 | H87: 13.890337 | I87: 13.767988 | J87: 13.645885 | K87: 13.520164 | L87: 13.411051 | M87: 13.323045 | N87: 13.25902 | O87: 13.203858 | P87: 13.147519 | Q87: 13.087383 | R87: 13.048246 | S87: 13.022289 | T87: 12.995312 | U87: 12.996621 | V87: 13.0055 | W87: 13.025239 | X87: 13.049395 | Y87: 13.085273 | Z87: 13.128707 | AA87: 13.19174 | AB87: 13.269163 | AC87: 13.350009 | AD87: 13.432016 | AE87: 13.539635 | AF87: -0.002125
B89: 1/ Commercial trucks have a 8,501 to 10,000 pound gross vehicle weight rating.
B90: 2/ CAFE standard based on projected new vehicle sales.
B91: 3/ Includes CAFE credits for alternative fueled vehicle sales and credit banking.
B92: 4/ U.S. Environmental Protection Agency rated miles per gallon.
B93: 5/ Tested new vehicle efficiency revised for on-road performance.
B94: 6/ Combined "on-the-road" estimate for all cars and light trucks.
B95: 7/ Fuel used in facilities that liquefy natural gas for export.
B96: CAFE = Corporate average fuel economy.
B97: Btu = British thermal unit.
B98: Note: Totals may not equal sum of components due to independent rounding.
B99: Data source: 2022: U.S. Energy Information Administration (EIA), Short-Term Energy Outlook, November 2022 and EIA, AEO2023
B100: AEO2023 National Energy Modeling System run ref2023.d020623a. Projections: EIA, AEO2023 National Energy Modeling System run ref2023.d020623a.

Sheet AEO 2025 Table 7
A1: Table 7. Transportation Sector Key Indicators and Delivered Energy Consumption
A2: https://www.eia.gov/outlooks/aeo/data/browser/#/?id=7-AEO2025&cases=alttrnp&sourcekey=0
A3: Fri Dec 05 2025 14:42:41 GMT-0800 (Pacific Standard Time)
A4: Source: U.S. Energy Information Administration
B5: full name | C5: api key | D5: units | E5: 2023 | F5: 2024 | G5: 2025 | H5: 2026 | I5: 2027 | J5: 2028 | K5: 2029 | L5: 2030 | M5: 2031 | N5: 2032 | O5: 2033 | P5: 2034 | Q5: 2035 | R5: 2036 | S5: 2037 | T5: 2038 | U5: 2039 | V5: 2040 | W5: 2041 | X5: 2042 | Y5: 2043 | Z5: 2044 | AA5: 2045 | AB5: 2046 | AC5: 2047 | AD5: 2048 | AE5: 2049 | AF5: 2050 | AG5: Growth (2024-2050)
A6: Key Indicators
A7: Travel Indicators
A8: (billion vehicle miles traveled)
A9: Light-Duty Vehicles less than 8 | B9: Transportation: Travel Indicators: Light-Duty Vehicles <= 8,500 lbs: Alternative Transportation | C9: AEO.2025.ALTTRNP.KEI_TRV_TRN_NA_LDV_NA_NA_BLNVEHMLS.A | D9: billion vehicle miles | F9: 3013.7297 | G9: 3058.3716 | H9: 3083.4512 | I9: 3100.0171 | J9: 3112.2297 | K9: 3125.5762 | L9: 3140.167 | M9: 3154.0073 | N9: 3161.4351 | O9: 3167.1465 | P9: 3171.917 | Q9: 3174.3567 | R9: 3179.4163 | S9: 3189.5078 | T9: 3202.9607 | U9: 3216.1187 | V9: 3230.5129 | W9: 3244.2317 | X9: 3257.2742 | Y9: 3268.8367 | Z9: 3279.3418 | AA9: 3288.4412 | AB9: 3297.5173 | AC9: 3308.5703 | AD9: 3321.3464 | AE9: 3335.0469 | AF9: 3349.864 | AG9: 0.004
A10: Commercial Light Trucks | B10: Transportation: Travel Indicators: Commercial Light Trucks: Alternative Transportation | C10: AEO.2025.ALTTRNP.KEI_TRV_TRN_NA_CML_NA_NA_BLNVEHMLS.A | D10: billion vehicle miles | F10: 90.234665 | G10: 88.746048 | H10: 87.524918 | I10: 86.879402 | J10: 86.146126 | K10: 85.551414 | L10: 85.088478 | M10: 84.55584 | N10: 84.013214 | O10: 83.542664 | P10: 83.043007 | Q10: 82.538109 | R10: 82.013916 | S10: 81.499672 | T10: 80.976738 | U10: 80.459801 | V10: 79.954575 | W10: 79.410118 | X10: 78.884186 | Y10: 78.326515 | Z10: 77.80687 | AA10: 77.239433 | AB10: 76.680191 | AC10: 76.081207 | AD10: 75.451775 | AE10: 74.792137 | AF10: 74.117767 | AG10: -0.008
A11: Freight Trucks greater than 10 | B11: Transportation: Travel Indicators: Freight Trucks > 10,000 lbs.: Alternative Transportation | C11: AEO.2025.ALTTRNP.KEI_TRV_TRN_NA_FGHT_NA_NA_BLNVEHMLS.A | D11: billion vehicle miles | F11: 340.05481 | G11: 346.20789 | H11: 350.06781 | I11: 353.52682 | J11: 356.01294 | K11: 358.95523 | L11: 362.11615 | M11: 364.84686 | N11: 367.715 | O11: 370.28033 | P11: 373.22687 | Q11: 376.19421 | R11: 379.62561 | S11: 383.28888 | T11: 386.97992 | U11: 390.32495 | V11: 393.89111 | W11: 397.25488 | X11: 400.59506 | Y11: 403.50134 | Z11: 406.14972 | AA11: 409.08057 | AB11: 411.83875 | AC11: 416.01117 | AD11: 420.09766 | AE11: 423.84226 | AF11: 427.05206 | AG11: 0.009
A12: (billion passenger miles traveled)
A13: Bus Transportation | B13: Transportation: Travel Indicators: Bus: Alternative Transportation | C13: AEO.2025.ALTTRNP.KEI_TRV_TRN_NA_BST_NA_NA_BPM.A | D13: billion passenger miles | F13: 190.78021 | G13: 196.63762 | H13: 200.38203 | I13: 202.76497 | J13: 204.50441 | K13: 205.76622 | L13: 206.65466 | M13: 207.15369 | N13: 207.40228 | O13: 207.54491 | P13: 207.69394 | Q13: 207.71609 | R13: 207.67081 | S13: 207.61053 | T13: 207.42905 | U13: 207.19026 | V13: 206.88676 | W13: 206.52594 | X13: 206.10233 | Y13: 205.65778 | Z13: 205.15973 | AA13: 204.65633 | AB13: 204.09099 | AC13: 203.49281 | AD13: 202.89883 | AE13: 202.30595 | AF13: 201.76945 | AG13: 0.002
A14: Passenger Rail | B14: Transportation: Travel Indicators: Passenger Rail: Alternative Transportation | C14: AEO.2025.ALTTRNP.KEI_TRV_TRN_NA_RLP_NA_NA_BPM.A | D14: billion passenger miles | F14: 25.878023 | G14: 28.773293 | H14: 30.990028 | I14: 32.691128 | J14: 34.018692 | K14: 35.161125 | L14: 36.109001 | M14: 36.852859 | N14: 37.463329 | O14: 37.9645 | P14: 38.458427 | Q14: 38.854378 | R14: 39.233795 | S14: 39.64349 | T14: 40.072304 | U14: 40.454437 | V14: 40.811695 | W14: 41.128437 | X14: 41.427906 | Y14: 41.717632 | Z14: 41.951229 | AA14: 42.199917 | AB14: 42.38929 | AC14: 42.61396 | AD14: 42.893345 | AE14: 43.173431 | AF14: 43.548084 | AG14: 0.02
A15: (billion seat miles available)
A16: Air | B16: Transportation: Travel Indicators: Air: Alternative Transportation | C16: AEO.2025.ALTTRNP.KEI_TRV_TRN_NA_AIR_NA_NA_BLNSEATMLS.A | D16: billion seat miles | F16: 1413.1366 | G16: 1426.5015 | H16: 1461.8976 | I16: 1494.7886 | J16: 1522.1002 | K16: 1551.6201 | L16: 1578.683 | M16: 1601.1815 | N16: 1627.1464 | O16: 1654.8922 | P16: 1681.6215 | Q16: 1711.0176 | R16: 1740.9607 | S16: 1772.7719 | T16: 1806.9364 | U16: 1841.1686 | V16: 1875.4396 | W16: 1909.1254 | X16: 1945.6185 | Y16: 1981.347 | Z16: 2014.7141 | AA16: 2047.4543 | AB16: 2079.6472 | AC16: 2117.3379 | AD16: 2157.5337 | AE16: 2196.0696 | AF16: 2234.0925 | AG16: 0.018
A17: (billion ton miles traveled)
A18: Rail | B18: Transportation: Travel Indicators: Rail: Alternative Transportation | C18: AEO.2025.ALTTRNP.KEI_TRV_TRN_NA_RAIL_NA_NA_BLNTNMLS.A | D18: billion ton miles | F18: 1464.8552 | G18: 1498.5776 | H18: 1462.3732 | I18: 1413.7332 | J18: 1414.1151 | K18: 1410.5652 | L18: 1369.7415 | M18: 1370.1805 | N18: 1305.8112 | O18: 1312.2113 | P18: 1299.8524 | Q18: 1300.421 | R18: 1305.7511 | S18: 1312.3923 | T18: 1330.2866 | U18: 1321.975 | V18: 1328.3295 | W18: 1330.2947 | X18: 1337.3475 | Y18: 1345.2047 | Z18: 1349.7686 | AA18: 1354.5587 | AB18: 1355.686 | AC18: 1370.3556 | AD18: 1382.5275 | AE18: 1392.7019 | AF18: 1397.2123 | AG18: -0.002
A19: Domestic Shipping | B19: Transportation: Travel Indicators: Domestic Shipping: Alternative Transportation | C19: AEO.2025.ALTTRNP.KEI_TRV_TRN_NA_DMT_NA_NA_BLNTNMLS.A | D19: billion ton miles | F19: 458.77335 | G19: 464.89285 | H19: 462.96167 | I19: 460.98572 | J19: 459.37042 | K19: 457.35059 | L19: 454.85974 | M19: 451.94983 | N19: 448.2905 | O19: 446.2366 | P19: 444.57028 | Q19: 442.67673 | R19: 440.63129 | S19: 439.09964 | T19: 437.71414 | U19: 435.98474 | V19: 434.76898 | W19: 433.49097 | X19: 432.2272 | Y19: 430.6734 | Z19: 428.80133 | AA19: 427.06717 | AB19: 425.276 | AC19: 424.65442 | AD19: 423.51385 | AE19: 422.14224 | AF19: 420.62109 | AG19: -0.003
A20: Energy Efficiency Indicators
A21: (miles per gallon)
A22: New Light-Duty Vehicle CAFE Standard | B22: Transportation: Energy Efficiency Indicators: CAFE Standard: New Light-Duty Vehicle: Alternative Transportation | C22: AEO.2025.ALTTRNP.EFI_CAFES_TRN_HWY_LDTY_NEW_NA_MLSPGLN.A | D22: mpg | F22: 39.271114 | G22: 42.959927 | H22: 47.575771 | I22: 47.493256 | J22: 47.449085 | K22: 47.490925 | L22: 47.59132 | M22: 47.604393 | N22: 47.569965 | O22: 47.492599 | P22: 47.679401 | Q22: 47.648468 | R22: 47.59169 | S22: 47.590065 | T22: 47.59457 | U22: 47.597126 | V22: 47.557652 | W22: 47.536556 | X22: 47.522251 | Y22: 47.527641 | Z22: 47.509605 | AA22: 47.515839 | AB22: 47.499699 | AC22: 47.476486 | AD22: 47.471779 | AE22: 47.466419 | AF22: 47.51144 | AG22: 0.007
A23: New Car | B23: Transportation: Energy Efficiency Indicators: CAFE Standard: New Car: Alternative Transportation | C23: AEO.2025.ALTTRNP.EFI_CAFES_TRN_HWY_CAR_NEW_NA_MLSPGLN.A | D23: mpg | F23: 48.175083 | G23: 52.414536 | H23: 58.241451 | I23: 58.255463 | J23: 58.26667 | K23: 58.284412 | L23: 58.290977 | M23: 58.296238 | N23: 58.292618 | O23: 58.297882 | P23: 58.32222 | Q23: 58.317551 | R23: 58.313091 | S23: 58.312267 | T23: 58.318325 | U23: 58.320648 | V23: 58.313702 | W23: 58.314289 | X23: 58.312122 | Y23: 58.322739 | Z23: 58.317924 | AA23: 58.327766 | AB23: 58.321186 | AC23: 58.318832 | AD23: 58.325527 | AE23: 58.327377 | AF23: 58.347694 | AG23: 0.007
A24: New Light Truck | B24: Transportation: Energy Efficiency Indicators: CAFE Standard: New Light Truck: Alternative Transportation | C24: AEO.2025.ALTTRNP.EFI_CAFES_TRN_HWY_LTRT_NEW_NA_MLSPGLN.A | D24: mpg | F24: 35.086903 | G24: 38.087925 | H24: 42.293404 | I24: 42.265976 | J24: 42.251019 | K24: 42.23045 | L24: 42.21875 | M24: 42.207088 | N24: 42.198193 | O24: 42.188656 | P24: 42.178352 | Q24: 42.170338 | R24: 42.163197 | S24: 42.15712 | T24: 42.150414 | U24: 42.144039 | V24: 42.139084 | W24: 42.13335 | X24: 42.127731 | Y24: 42.121071 | Z24: 42.115974 | AA24: 42.109615 | AB24: 42.105438 | AC24: 42.100983 | AD24: 42.095028 | AE24: 42.089645 | AF24: 42.083157 | AG24: 0.007
A25: Compliance New Light-Duty Vehicle | B25: Transportation: Energy Efficiency Indicators: Compliance: New Light-Duty Vehicle: Alternative Transportation | C25: AEO.2025.ALTTRNP.EFI_CAFEC_TRN_HWY_LDTY_NEW_NA_MLSPGLN.A | D25: mpg | F25: 39.942822 | G25: 43.957706 | H25: 47.924385 | I25: 48.168633 | J25: 48.206814 | K25: 47.845936 | L25: 47.905159 | M25: 48.590633 | N25: 49.493092 | O25: 48.658333 | P25: 49.540321 | Q25: 50.266624 | R25: 50.779812 | S25: 51.219345 | T25: 51.674301 | U25: 52.231579 | V25: 52.558426 | W25: 52.808189 | X25: 52.984974 | Y25: 53.223259 | Z25: 53.34993 | AA25: 53.548645 | AB25: 53.65453 | AC25: 53.715496 | AD25: 53.847446 | AE25: 53.972466 | AF25: 54.298809 | AG25: 0.012
A26: New Car | B26: Transportation: Energy Efficiency Indicators: Compliance: New Car: Alternative Transportation | C26: AEO.2025.ALTTRNP.EFI_CAFEC_TRN_HWY_CAR_NEW_NA_MLSPGLN.A | D26: mpg | F26: 53.113453 | G26: 57.640594 | H26: 63.3256 | I26: 68.261688 | J26: 68.800171 | K26: 66.58007 | L26: 66.17157 | M26: 67.334129 | N26: 70.141273 | O26: 69.02169 | P26: 70.175095 | Q26: 72.345963 | R26: 73.417397 | S26: 74.362701 | T26: 75.273003 | U26: 76.767471 | V26: 77.966553 | W26: 78.546875 | X26: 79.005653 | Y26: 79.448586 | Z26: 79.81424 | AA26: 80.153214 | AB26: 80.456696 | AC26: 80.688454 | AD26: 80.951462 | AE26: 81.205383 | AF26: 81.537048 | AG26: 0.017
A27: New Light Truck | B27: Transportation: Energy Efficiency Indicators: Compliance: New Light Truck: Alternative Transportation | C27: AEO.2025.ALTTRNP.EFI_CAFEC_TRN_HWY_LTRT_NEW_NA_MLSPGLN.A | D27: mpg | F27: 34.459515 | G27: 37.642277 | H27: 41.127472 | I27: 40.267258 | J27: 40.25531 | K27: 40.242519 | L27: 40.218754 | M27: 40.700054 | N27: 41.130524 | O27: 40.5546 | P27: 40.930511 | Q27: 41.310795 | R27: 41.765965 | S27: 42.053349 | T27: 42.351562 | U27: 42.643215 | V27: 42.837719 | W27: 43.033184 | X27: 43.158432 | Y27: 43.308086 | Z27: 43.407925 | AA27: 43.533504 | AB27: 43.621685 | AC27: 43.68882 | AD27: 43.782269 | AE27: 43.872547 | AF27: 44.049908 | AG27: 0.009
A28: Tested New Light-Duty Vehicle | B28: Transportation: Energy Efficiency Indicators: Tested: New Light-Duty Vehicle: Alternative Transportation | C28: AEO.2025.ALTTRNP.EFI_CAFET_TRN_HWY_LDTY_NEW_NA_MLSPGLN.A | D28: mpg | F28: 36.992214 | G28: 40.049953 | H28: 42.808971 | I28: 43.230892 | J28: 44.016903 | K28: 44.308899 | L28: 44.989899 | M28: 45.61496 | N28: 46.454155 | O28: 45.667557 | P28: 46.478081 | Q28: 47.149429 | R28: 47.616024 | S28: 48.020485 | T28: 48.435196 | U28: 48.949013 | V28: 49.253231 | W28: 49.479267 | X28: 49.642773 | Y28: 49.856163 | Z28: 49.976059 | AA28: 50.153816 | AB28: 50.256393 | AC28: 50.313774 | AD28: 50.431538 | AE28: 50.545406 | AF28: 50.836014 | AG28: 0.012
A29: New Car | B29: Transportation: Energy Efficiency Indicators: Tested: New Car: Alternative Transportation | C29: AEO.2025.ALTTRNP.EFI_CAFET_TRN_HWY_CAR_NEW_NA_MLSPGLN.A | D29: mpg | F29: 48.381924 | G29: 51.754009 | H29: 55.653797 | I29: 59.137737 | J29: 61.278339 | K29: 61.308632 | L29: 62.88327 | M29: 63.968285 | N29: 66.642883 | O29: 65.576897 | P29: 66.66021 | Q29: 68.722473 | R29: 69.727547 | S29: 70.61306 | T29: 71.466324 | U29: 72.886696 | V29: 74.021286 | W29: 74.5662 | X29: 74.998436 | Y29: 75.41684 | Z29: 75.761993 | AA29: 76.083054 | AB29: 76.370346 | AC29: 76.590515 | AD29: 76.839706 | AE29: 77.080559 | AF29: 77.395805 | AG29: 0.018
A30: New Light Truck | B30: Transportation: Energy Efficiency Indicators: Tested: New Light Truck: Alternative Transportation | C30: AEO.2025.ALTTRNP.EFI_CAFET_TRN_HWY_LTRT_NEW_NA_MLSPGLN.A | D30: mpg | F30: 32.114288 | G30: 34.514839 | H30: 36.986862 | I30: 36.634201 | J30: 37.092926 | K30: 37.343777 | L30: 37.577011 | M30: 38.011017 | N30: 38.403038 | O30: 37.869068 | P30: 38.209908 | Q30: 38.555424 | R30: 38.963661 | S30: 39.224598 | T30: 39.495064 | U30: 39.75996 | V30: 39.93721 | W30: 40.114799 | X30: 40.230305 | Y30: 40.36813 | Z30: 40.460381 | AA30: 40.576187 | AB30: 40.657494 | AC30: 40.719509 | AD30: 40.805653 | AE30: 40.888672 | AF30: 41.051575 | AG30: 0.009
A31: On-Road New Light-Duty Vehicle | B31: Transportation: Energy Efficiency Indicators: On-Road New Light-Duty Vehicle: Alternative Transportation | C31: AEO.2025.ALTTRNP.EFI_CAFEO_TRN_HWY_LDTY_NEW_NA_MLSPGLN.A | D31: mpg | F31: 27.538565 | G31: 29.747971 | H31: 31.720669 | I31: 32.058968 | J31: 32.641983 | K31: 32.859589 | L31: 33.335556 | M31: 33.78616 | N31: 34.398438 | O31: 33.841164 | P31: 34.423504 | Q31: 34.90659 | R31: 35.2328 | S31: 35.521309 | T31: 35.816288 | U31: 36.185467 | V31: 36.402821 | W31: 36.561584 | X31: 36.675686 | Y31: 36.824799 | Z31: 36.907936 | AA31: 37.031731 | AB31: 37.102467 | AC31: 37.140446 | AD31: 37.221237 | AE31: 37.299519 | AF31: 37.503345 | AG31: 0.012
A32: New Car | B32: Transportation: Energy Efficiency Indicators: On-Road New Car: Alternative Transportation | C32: AEO.2025.ALTTRNP.EFI_CAFEO_TRN_HWY_CAR_NEW_NA_MLSPGLN.A | D32: mpg | F32: 35.736515 | G32: 38.187515 | H32: 41.026562 | I32: 43.567795 | J32: 45.12907 | K32: 45.143227 | L32: 46.28548 | M32: 47.069462 | N32: 49.029163 | O32: 48.263416 | P32: 49.0424 | Q32: 50.544037 | R32: 51.270535 | S32: 51.909389 | T32: 52.522804 | U32: 53.556107 | V32: 54.379284 | W32: 54.76899 | X32: 55.077839 | Y32: 55.373089 | Z32: 55.619442 | AA32: 55.844055 | AB32: 56.048706 | AC32: 56.203579 | AD32: 56.377033 | AE32: 56.545631 | AF32: 56.762432 | AG32: 0.018
A33: New Light Truck | B33: Transportation: Energy Efficiency Indicators: On-Road New Light Truck: Alternative Transportation | C33: AEO.2025.ALTTRNP.EFI_CAFEO_TRN_HWY_LTRT_NEW_NA_MLSPGLN.A | D33: mpg | F33: 23.988018 | G33: 25.717506 | H33: 27.470898 | I33: 27.24152 | J33: 27.584202 | K33: 27.775764 | L33: 27.919968 | M33: 28.231255 | N33: 28.51063 | O33: 28.137867 | P33: 28.37771 | Q33: 28.619431 | R33: 28.901937 | S33: 29.085546 | T33: 29.275507 | U33: 29.461161 | V33: 29.584818 | W33: 29.708748 | X33: 29.788166 | Y33: 29.883118 | Z33: 29.9464 | AA33: 30.026072 | AB33: 30.081591 | AC33: 30.123497 | AD33: 30.182156 | AE33: 30.238665 | AF33: 30.351025 | AG33: 0.009
... A37: Freight Truck | B37: Transportation: Energy Efficiency Indicators: Freight Truck: Alternative Transportation | C37: AEO.2025.ALTTRNP.EFI_NA_TRN_HWY_FRTT_STK_NA_MLSPGLN.A | D37: mpg | F37: 7.757023 | G37: 7.826031 | H37: 7.906292 | I37: 7.996029 | J37: 8.094789 | K37: 8.199175 | L37: 8.307471 | M37: 8.417607 | N37: 8.528322 | O37: 8.63801 | P37: 8.745068 | Q37: 8.847067 | R37: 8.942054 | S37: 9.029954 | T37: 9.112733 | U37: 9.191482 | V37: 9.266891 | W37: 9.337207 | X37: 9.402058 | Y37: 9.46137 | Z37: 9.51621 | AA37: 9.569106 | AB37: 9.620891 | AC37: 9.670567 | AD37: 9.716979 | AE37: 9.761371 | AF37: 9.804544 | AG37: 0.009
A38: (seat miles per gallon)
A39: Aircraft | B39: Transportation: Energy Efficiency Indicators: Aircraft: Alternative Transportation | C39: AEO.2025.ALTTRNP.EFI_NA_TRN_NA_AIRC_NA_NA_SEATMPG.A | D39: seat mpg | F39: 85.368492 | G39: 85.782234 | H39: 86.453064 | I39: 87.12735 | J39: 87.815926 | K39: 88.497086 | L39: 89.183655 | M39: 89.886848 | N39: 90.639893 | O39: 91.399002 | P39: 92.155807 | Q39: 92.914574 | R39: 93.675323 | S39: 94.433296 | T39: 95.211731 | U39: 95.983521 | V39: 96.76857 | W39: 97.563377 | X39: 98.389313 | Y39: 99.21096 | Z39: 100.03321 | AA39: 100.86144 | AB39: 101.69376 | AC39: 102.53442 | AD39: 103.37976 | AE39: 104.222 | AF39: 105.06316 | AG39: 0.008
A40: (ton miles/thousand Btu)
A41: Rail | B41: Transportation: Energy Efficiency Indicators: Rail: Alternative Transportation | C41: AEO.2025.ALTTRNP.EFI_NA_TRN_NA_RAIL_NA_NA_TONMLPTHBTU.A | D41: ton miles/thousand Btu | F41: 3.37345 | G41: 3.37701 | H41: 3.380574 | I41: 3.384142 | J41: 3.387713 | K41: 3.391289 | L41: 3.394868 | M41: 3.398451 | N41: 3.402037 | O41: 3.405628 | P41: 3.409222 | Q41: 3.41282 | R41: 3.416422 | S41: 3.420027 | T41: 3.423637 | U41: 3.42725 | V41: 3.430867 | W41: 3.434488 | X41: 3.438113 | Y41: 3.441741 | Z41: 3.445373 | AA41: 3.44901 | AB41: 3.452649 | AC41: 3.456293 | AD41: 3.459941 | AE41: 3.463593 | AF41: 3.467248 | AG41: 0.001
A42: Domestic Shipping | B42: Transportation: Energy Efficiency Indicators: Domestic Shipping: Alternative Transportation | C42: AEO.2025.ALTTRNP.EFI_NA_TRN_NA_DMT_NA_NA_TONMLPTHBTU.A | D42: ton miles/thousand Btu | F42: 4.857779 | G42: 4.876665 | H42: 4.895624 | I42: 4.914657 | J42: 4.933764 | K42: 4.952945 | L42: 4.9722 | M42: 4.991531 | N42: 5.010937 | O42: 5.030418 | P42: 5.049975 | Q42: 5.069608 | R42: 5.089317 | S42: 5.109103 | T42: 5.128966 | U42: 5.148906 | V42: 5.168923 | W42: 5.189019 | X42: 5.209192 | Y42: 5.229445 | Z42: 5.249775 | AA42: 5.270185 | AB42: 5.290674 | AC42: 5.311243 | AD42: 5.331892 | AE42: 5.352621 | AF42: 5.37343 | AG42: 0.004
A43: Energy Use by Mode
A44: (quadrillion Btu)
A45: Light-Duty Vehicles | B45: Transportation: Energy Use by Mode: Light-Duty Vehicles: Alternative Transportation | C45: AEO.2025.ALTTRNP.CNSM_NA_TRN_LDV_USE_NA_NA_QBTU.A | D45: quads | F45: 15.264656 | G45: 15.318794 | H45: 15.263797 | I45: 15.137206 | J45: 14.977221 | K45: 14.792022 | L45: 14.586777 | M45: 14.410761 | N45: 14.212754 | O45: 14.032137 | P45: 13.876548 | Q45: 13.716936 | R45: 13.53182 | S45: 13.355209 | T45: 13.213084 | U45: 13.074738 | V45: 12.960391 | W45: 12.861576 | X45: 12.746393 | Y45: 12.672747 | Z45: 12.58318 | AA45: 12.516975 | AB45: 12.440613 | AC45: 12.393321 | AD45: 12.311717 | AE45: 12.264787 | AF45: 12.255931 | AG45: -0.008
A46: Commercial Light Trucks | B46: Transportation: Energy Use by Mode: Commercial Light Trucks: Alternative Transportation | C46: AEO.2025.ALTTRNP.CNSM_NA_TRN_CML_USE_NA_NA_QBTU.A | D46: quads | F46: 0.874375 | G46: 0.855739 | H46: 0.839741 | I46: 0.829063 | J46: 0.817038 | K46: 0.806523 | L46: 0.797053 | M46: 0.786668 | N46: 0.776019 | O46: 0.765748 | P46: 0.755153 | Q46: 0.744233 | R46: 0.733154 | S46: 0.721991 | T46: 0.710859 | U46: 0.699931 | V46: 0.689723 | W46: 0.678654 | X46: 0.668121 | Y46: 0.657262 | Z46: 0.646873 | AA46: 0.636532 | AB46: 0.626425 | AC46: 0.616496 | AD46: 0.606532 | AE46: 0.596606 | AF46: 0.586683 | AG46: -0.015
A47: Bus Transportation | B47: Transportation: Energy Use by Mode: Bus Transportation: Alternative Transportation | C47: AEO.2025.ALTTRNP.CNSM_NA_TRN_BST_USE_NA_NA_QBTU.A | D47: quads | F47: 0.207859 | G47: 0.213516 | H47: 0.21613 | I47: 0.217126 | J47: 0.217482 | K47: 0.217428 | L47: 0.217244 | M47: 0.216242 | N47: 0.214765 | O47: 0.213186 | P47: 0.211906 | Q47: 0.210372 | R47: 0.208783 | S47: 0.207225 | T47: 0.205645 | U47: 0.20398 | V47: 0.202187 | W47: 0.200301 | X47: 0.198292 | Y47: 0.196337 | Z47: 0.194281 | AA47: 0.19232 | AB47: 0.190195 | AC47: 0.187951 | AD47: 0.185792 | AE47: 0.183691 | AF47: 0.181904 | AG47: -0.005
A48: Freight Trucks | B48: Transportation: Energy Use by Mode: Freight Trucks: Alternative Transportation | C48: AEO.2025.ALTTRNP.CNSM_NA_TRN_FGHT_USE_NA_NA_QBTU.A | D48: quads | F48: 6.005128 | G48: 6.058611 | H48: 6.062553 | I48: 6.052277 | J48: 6.018679 | K48: 5.988855 | L48: 5.960129 | M48: 5.92348 | N48: 5.889193 | O48: 5.851345 | P48: 5.82186 | Q48: 5.796485 | R48: 5.783072 | S48: 5.777648 | T48: 5.775574 | U48: 5.770501 | V48: 5.770604 | W48: 5.771068 | X48: 5.774972 | Y48: 5.776579 | Z48: 5.77775 | AA48: 5.784515 | AB48: 5.789783 | AC48: 5.816376 | AD48: 5.843774 | AE48: 5.867581 | AF48: 5.884564 | AG48: -0.001
A49: Rail | B49: Transportation: Energy Use by Mode: Rail, Passenger: Alternative Transportation | C49: AEO.2025.ALTTRNP.CNSM_NA_TRN_RLP_USE_NA_NA_QBTU.A | D49: quads | F49: 0.043892 | G49: 0.046491 | H49: 0.047929 | I49: 0.048711 | J49: 0.049232 | K49: 0.049774 | L49: 0.050394 | M49: 0.050847 | N49: 0.05125 | O49: 0.051578 | P49: 0.051859 | Q49: 0.052284 | R49: 0.052821 | S49: 0.05337 | T49: 0.053936 | U49: 0.054449 | V49: 0.05492 | W49: 0.05534 | X49: 0.055737 | Y49: 0.056129 | Z49: 0.056455 | AA49: 0.056805 | AB49: 0.057083 | AC49: 0.057393 | AD49: 0.057765 | AE49: 0.058137 | AF49: 0.058625 | AG49: 0.011
A50: Rail | B50: Transportation: Energy Use by Mode: Rail, Freight: Alternative Transportation | C50: AEO.2025.ALTTRNP.CNSM_NA_TRN_RLF_USE_NA_NA_QBTU.A | D50: quads | F50: 0.434231 | G50: 0.443759 | H50: 0.432581 | I50: 0.417752 | J50: 0.417425 | K50: 0.415938 | L50: 0.403474 | M50: 0.403178 | N50: 0.383832 | O50: 0.385307 | P50: 0.381275 | Q50: 0.38104 | R50: 0.382198 | S50: 0.383737 | T50: 0.38856 | U50: 0.385725 | V50: 0.38717 | W50: 0.387334 | X50: 0.388977 | Y50: 0.39085 | Z50: 0.391763 | AA50: 0.392738 | AB50: 0.392651 | AC50: 0.396481 | AD50: 0.399581 | AE50: 0.402098 | AF50: 0.402975 | AG50: -0.003
A51: Shipping | B51: Transportation: Energy Use by Mode: Shipping, Domestic: Alternative Transportation | C51: AEO.2025.ALTTRNP.CNSM_NA_TRN_SHDT_USE_NA_NA_QBTU.A | D51: quads | F51: 0.094441 | G51: 0.09533 | H51: 0.094566 | I51: 0.093798 | J51: 0.093108 | K51: 0.092339 | L51: 0.091481 | M51: 0.090543 | N51: 0.089462 | O51: 0.088708 | P51: 0.088034 | Q51: 0.08732 | R51: 0.08658 | S51: 0.085945 | T51: 0.085342 | U51: 0.084675 | V51: 0.084112 | W51: 0.08354 | X51: 0.082974 | Y51: 0.082355 | Z51: 0.08168 | AA51: 0.081035 | AB51: 0.080382 | AC51: 0.079954 | AD51: 0.07943 | AE51: 0.078866 | AF51: 0.078278 | AG51: -0.007
A52: Shipping | B52: Transportation: Energy Use by Mode: Shipping, International: Alternative Transportation | C52: AEO.2025.ALTTRNP.CNSM_NA_TRN_SHINT_USE_NA_NA_QBTU.A | D52: quads | F52: 0.752119 | G52: 0.733382 | H52: 0.741755 | I52: 0.75532 | J52: 0.766295 | K52: 0.778196 | L52: 0.789926 | M52: 0.800556 | N52: 0.812124 | O52: 0.823287 | P52: 0.83493 | Q52: 0.844164 | R52: 0.851842 | S52: 0.859284 | T52: 0.865818 | U52: 0.872407 | V52: 0.878262 | W52: 0.883989 | X52: 0.889835 | Y52: 0.895572 | Z52: 0.901093 | AA52: 0.906316 | AB52: 0.910759 | AC52: 0.916784 | AD52: 0.923919 | AE52: 0.930804 | AF52: 0.937273 | AG52: 0.009
A53: Recreational Boats | B53: Transportation: Energy Use by Mode: Recreational Boats: Alternative Transportation | C53: AEO.2025.ALTTRNP.CNSM_NA_TRN_RBT_USE_NA_NA_QBTU.A | D53: quads | F53: 0.207605 | G53: 0.206045 | H53: 0.205252 | I53: 0.204434 | J53: 0.203145 | K53: 0.202085 | L53: 0.200753 | M53: 0.199065 | N53: 0.197719 | O53: 0.196503 | P53: 0.195253 | Q53: 0.194235 | R53: 0.193269 | S53: 0.192455 | T53: 0.191702 | U53: 0.190906 | V53: 0.190126 | W53: 0.189319 | X53: 0.188616 | Y53: 0.187856 | Z53: 0.186963 | AA53: 0.186015 | AB53: 0.185016 | AC53: 0.184286 | AD53: 0.183617 | AE53: 0.182851 | AF53: 0.182055 | AG53: -0.005
A54: Air | B54: Transportation: Energy Use by Mode: Air: Alternative Transportation | C54: AEO.2025.ALTTRNP.CNSM_NA_TRN_AIR_USE_NA_NA_QBTU.A | D54: quads | F54: 3.268324 | G54: 3.262033 | H54: 3.288747 | I54: 3.323875 | J54: 3.351261 | K54: 3.383548 | L54: 3.411572 | M54: 3.430951 | N54: 3.454605 | O54: 3.479305 | P54: 3.503246 | Q54: 3.534024 | R54: 3.567556 | S54: 3.607157 | T54: 3.649621 | U54: 3.693142 | V54: 3.735951 | W54: 3.776446 | X54: 3.821688 | Y54: 3.863978 | Z54: 3.901178 | AA54: 3.93691 | AB54: 3.970224 | AC54: 4.011132 | AD54: 4.05513 | AE54: 4.094516 | AF54: 4.133512 | AG54: 0.009
A55: Military Use | B55: Transportation: Energy Use by Mode: Military Use: Alternative Transportation | C55: AEO.2025.ALTTRNP.CNSM_NA_TRN_MILU_USE_NA_NA_QBTU.A | D55: quads | F55: 0.444789 | G55: 0.449845 | H55: 0.452969 | I55: 0.454896 | J55: 0.455762 | K55: 0.455593 | L55: 0.455377 | M55: 0.455842 | N55: 0.456217 | O55: 0.45661 | P55: 0.456933 | Q55: 0.457185 | R55: 0.457633 | S55: 0.458221 | T55: 0.458787 | U55: 0.459339 | V55: 0.459875 | W55: 0.460399 | X55: 0.460914 | Y55: 0.461423 | Z55: 0.461927 | AA55: 0.462425 | AB55: 0.462922 | AC55: 0.463419 | AD55: 0.463913 | AE55: 0.464408 | AF55: 0.464904 | AG55: 0.002
A56: Lubricants | B56: Transportation: Energy Use by Mode: Lubricants: Alternative Transportation | C56: AEO.2025.ALTTRNP.CNSM_NA_TRN_LBC_USE_NA_NA_QBTU.A | D56: quads | F56: 0.134269 | G56: 0.134665 | H56: 0.135305 | I56: 0.135764 | J56: 0.135972 | K56: 0.136085 | L56: 0.136129 | M56: 0.136055 | N56: 0.135958 | O56: 0.13591 | P56: 0.135892 | Q56: 0.135863 | R56: 0.135821 | S56: 0.135776 | T56: 0.135757 | U56: 0.135764 | V56: 0.135768 | W56: 0.135743 | X56: 0.135699 | Y56: 0.135634 | Z56: 0.135567 | AA56: 0.135501 | AB56: 0.135418 | AC56: 0.135323 | AD56: 0.135196 | AE56: 0.135056 | AF56: 0.134919 | AG56: 0
... A59: Total | B59: Transportation: Energy Use by Mode: Total: Alternative Transportation | C59: AEO.2025.ALTTRNP.CNSM_NA_TRN_NA_USE_NA_NA_QBTU.A | D59: quads | F59: 29.023834 | G59: 29.108829 | H59: 29.09259 | I59: 28.954325 | J59: 28.829184 | K59: 28.671766 | L59: 28.471897 | M59: 28.308323 | N59: 28.159512 | O59: 28.02387 | P59: 27.891521 | Q59: 27.749924 | R59: 27.603794 | S59: 27.481892 | T59: 27.396921 | U59: 27.298918 | V59: 27.232672 | W59: 27.171799 | X59: 27.104918 | Y59: 27.072628 | Z59: 27.025742 | AA59: 26.999422 | AB59: 26.969101 | AC59: 26.995098 | AD59: 26.992891 | AE59: 27.013369 | AF59: 27.068243 | AG59: -0.003
A60: (million barrels per day oil equivalent)
A61: Light-Duty Vehicles | B61: Transportation: Energy Use by Mode: Light-Duty Vehicles: Alternative Transportation | C61: AEO.2025.ALTTRNP.CNSM_NA_TRN_LDV_USE_NA_NA_MILLBPDYOEQ.A | D61: MMb/d oil eq | F61: 8.280889 | G61: 8.309361 | H61: 8.277567 | I61: 8.20647 | J61: 8.11729 | K61: 8.014231 | L61: 7.900139 | M61: 7.802271 | N61: 7.692446 | O61: 7.592483 | P61: 7.506065 | Q61: 7.417579 | R61: 7.314888 | S61: 7.216888 | T61: 7.13751 | U61: 7.060346 | V61: 6.996391 | W61: 6.940898 | X61: 6.876627 | Y61: 6.835149 | Z61: 6.785208 | AA61: 6.74804 | AB61: 6.705527 | AC61: 6.679025 | AD61: 6.633841 | AE61: 6.607573 | AF61: 6.602071 | AG61: -0.009
A62: Commercial Light Trucks | B62: Transportation: Energy Use by Mode: Commercial Light Trucks: Alternative Transportation | C62: AEO.2025.ALTTRNP.CNSM_NA_TRN_CML_USE_NA_NA_MILLBPDYOEQ.A | D62: MMb/d oil eq | F62: 0.457016 | G62: 0.447813 | H62: 0.440019 | I62: 0.434969 | J62: 0.429303 | K62: 0.42445 | L62: 0.420061 | M62: 0.415188 | N62: 0.410158 | O62: 0.405297 | P62: 0.400243 | Q62: 0.39499 | R62: 0.389598 | S62: 0.384107 | T62: 0.378557 | U62: 0.373077 | V62: 0.367916 | W62: 0.362277 | X62: 0.35687 | Y62: 0.351243 | Z62: 0.345849 | AA62: 0.340455 | AB62: 0.335169 | AC62: 0.329957 | AD62: 0.324721 | AE62: 0.319494 | AF62: 0.314264 | AG62: -0.014
A63: Bus Transportation | B63: Transportation: Energy Use by Mode: Bus Transportation: Alternative Transportation | C63: AEO.2025.ALTTRNP.CNSM_NA_TRN_BST_USE_NA_NA_MILLBPDYOEQ.A | D63: MMb/d oil eq | F63: 0.103228 | G63: 0.105926 | H63: 0.107151 | I63: 0.107583 | J63: 0.107718 | K63: 0.107648 | L63: 0.107517 | M63: 0.106982 | N63: 0.106228 | O63: 0.105447 | P63: 0.104835 | Q63: 0.104076 | R63: 0.103287 | S63: 0.102533 | T63: 0.101759 | U63: 0.100944 | V63: 0.100055 | W63: 0.099111 | X63: 0.098109 | Y63: 0.097108 | Z63: 0.096052 | AA63: 0.095037 | AB63: 0.093949 | AC63: 0.09284 | AD63: 0.091765 | AE63: 0.090727 | AF63: 0.089832 | AG63: -0.005
A64: Freight Trucks | B64: Transportation: Energy Use by Mode: Freight Trucks: Alternative Transportation | C64: AEO.2025.ALTTRNP.CNSM_NA_TRN_FGHT_USE_NA_NA_MILLBPDYOEQ.A | D64: MMb/d oil eq | F64: 2.893941 | G64: 2.920017 | H64: 2.922178 | I64: 2.91758 | J64: 2.902385 | K64: 2.889214 | L64: 2.876924 | M64: 2.860907 | N64: 2.846161 | O64: 2.829921 | P64: 2.817726 | Q64: 2.807262 | R64: 2.802357 | S64: 2.801118 | T64: 2.801233 | U64: 2.799705 | V64: 2.800392 | W64: 2.800707 | X64: 2.80227 | Y64: 2.802311 | Z64: 2.802036 | AA64: 2.804259 | AB64: 2.805666 | AC64: 2.817162 | AD64: 2.828771 | AE64: 2.838518 | AF64: 2.844889 | AG64: -0.001
A65: Rail | B65: Transportation: Energy Use by Mode: Rail, Passenger: Alternative Transportation | C65: AEO.2025.ALTTRNP.CNSM_NA_TRN_RLP_USE_NA_NA_MILLBPDYOEQ.A | D65: MMb/d oil eq | F65: 0.020775 | G65: 0.022004 | H65: 0.022684 | I65: 0.023053 | J65: 0.0233 | K65: 0.023556 | L65: 0.023849 | M65: 0.024064 | N65: 0.024254 | O65: 0.02441 | P65: 0.024543 | Q65: 0.024743 | R65: 0.024998 | S65: 0.025258 | T65: 0.025526 | U65: 0.025769 | V65: 0.025992 | W65: 0.026191 | X65: 0.026378 | Y65: 0.026564 | Z65: 0.026718 | AA65: 0.026884 | AB65: 0.027016 | AC65: 0.027163 | AD65: 0.027339 | AE65: 0.027515 | AF65: 0.027746 | AG65: 0.011
A66: Rail | B66: Transportation: Energy Use by Mode: Rail, Freight: Alternative Transportation | C66: AEO.2025.ALTTRNP.CNSM_NA_TRN_RLF_USE_NA_NA_MILLBPDYOEQ.A | D66: MMb/d oil eq | F66: 0.205982 | G66: 0.210496 | H66: 0.205175 | I66: 0.198123 | J66: 0.197978 | K66: 0.197273 | L66: 0.191365 | M66: 0.191222 | N66: 0.182045 | O66: 0.182744 | P66: 0.180835 | Q66: 0.180721 | R66: 0.181272 | S66: 0.182005 | T66: 0.184292 | U66: 0.182949 | V66: 0.183637 | W66: 0.183713 | X66: 0.184492 | Y66: 0.18538 | Z66: 0.185815 | AA66: 0.186277 | AB66: 0.186239 | AC66: 0.188059 | AD66: 0.189528 | AE66: 0.19072 | AF66: 0.191137 | AG66: -0.003
A67: Shipping | B67: Transportation: Energy Use by Mode: Shipping, Domestic: Alternative Transportation | C67: AEO.2025.ALTTRNP.CNSM_NA_TRN_SHDT_USE_NA_NA_MILLBPDYOEQ.A | D67: MMb/d oil eq | F67: 0.044744 | G67: 0.045169 | H67: 0.044805 | I67: 0.044439 | J67: 0.044117 | K67: 0.043755 | L67: 0.043351 | M67: 0.042908 | N67: 0.042398 | O67: 0.042042 | P67: 0.041725 | Q67: 0.041388 | R67: 0.04104 | S67: 0.040741 | T67: 0.040457 | U67: 0.040144 | V67: 0.039879 | W67: 0.039608 | X67: 0.039339 | Y67: 0.039046 | Z67: 0.038726 | AA67: 0.038419 | AB67: 0.03811 | AC67: 0.037908 | AD67: 0.037659 | AE67: 0.037391 | AF67: 0.037112 | AG67: -0.007
A68: Shipping | B68: Transportation: Energy Use by Mode: Shipping, International: Alternative Transportation | C68: AEO.2025.ALTTRNP.CNSM_NA_TRN_SHINT_USE_NA_NA_MILLBPDYOEQ.A | D68: MMb/d oil eq | F68: 0.335526 | G68: 0.328032 | H68: 0.332124 | I68: 0.338171 | J68: 0.34317 | K68: 0.348464 | L68: 0.353706 | M68: 0.358505 | N68: 0.363798 | O68: 0.368916 | P68: 0.374241 | Q68: 0.378378 | R68: 0.381832 | S68: 0.385139 | T68: 0.388078 | U68: 0.391027 | V68: 0.393661 | W68: 0.396252 | X68: 0.398897 | Y68: 0.401481 | Z68: 0.403971 | AA68: 0.40631 | AB68: 0.408261 | AC68: 0.410949 | AD68: 0.414133 | AE68: 0.417221 | AF68: 0.420119 | AG68: 0.009
A69: Recreational Boats | B69: Transportation: Energy Use by Mode: Recreational Boats: Alternative Transportation | C69: AEO.2025.ALTTRNP.CNSM_NA_TRN_RBT_USE_NA_NA_MILLBPDYOEQ.A | D69: MMb/d oil eq | F69: 0.112644 | G69: 0.111823 | H69: 0.111419 | I69: 0.111002 | J69: 0.110329 | K69: 0.109779 | L69: 0.109081 | M69: 0.10819 | N69: 0.107484 | O69: 0.106848 | P69: 0.106194 | Q69: 0.105666 | R69: 0.105161 | S69: 0.104739 | T69: 0.10435 | U69: 0.103936 | V69: 0.103532 | W69: 0.10311 | X69: 0.102745 | Y69: 0.102349 | Z69: 0.10188 | AA69: 0.101381 | AB69: 0.100854 | AC69: 0.100474 | AD69: 0.100127 | AE69: 0.099726 | AF69: 0.099309 | AG69: -0.005
A70: Air | B70: Transportation: Energy Use by Mode: Air: Alternative Transportation | C70: AEO.2025.ALTTRNP.CNSM_NA_TRN_AIR_USE_NA_NA_MILLBPDYOEQ.A | D70: MMb/d oil eq | F70: 1.580574 | G70: 1.577537 | H70: 1.590447 | I70: 1.607424 | J70: 1.620659 | K70: 1.636263 | L70: 1.649807 | M70: 1.659173 | N70: 1.670605 | O70: 1.682543 | P70: 1.694114 | Q70: 1.708989 | R70: 1.725194 | S70: 1.744331 | T70: 1.764852 | U70: 1.785884 | V70: 1.806571 | W70: 1.82614 | X70: 1.848003 | Y70: 1.86844 | Z70: 1.886417 | AA70: 1.903684 | AB70: 1.919784 | AC70: 1.939552 | AD70: 1.960815 | AE70: 1.979848 | AF70: 1.998692 | AG70: 0.009
A71: Military Use | B71: Transportation: Energy Use by Mode: Military Use: Alternative Transportation | C71: AEO.2025.ALTTRNP.CNSM_NA_TRN_MILU_USE_NA_NA_MILLBPDYOEQ.A | D71: MMb/d oil eq | F71: 0.213959 | G71: 0.216389 | H71: 0.217888 | I71: 0.218809 | J71: 0.219229 | K71: 0.219148 | L71: 0.219045 | M71: 0.219267 | N71: 0.219448 | O71: 0.219636 | P71: 0.219792 | Q71: 0.219913 | R71: 0.220129 | S71: 0.220413 | T71: 0.220685 | U71: 0.220951 | V71: 0.22121 | W71: 0.221461 | X71: 0.221709 | Y71: 0.221954 | Z71: 0.222197 | AA71: 0.222436 | AB71: 0.222676 | AC71: 0.222916 | AD71: 0.223153 | AE71: 0.223391 | AF71: 0.22363 | AG71: 0.002
A72: Lubricants | B72: Transportation: Energy Use by Mode: Lubricants: Alternative Transportation | C72: AEO.2025.ALTTRNP.CNSM_NA_TRN_LBC_USE_NA_NA_MILLBPDYOEQ.A | D72: MMb/d oil eq | F72: 0.063424 | G72: 0.063611 | H72: 0.063913 | I72: 0.064131 | J72: 0.064228 | K72: 0.064282 | L72: 0.064303 | M72: 0.064268 | N72: 0.064222 | O72: 0.064199 | P72: 0.064191 | Q72: 0.064177 | R72: 0.064157 | S72: 0.064136 | T72: 0.064127 | U72: 0.06413 | V72: 0.064132 | W72: 0.064121 | X72: 0.0641 | Y72: 0.064069 | Z72: 0.064037 | AA72: 0.064006 | AB72: 0.063967 | AC72: 0.063922 | AD72: 0.063862 | AE72: 0.063796 | AF72: 0.063731 | AG72: 0
... A75: Total | B75: Transportation: Energy Use by Mode: Total: Alternative Transportation | C75: AEO.2025.ALTTRNP.CNSM_NA_TRN_NA_USE_NA_NA_MILLBPDYOEQ.A | D75: MMb/d oil eq | F75: 14.923069 | G75: 14.967827 | H75: 14.954769 | I75: 14.878322 | J75: 14.806329 | K75: 14.717354 | L75: 14.60704 | M75: 14.516214 | N75: 14.431001 | O75: 14.353938 | P75: 14.280197 | Q75: 14.201674 | R75: 14.11879 | S75: 14.047919 | T75: 13.996613 | U75: 13.939302 | V75: 13.898635 | W75: 13.860985 | X75: 13.819115 | Y75: 13.79618 | Z75: 13.765251 | AA75: 13.745568 | AB75: 13.723292 | AC75: 13.73004 | AD75: 13.720713 | AE75: 13.724433 | AF75: 13.747025 | AG75: -0.003
A76: Battery Prices (2024 dollars per nominal kWh)
A77: Light-Duty Vehicles
A78: Battery Electric Vehicles | B78: Transportation: Battery Prices: Light-Duty Battery Electric: Alternative Transportation | C78: AEO.2025.ALTTRNP.PRCE_NA_TRN_NA_BAT_LDV_NA_13YDKWH.A | D78: 2024 $/kWh RPE | F78: 196.04523 | G78: 171.4099 | H78: 162.35551 | I78: 154.32104 | J78: 148.64557 | K78: 144.48248 | L78: 141.27228 | M78: 138.77521 | N78: 136.61577 | O78: 134.6274 | P78: 133.02846 | Q78: 131.5237 | R78: 130.10266 | S78: 128.79533 | T78: 127.58627 | U78: 126.45885 | V78: 125.39216 | W78: 124.39598 | X78: 123.47098 | Y78: 122.61042 | Z78: 121.80572 | AA78: 121.05392 | AB78: 120.34687 | AC78: 119.6844 | AD78: 119.06255 | AE78: 118.47816 | AF78: 117.92687 | AG78: -0.019
A79: Plug-In Hybrid Electric Vehicles | B79: Transportation: Battery Prices: Light-Duty Plug-in Hybrid Electric: Alternative Transportation | C79: AEO.2025.ALTTRNP.PRCE_NA_TRN_NA_BAT_LDV_NA_13YDKWH.A | D79: 2024 $/kWh RPE | F79: 570.03552 | G79: 489.47833 | H79: 459.87057 | I79: 433.59802 | J79: 415.03928 | K79: 401.426 | L79: 390.92868 | M79: 382.76331 | N79: 375.70193 | O79: 369.19998 | P79: 363.9715 | Q79: 359.0509 | R79: 354.40418 | S79: 350.12924 | T79: 346.17563 | U79: 342.48895 | V79: 339.00088 | W79: 335.74341 | X79: 332.71866 | Y79: 329.9046 | Z79: 327.27328 | AA79: 324.81485 | AB79: 322.50284 | AC79: 320.33652 | AD79: 318.30307 | AE79: 316.39218 | AF79: 314.58951 | AG79: -0.023
A80: Hybrid Electric Vehicles | B80: Transportation: Battery Prices: Light-Duty Hybrid Electric: Alternative Transportation | C80: AEO.2025.ALTTRNP.PRCE_NA_TRN_NA_BAT_LDV_NA_13YDKWH.A | D80: 2024 $/kWh RPE | F80: 570.03552 | G80: 489.47833 | H80: 459.87057 | I80: 433.59802 | J80: 415.03928 | K80: 401.426 | L80: 390.92868 | M80: 382.76331 | N80: 375.70193 | O80: 369.19998 | P80: 363.9715 | Q80: 359.0509 | R80: 354.40418 | S80: 350.12924 | T80: 346.17563 | U80: 342.48895 | V80: 339.00088 | W80: 335.74341 | X80: 332.71866 | Y80: 329.9046 | Z80: 327.27328 | AA80: 324.81485 | AB80: 322.50284 | AC80: 320.33652 | AD80: 318.30307 | AE80: 316.39218 | AF80: 314.58951 | AG80: -0.023
A81: Freight Trucks
A82: Class 4 & 5 | B82: Transportation: Battery Prices: Freight Truck Class 4-5: Alternative Transportation | C82: AEO.2025.ALTTRNP.PRCE_NA_TRN_NA_BAT_FRTTRK_NA_13YDKWH.A | D82: 2024 $/kWh | F82: 336.87881 | G82: 307.29883 | H82: 288.80246 | I82: 271.077 | J82: 255.56863 | K82: 244.60071 | L82: 236.54897 | M82: 230.33711 | N82: 225.49472 | O82: 221.30664 | P82: 217.4583 | Q82: 214.35638 | R82: 211.43359 | S82: 208.67517 | T82: 206.13972 | U82: 203.79489 | V82: 201.60883 | W82: 199.54256 | X82: 197.6105 | Y82: 195.81801 | Z82: 194.15103 | AA82: 192.59424 | AB82: 191.14033 | AC82: 189.7733 | AD82: 188.49175 | AE82: 187.28937 | AF82: 186.15944 | AG82: -0.023
A83: Class 6-8 Vocational | B83: Transportation: Battery Prices: Freight Truck Class 6-8 Vocational: Alternative Transportation | C83: AEO.2025.ALTTRNP.PRCE_NA_TRN_NA_BAT_FRTTRK_NA_13YDKWH.A | D83: 2024 $/kWh | F83: 483.72339 | G83: 441.24963 | H83: 414.69074 | I83: 389.23874 | J83: 366.97034 | K83: 351.22153 | L83: 339.66006 | M83: 330.74048 | N83: 323.78732 | O83: 317.77362 | P83: 312.24777 | Q83: 307.79376 | R83: 303.59692 | S83: 299.6362 | T83: 295.99548 | U83: 292.62854 | V83: 289.48953 | W83: 286.52267 | X83: 283.74841 | Y83: 281.17456 | Z83: 278.78098 | AA83: 276.54559 | AB83: 274.45789 | AC83: 272.495 | AD83: 270.65482 | AE83: 268.92828 | AF83: 267.30588 | AG83: -0.023
A84: Class 7&8 Tractors | B84: Transportation: Battery Prices: Freight Truck Class 7&8 Tractor: Alternative Transportation | C84: AEO.2025.ALTTRNP.PRCE_NA_TRN_NA_BAT_FRTTRK_NA_13YDKWH.A | D84: 2024 $/kWh | F84: 362.79254 | G84: 330.93723 | H84: 311.01801 | I84: 291.92905 | J84: 275.22778 | K84: 263.41614 | L84: 254.74504 | M84: 248.05534 | N84: 242.84049 | O84: 238.3302 | P84: 234.18585 | Q84: 230.84532 | R84: 227.69771 | S84: 224.72713 | T84: 221.99663 | U84: 219.47142 | V84: 217.1172 | W84: 214.892 | X84: 212.81133 | Y84: 210.88094 | Z84: 209.08574 | AA84: 207.4092 | AB84: 205.84343 | AC84: 204.37125 | AD84: 202.9911 | AE84: 201.69624 | AF84: 200.4794 | AG84: -0.023
A85: Class 2b & 3 | B85: Transportation: Battery Prices: Freight Truck Class 2b&3: Alternative Transportation | C85: AEO.2025.ALTTRNP.PRCE_NA_TRN_NA_BAT_FRTTRK_NA_13YDKWH.A | D85: 2024 $/kWh | F85: 238.97354 | G85: 217.99026 | H85: 204.86937 | I85: 192.29535 | J85: 181.29411 | K85: 173.51375 | L85: 167.80203 | M85: 163.39551 | N85: 159.96042 | O85: 156.98949 | P85: 154.25957 | Q85: 152.05914 | R85: 149.98578 | S85: 148.02907 | T85: 146.23045 | U85: 144.56708 | V85: 143.01633 | W85: 141.5506 | X85: 140.18007 | Y85: 138.90848 | Z85: 137.72598 | AA85: 136.62163 | AB85: 135.59027 | AC85: 134.62053 | AD85: 133.71143 | AE85: 132.85846 | AF85: 132.05695 | AG85: -0.023
A86: Hybrid Electric Vehicles | B86: Transportation: Battery Prices: Freight Truck Gasoline Hybrid Electric: Alternative Transportation | C86: AEO.2025.ALTTRNP.PRCE_NA_TRN_NA_BAT_FRTTRK_NA_13YDKWH.A | D86: 2024 $/kWh | F86: 993.36047 | G86: 906.13757 | H86: 851.59699 | I86: 799.32953 | J86: 753.59985 | K86: 721.25848 | L86: 697.51624 | M86: 679.1991 | N86: 664.92035 | O86: 652.57074 | P86: 641.22315 | Q86: 632.07648 | R86: 623.45795 | S86: 615.32428 | T86: 607.8479 | U86: 600.93366 | V86: 594.48749 | W86: 588.39471 | X86: 582.69769 | Y86: 577.41205 | Z86: 572.49664 | AA86: 567.90607 | AB86: 563.6189 | AC86: 559.58795 | AD86: 555.80896 | AE86: 552.26349 | AF86: 548.93164 | AG86: -0.023
A87: Electricity Prices (2024 cents per kWh)
A88: Light Trains | B88: Transportation: Electricity Prices: Light Trains: Alternative Transportation | C88: AEO.2025.ALTTRNP.PRCE_NA_TRN_NA_ELC_LTRNS_NA_Y13DLRPMMBTU.A | D88: 2024 cents/kWh | F88: 14.660725 | G88: 14.47932 | H88: 13.539622 | I88: 12.501745 | J88: 12.45952 | K88: 12.533541 | L88: 12.655854 | M88: 12.79153 | N88: 12.88917 | O88: 13.116578 | P88: 13.132267 | Q88: 13.026171 | R88: 13.029432 | S88: 13.024822 | T88: 13.013798 | U88: 12.905737 | V88: 12.819233 | W88: 12.860767 | X88: 12.948478 | Y88: 13.121889 | Z88: 13.205758 | AA88: 13.272813 | AB88: 13.279309 | AC88: 13.341878 | AD88: 13.308397 | AE88: 13.32265 | AF88: 13.292919 | AG88: -0.004
A89: Light-Duty Vehicles | B89: Transportation: Electricity Prices: Light-Duty Vehicles: Alternative Transportation | C89: AEO.2025.ALTTRNP.PRCE_NA_TRN_NA_ELC_LDV_NA_Y13DLRPMMBTU.A | D89: 2024 cents/kWh | F89: 21.406419 | G89: 20.894677 | H89: 18.821585 | I89: 17.486322 | J89: 17.284581 | K89: 17.332429 | L89: 17.445575 | M89: 17.659478 | N89: 17.786637 | O89: 18.025981 | P89: 18.087261 | Q89: 18.058178 | R89: 18.077915 | S89: 18.038933 | T89: 18.008388 | U89: 17.904356 | V89: 17.860285 | W89: 17.921337 | X89: 18.047403 | Y89: 18.188304 | Z89: 18.28047 | AA89: 18.398088 | AB89: 18.47851 | AC89: 18.575383 | AD89: 18.601013 | AE89: 18.634261 | AF89: 18.651932 | AG89: -0.005
A90: Home | B90: Transportation: Electricity Prices: Light-Duty Vehicles Home: Alternative Transportation | C90: AEO.2025.ALTTRNP.PRCE_NA_TRN_NA_ELC_LDV_NA_Y13DLRPMMBTU.A | D90: 2024 cents/kWh | F90: 18.915469 | G90: 18.494361 | H90: 16.748058 | I90: 15.598786 | J90: 15.387491 | K90: 15.411831 | L90: 15.48303 | M90: 15.651556 | N90: 15.761011 | O90: 15.963941 | P90: 16.044131 | Q90: 16.044027 | R90: 16.074539 | S90: 16.049256 | T90: 16.027717 | U90: 15.944241 | V90: 15.890953 | W90: 15.949241 | X90: 16.076356 | Y90: 16.220197 | Z90: 16.330137 | AA90: 16.446975 | AB90: 16.533956 | AC90: 16.647703 | AD90: 16.695798 | AE90: 16.747364 | AF90: 16.7914 | AG90: -0.005
A91: Public Level 2 | B91: Transportation: Electricity Prices: Light-Duty Vehicles Public Level 2: Alternative Transportation | C91: AEO.2025.ALTTRNP.PRCE_NA_TRN_NA_ELC_LDV_NA_Y13DLRPMMBTU.A | D91: 2024 cents/kWh | F91: 24.560234 | G91: 23.65334 | H91: 20.961617 | I91: 19.246886 | J91: 18.991436 | K91: 18.994349 | L91: 19.096301 | M91: 19.288596 | N91: 19.346433 | O91: 19.542026 | P91: 19.505563 | Q91: 19.382212 | R91: 19.341442 | S91: 19.236585 | T91: 19.152076 | U91: 18.98241 | V91: 18.923145 | W91: 18.947121 | X91: 19.024059 | Y91: 19.112776 | Z91: 19.133858 | AA91: 19.210448 | AB91: 19.242525 | AC91: 19.275586 | AD91: 19.235342 | AE91: 19.213842 | AF91: 19.162221 | AG91: -0.01
A92: Public DC Fast Charge | B92: Transportation: Electricity Prices: Light-Duty Vehicles Public DCFC: Alternative Transportation | C92: AEO.2025.ALTTRNP.PRCE_NA_TRN_NA_ELC_LDV_NA_Y13DLRPMMBTU.A | D92: 2024 cents/kWh | F92: 32.392368 | G92: 31.175576 | H92: 27.621338 | I92: 25.355183 | J92: 25.018739 | K92: 25.021774 | L92: 25.15715 | M92: 25.409142 | N92: 25.478199 | O92: 25.725658 | P92: 25.6675 | Q92: 25.497035 | R92: 25.434052 | S92: 25.300881 | T92: 25.193921 | U92: 24.978706 | V92: 24.923964 | W92: 24.95951 | X92: 25.053393 | Y92: 25.160581 | Z92: 25.174086 | AA92: 25.273709 | AB92: 25.316188 | AC92: 25.346585 | AD92: 25.289458 | AE92: 25.253148 | AF92: 25.178396 | AG92: -0.01
A93: Bus | B93: Transportation: Electricity Prices: Bus: Alternative Transportation | C93: AEO.2025.ALTTRNP.PRCE_NA_TRN_NA_ELC_BUS_NA_Y13DLRPMMBTU.A | D93: 2024 cents/kWh | F93: 17.499978 | G93: 16.868295 | H93: 14.858658 | I93: 13.690975 | J93: 13.510317 | K93: 13.550777 | L93: 13.650695 | M93: 13.814606 | N93: 13.887226 | O93: 14.057883 | P93: 14.094117 | Q93: 14.088541 | R93: 14.142582 | S93: 14.072425 | T93: 14.010379 | U93: 13.850702 | V93: 13.739597 | W93: 13.741968 | X93: 13.801117 | Y93: 13.910145 | Z93: 13.958562 | AA93: 14.029274 | AB93: 14.033215 | AC93: 14.086241 | AD93: 14.057613 | AE93: 14.07015 | AF93: 14.052716 | AG93: -0.008
A94: School | B94: Transportation: Electricity Prices: School Bus: Alternative Transportation | C94: AEO.2025.ALTTRNP.PRCE_NA_TRN_NA_ELC_BUS_NA_Y13DLRPMMBTU.A | D94: 2024 cents/kWh | F94: 17.109795 | G94: 16.165377 | H94: 14.333702 | I94: 13.116031 | J94: 12.958225 | K94: 12.986747 | L94: 13.08336 | M94: 13.197463 | N94: 13.25392 | O94: 13.438112 | P94: 13.430469 | Q94: 13.314503 | R94: 13.323175 | S94: 13.323256 | T94: 13.299072 | U94: 13.205408 | V94: 13.172117 | W94: 13.215064 | X94: 13.264645 | Y94: 13.397519 | Z94: 13.428667 | AA94: 13.513114 | AB94: 13.536572 | AC94: 13.570066 | AD94: 13.520778 | AE94: 13.50327 | AF94: 13.441691 | AG94: -0.009
A95: Transit | B95: Transportation: Electricity Prices: Transit Bus: Alternative Transportation | C95: AEO.2025.ALTTRNP.PRCE_NA_TRN_NA_ELC_BUS_NA_Y13DLRPMMBTU.A | D95: 2024 cents/kWh | F95: 17.561289 | G95: 17.02472 | H95: 14.998709 | I95: 13.865488 | J95: 13.694797 | K95: 13.753669 | L95: 13.866458 | M95: 14.061038 | N95: 14.151945 | O95: 14.327889 | P95: 14.392894 | Q95: 14.448506 | R95: 14.535325 | S95: 14.441809 | T95: 14.369105 | U95: 14.182898 | V95: 14.037636 | W95: 14.023992 | X95: 14.093598 | Y95: 14.194002 | Z95: 14.256455 | AA95: 14.322983 | AB95: 14.319469 | AC95: 14.387855 | AD95: 14.374875 | AE95: 14.408455 | AF95: 14.418906 | AG95: -0.008
A96: Intercity | B96: Transportation: Electricity Prices: Intercity Bus: Alternative Transportation | C96: AEO.2025.ALTTRNP.PRCE_NA_TRN_NA_ELC_BUS_NA_Y13DLRPMMBTU.A | D96: 2024 cents/kWh | F96: 12.941013 | G96: 12.624144 | H96: 11.719846 | I96: 11.091652 | J96: 11.041523 | K96: 11.135455 | L96: 11.261929 | M96: 11.467452 | N96: 11.591284 | O96: 11.827546 | P96: 11.914558 | Q96: 11.840053 | R96: 11.800545 | S96: 11.73856 | T96: 11.673352 | U96: 11.557298 | V96: 11.491102 | W96: 11.510795 | X96: 11.566348 | Y96: 11.638818 | Z96: 11.67062 | AA96: 11.73199 | AB96: 11.780459 | AC96: 11.801879 | AD96: 11.767419 | AE96: 11.73159 | AF96: 11.686546 | AG96: -0.004
A97: Freight truck | B97: Transportation: Electricity Prices: Freight Truck: Alternative Transportation | C97: AEO.2025.ALTTRNP.PRCE_NA_TRN_NA_ELC_FRTTRK_NA_Y13DLRPMMBTU.A | D97: 2024 cents/kWh | F97: 18.39276 | G97: 17.9644 | H97: 16.773347 | I97: 15.913227 | J97: 15.843658 | K97: 15.975295 | L97: 16.123283 | M97: 16.242621 | N97: 16.119142 | O97: 16.181033 | P97: 15.929745 | Q97: 15.355148 | R97: 14.820856 | S97: 14.332749 | T97: 13.900952 | U97: 13.469419 | V97: 13.144062 | W97: 12.936471 | X97: 12.805147 | Y97: 12.721908 | Z97: 12.632145 | AA97: 12.598369 | AB97: 12.569184 | AC97: 12.521887 | AD97: 12.426758 | AE97: 12.339561 | AF97: 12.250221 | AG97: -0.016
A98: Depot | B98: Transportation: Electricity Prices: Freight Truck Depot: Alternative Transportation | C98: AEO.2025.ALTTRNP.PRCE_NA_TRN_NA_ELC_FRTTRK_NA_Y13DLRPMMBTU.A | D98: 2024 cents/kWh | F98: 12.941013 | G98: 12.624144 | H98: 11.719846 | I98: 11.091652 | J98: 11.041523 | K98: 11.135455 | L98: 11.261929 | M98: 11.467452 | N98: 11.591284 | O98: 11.827546 | P98: 11.914558 | Q98: 11.840053 | R98: 11.800545 | S98: 11.73856 | T98: 11.673352 | U98: 11.557298 | V98: 11.491102 | W98: 11.510795 | X98: 11.566348 | Y98: 11.638818 | Z98: 11.67062 | AA98: 11.73199 | AB98: 11.780459 | AC98: 11.801879 | AD98: 11.767419 | AE98: 11.73159 | AF98: 11.686546 | AG98: -0.004
A99: Public/Retail | B99: Transportation: Electricity Prices: Freight Truck Public/Retail: Alternative Transportation | C99: AEO.2025.ALTTRNP.PRCE_NA_TRN_NA_ELC_FRTTRK_NA_Y13DLRPMMBTU.A | D99: 2024 cents/kWh | F99: 24.149309 | G99: 23.538984 | H99: 22.020655 | I99: 20.899756 | J99: 20.810403 | K99: 21.018689 | L99: 21.265513 | M99: 21.630918 | N99: 21.821585 | O99: 22.191971 | P99: 22.233132 | Q99: 21.968354 | R99: 21.82507 | S99: 21.729992 | T99: 21.668022 | U99: 21.554519 | V99: 21.546307 | W99: 21.653545 | X99: 21.818481 | Y99: 21.973881 | Z99: 22.062764 | AA99: 22.223499 | AB99: 22.378456 | AC99: 22.459212 | AD99: 22.427599 | AE99: 22.37236 | AF99: 22.297429 | AG99: -0.003
A100: Commercial light truck
A101: Depot | B101: Transportation: Electricity Prices: Commercial Light Truck Depot: Alternative Transportation | C101: AEO.2025.ALTTRNP.PRCE_NA_TRN_NA_ELC_CLT_NA_Y13DLRPMMBTU.A | D101: 2024 cents/kWh | F101: 12.941013 | G101: 12.624144 | H101: 11.719846 | I101: 11.091652 | J101: 11.041523 | K101: 11.135455 | L101: 11.261929 | M101: 11.467452 | N101: 11.591284 | O101: 11.827546 | P101: 11.914558 | Q101: 11.840053 | R101: 11.800545 | S101: 11.73856 | T101: 11.673352 | U101: 11.557298 | V101: 11.491102 | W101: 11.510795 | X101: 11.566348 | Y101: 11.638818 | Z101: 11.67062 | AA101: 11.73199 | AB101: 11.780459 | AC101: 11.801879 | AD101: 11.767419 | AE101: 11.73159 | AF101: 11.686546 | AG101: -0.004
A102: Public/Retail | B102: Transportation: Electricity Prices: Commercial Light Truck Public/Retail: Alternative Transportation | C102: AEO.2025.ALTTRNP.PRCE_NA_TRN_NA_ELC_CLT_NA_Y13DLRPMMBTU.A | D102: 2024 cents/kWh | F102: 24.149309 | G102: 23.538984 | H102: 22.020655 | I102: 20.899756 | J102: 20.810403 | K102: 21.018689 | L102: 21.265513 | M102: 21.630918 | N102: 21.821585 | O102: 22.191971 | P102: 22.233132 | Q102: 21.968354 | R102: 21.82507 | S102: 21.729992 | T102: 21.668022 | U102: 21.554519 | V102: 21.546307 | W102: 21.653545 | X102: 21.818481 | Y102: 21.973881 | Z102: 22.062764 | AA102: 22.223499 | AB102: 22.378456 | AC102: 22.459212 | AD102: 22.427599 | AE102: 22.37236 | AF102: 22.297429 | AG102: -0.003
A103: Hydrogen Price (2024 dollars per kg) | B103: Transportation: Hydrogen Price: Delivered: Alternative Transportation | C103: AEO.2025.ALTTRNP.PRCE_NA_TRN_NA_HDG_NA_NA_NA.A | D103: 2024 $/kg | F103: 8.231517 | G103: 8.356859 | H103: 8.318288 | I103: 8.29093 | J103: 8.307778 | K103: 8.337455 | L103: 8.375732 | M103: 8.402835 | N103: 8.464133 | O103: 8.495932 | P103: 8.540318 | Q103: 8.527973 | R103: 8.505517 | S103: 8.488868 | T103: 8.483689 | U103: 8.47639 | V103: 8.484052 | W103: 8.50936 | X103: 8.535672 | Y103: 8.548611 | Z103: 8.557114 | AA103: 8.560738 | AB103: 8.56083 | AC103: 8.554235 | AD103: 8.551289 | AE103: 8.548012 | AF103: 8.546188 | AG103: 0.001
A104: Natural Gas Prices (2024 dollars per mmBtu)
A105: Compressed Natural Gas
A106: Freight Trucks | B106: Transportation: Natural Gas Prices: Compressed: Vehicles: Alternative Transportation | C106: AEO.2025.ALTTRNP.PRCE_NA_TRN_NA_CNG_LDTVHFT_NA_Y13DLRPMMBTU.A | D106: 2024 $/MMBtu | F106: 17.766323 | G106: 17.970211 | H106: 17.959671 | I106: 17.85622 | J106: 17.812986 | K106: 17.876345 | L106: 17.945992 | M106: 17.996149 | N106: 18.214977 | O106: 18.394098 | P106: 18.492506 | Q106: 19.302898 | R106: 19.313524 | S106: 19.199713 | T106: 19.099436 | U106: 19.006401 | V106: 18.972618 | W106: 19.015932 | X106: 19.059195 | Y106: 19.089003 | Z106: 19.078463 | AA106: 19.073223 | AB106: 19.035549 | AC106: 18.976643 | AD106: 18.914948 | AE106: 18.991774 | AF106: 18.961599 | AG106: 0.003
A107: Public/Retail | B107: Transportation: Natural Gas Prices: Compressed: Vehicles: Public/Retail: Alternative Transportation | C107: AEO.2025.ALTTRNP.PRCE_NA_TRN_NA_CNG_NFLEET_NA_Y13DLRPMMBTU.A | D107: 2024 $/MMBtu | F107: 19.777599 | G107: 19.960829 | H107: 19.863552 | I107: 19.700586 | J107: 19.63954 | K107: 19.690779 | L107: 19.757977 | M107: 19.798512 | N107: 20.007479 | O107: 20.204947 | P107: 20.307543 | Q107: 20.827049 | R107: 20.821226 | S107: 20.723356 | T107: 20.637676 | U107: 20.552267 | V107: 20.518707 | W107: 20.559086 | X107: 20.594023 | Y107: 20.61274 | Z107: 20.589821 | AA107: 20.572636 | AB107: 20.518938 | AC107: 20.441103 | AD107: 20.358809 | AE107: 20.404718 | AF107: 20.358135 | AG107: 0.001
...

Sheet AEO 2022 Table 7
B1: highogs.d120120a | C1: 2021 | D1: 2022 | E1: 2023 | F1: 2024 | G1: 2025 | H1: 2026 | I1: 2027 | J1: 2028 | K1: 2029 | L1: 2030 | M1: 2031 | N1: 2032 | O1: 2033 | P1: 2034 | Q1: 2035 | R1: 2036 | S1: 2037 | T1: 2038 | U1: 2039 | V1: 2040 | W1: 2041 | X1: 2042 | Y1: 2043 | Z1: 2044 | AA1: 2045 | AB1: 2046 | AC1: 2047 | AD1: 2048 | AE1: 2049 | AF1: 2050
C3: Annual Energy Outlook 2021
C4: ref2021 | F4: Reference case
C5: d113020a
D6: January 2021
A10: TKI000 | B10: 7. Transportation Sector Key Indicators and Delivered Energy Consumption | AG10: Compound
AG11: Growth
AG12: 2020-2050
B13: Key Indicators and Consumption | C13: 2021 | D13: 2022 | E13: 2023 | F13: 2024 | G13: 2025 | H13: 2026 | I13: 2027 | J13: 2028 | K13: 2029 | L13: 2030 | M13: 2031 | N13: 2032 | O13: 2033 | P13: 2034 | Q13: 2035 | R13: 2036 | S13: 2037 | T13: 2038 | U13: 2039 | V13: 2040 | W13: 2041 | X13: 2042 | Y13: 2043 | Z13: 2044 | AA13: 2045 | AB13: 2046 | AC13: 2047 | AD13: 2048 | AE13: 2049 | AF13: 2050 | AG13: (percent)
B15: Key Indicators
B16: Travel Indicators
B17: (billion vehicle miles traveled)
A18: TKI000:ba_Light-DutyVeh | B18: Light-Duty Vehicles less than 8,501 pounds | C18: 2761.1487 | D18: 2887.3313 | E18: 2986.1375 | F18: 3033.4624 | G18: 3075.9688 | H18: 3112.4636 | I18: 3140.5366 | J18: 3162.593 | K18: 3183.811 | L18: 3206.8018 | M18: 3229.7073 | N18: 3247.4204 | O18: 3266.4207 | P18: 3283.7412 | Q18: 3299.2346 | R18: 3314.6108 | S18: 3331.2617 | T18: 3348.0293 | U18: 3367.125 | V18: 3386.949 | W18: 3405.9556 | X18: 3425.8684 | Y18: 3445.7124 | Z18: 3465.4507 | AA18: 3486.7061 | AB18: 3510.4651 | AC18: 3534.4812 | AD18: 3558.8704 | AE18: 3584.9614 | AF18: 3613.5239 | AG18: 0.009
A19: TKI000:ba_CommercialLig | B19: Commercial Light Trucks 1/ | C19: 100.76003 | D19: 104.34176 | E19: 106.70262 | F19: 108.00214 | G19: 109.34573 | H19: 110.56496 | I19: 111.42751 | J19: 112.36408 | K19: 113.47929 | L19: 114.62598 | M19: 115.78786 | N19: 117.00378 | O19: 118.26071 | P19: 119.48289 | Q19: 120.7066 | R19: 121.99136 | S19: 123.41512 | T19: 124.85188 | U19: 126.28014 | V19: 127.69122 | W19: 129.20485 | X19: 130.79395 | Y19: 132.42688 | Z19: 134.00609 | AA19: 135.59607 | AB19: 137.31485 | AC19: 138.90479 | AD19: 140.36012 | AE19: 142.02193 | AF19: 144.02313 | AG19: 0.012
A20: TKI000:ba_FreightTrucks | B20: Freight Trucks greater than 10,000 pounds | C20: 296.81839 | D20: 304.25449 | E20: 308.97504 | F20: 312.70242 | G20: 316.88568 | H20: 320.48059 | I20: 323.30453 | J20: 326.69177 | K20: 330.38946 | L20: 333.86133 | M20: 337.28406 | N20: 340.79715 | O20: 344.26349 | P20: 347.5257 | Q20: 350.95914 | R20: 354.45807 | S20: 358.38226 | T20: 362.35556 | U20: 366.2616 | V20: 370.20163 | W20: 374.51642 | X20: 379.08896 | Y20: 383.45093 | Z20: 387.78918 | AA20: 392.14526 | AB20: 396.80841 | AC20: 400.81616 | AD20: 404.24228 | AE20: 408.71432 | AF20: 414.21069 | AG20: 0.012
B21: (billion passenger miles traveled)
A22: TKI000:buspassmiles | B22: Bus Transportation | C22: 151.30966 | D22: 173.16789 | E22: 184.76592 | F22: 191.65541 | G22: 196.21399 | H22: 199.3981 | I22: 201.69253 | J22: 203.40639 | K22: 204.7121 | L22: 205.76692 | M22: 206.62942 | N22: 207.27484 | O22: 207.8185 | P22: 208.29555 | Q22: 208.67419 | R22: 209.06363 | S22: 209.5192 | T22: 209.89679 | U22: 210.00269 | V22: 210.10393 | W22: 210.12295 | X22: 210.09636 | Y22: 210.06598 | Z22: 210.01566 | AA22: 209.94398 | AB22: 209.88408 | AC22: 209.77901 | AD22: 209.63933 | AE22: 209.48929 | AF22: 209.347 | AG22: 0.011
A23: TKI000:railpassmiles | B23: Passenger Rail | C23: 29.706352 | D23: 33.420921 | E23: 35.774769 | F23: 37.825356 | G23: 39.433685 | H23: 40.788967 | I23: 41.767357 | J23: 42.560257 | K23: 43.304031 | L23: 44.145664 | M23: 44.963547 | N23: 45.652962 | O23: 46.319397 | P23: 46.919537 | Q23: 47.423344 | R23: 47.944431 | S23: 48.515842 | T23: 49.068516 | U23: 49.548981 | V23: 50.127491 | W23: 50.601322 | X23: 51.080406 | Y23: 51.618813 | Z23: 52.163063 | AA23: 52.755924 | AB23: 53.42416 | AC23: 53.984158 | AD23: 54.50843 | AE23: 55.108772 | AF23: 55.777504 | AG23: 0.022
B24: (billion seat miles available)
A25: TKI000:ba_Air | B25: Air | C25: 884.81805 | D25: 1076.55 | E25: 1230.1667 | F25: 1281.0972 | G25: 1332.4701 | H25: 1370.9828 | I25: 1398.9177 | J25: 1427.2495 | K25: 1459.7749 | L25: 1496.7294 | M25: 1531.1088 | N25: 1567.3237 | O25: 1606.1002 | P25: 1644.3704 | Q25: 1681.6504 | R25: 1717.8458 | S25: 1756.6516 | T25: 1794.5098 | U25: 1835.0491 | V25: 1878.3563 | W25: 1916.7485 | X25: 1957.8833 | Y25: 2001.3043 | Z25: 2045.0242 | AA25: 2092.8052 | AB25: 2142.4402 | AC25: 2188.459 | AD25: 2235.0183 | AE25: 2287.7986 | AF25: 2344.385 | AG25: 0.034
B26: (billion ton miles traveled)
A27: TKI000:ba_Rail | B27: Rail | C27: 1644.4915 | D27: 1665.1613 | E27: 1687.2128 | F27: 1584.5679 | G27: 1618.0447 | H27: 1660.0645 | I27: 1667.3862 | J27: 1673.5901 | K27: 1678.8776 | L27: 1688.5286 | M27: 1699.8828 | N27: 1711.3606 | O27: 1724.6821 | P27: 1718.1174 | Q27: 1722.3843 | R27: 1715.6056 | S27: 1728.4023 | T27: 1737.8145 | U27: 1747.3446 | V27: 1754.1726 | W27: 1763.5247 | X27: 1775.6241 | Y27: 1781.4792 | Z27: 1785.2306 | AA27: 1792.4877 | AB27: 1803.1855 | AC27: 1810.229 | AD27: 1819.6707 | AE27: 1831.4158 | AF27: 1852.35 | AG27: 0.004
A28: TKI000:ba_DomesticShipp | B28: Domestic Shipping | C28: 340.48685 | D28: 355.078 | E28: 354.80612 | F28: 347.34994 | G28: 340.59833 | H28: 332.84692 | I28: 323.82996 | J28: 315.29077 | K28: 306.4082 | L28: 297.53073 | M28: 293.53958 | N28: 289.49127 | O28: 285.82245 | P28: 281.63907 | Q28: 277.23456 | R28: 273.04852 | S28: 269.29669 | T28: 265.319 | U28: 261.74301 | V28: 258.02158 | W28: 257.14194 | X28: 256.13333 | Y28: 254.95567 | Z28: 253.95633 | AA28: 252.95215 | AB28: 252.08273 | AC28: 250.62955 | AD28: 248.75684 | AE28: 247.7997 | AF28: 247.80908 | AG28: -0.011
B30: Energy Efficiency Indicators
B31: (miles per gallon)
A32: TKI000:ca_AvgCAFEStand | B32: New Light-Duty Vehicle CAFE Standard 2/ | C32: 35.285992 | D32: 35.48703 | E32: 35.771912 | F32: 36.135601 | G32: 36.515312 | H32: 37.058449 | I32: 37.01659 | J32: 36.995026 | K32: 36.98127 | L32: 36.99622 | M32: 37.031643 | N32: 37.041542 | O32: 37.047226 | P32: 37.049618 | Q32: 37.040478 | R32: 37.033859 | S32: 37.025627 | T32: 37.023102 | U32: 37.003475 | V32: 36.994915 | W32: 36.983158 | X32: 36.964703 | Y32: 36.957966 | Z32: 36.952953 | AA32: 36.939468 | AB32: 36.932568 | AC32: 36.915142 | AD32: 36.891186 | AE32: 36.867813 | AF32: 36.844318 | AG32: 0.001
A33: TKI000:ca_CarCAFEStand | B33: New Car 2/ | C33: 44.288506 | D33: 44.826138 | E33: 45.45166 | F33: 46.205555 | G33: 46.881027 | H33: 47.673538 | I33: 47.678375 | J33: 47.68045 | K33: 47.684368 | L33: 47.699383 | M33: 47.710827 | N33: 47.710827 | O33: 47.710827 | P33: 47.710827 | Q33: 47.710827 | R33: 47.710827 | S33: 47.711578 | T33: 47.714207 | U33: 47.714207 | V33: 47.715466 | W33: 47.715603 | X33: 47.715603 | Y33: 47.71888 | Z33: 47.719818 | AA33: 47.719818 | AB33: 47.721157 | AC33: 47.721157 | AD33: 47.721157 | AE33: 47.721157 | AF33: 47.721333 | AG33: 0.003
A34: TKI000:ca_TwukCAFEStand | B34: New Light Truck 2/ | C34: 31.772453 | D34: 32.124016 | E34: 32.563663 | F34: 33.014378 | G34: 33.490173 | H34: 34.05373 | I34: 34.053749 | J34: 34.053802 | K34: 34.053837 | L34: 34.053837 | M34: 34.053837 | N34: 34.053913 | O34: 34.053944 | P34: 34.053978 | Q34: 34.054016 | R34: 34.054024 | S34: 34.054043 | T34: 34.054043 | U34: 34.054092 | V34: 34.054092 | W34: 34.054096 | X34: 34.054131 | Y34: 34.054131 | Z34: 34.054131 | AA34: 34.054165 | AB34: 34.054165 | AC34: 34.054195 | AD34: 34.054214 | AE34: 34.054226 | AF34: 34.054241 | AG34: 0.002
A35: TKI000:ca_NewVehCred | B35: Compliance New Light-Duty Vehicle 3/ | C35: 36.320473 | D35: 37.31142 | E35: 37.662174 | F35: 38.010811 | G35: 38.094296 | H35: 38.247921 | I35: 38.293079 | J35: 38.352066 | K35: 38.418518 | L35: 38.54631 | M35: 38.726295 | N35: 38.866302 | O35: 38.983082 | P35: 39.093426 | Q35: 39.1922 | R35: 39.302681 | S35: 39.416943 | T35: 39.533672 | U35: 39.591755 | V35: 39.675838 | W35: 39.750217 | X35: 39.796734 | Y35: 39.879173 | Z35: 39.96608 | AA35: 40.016975 | AB35: 40.087498 | AC35: 40.122173 | AD35: 40.129021 | AE35: 40.139771 | AF35: 40.152401 | AG35: 0.003
A36: TKI000:ca_NewCarCred | B36: New Car 3/ | C36: 45.475075 | D36: 46.463356 | E36: 46.871098 | F36: 47.613346 | G36: 48.15469 | H36: 48.952316 | I36: 49.009914 | J36: 48.983555 | K36: 49.005871 | L36: 49.1185 | M36: 49.276249 | N36: 49.423874 | O36: 49.562927 | P36: 49.715073 | Q36: 49.873493 | R36: 50.02845 | S36: 50.20089 | T36: 50.381207 | U36: 50.512337 | V36: 50.639797 | W36: 50.785503 | X36: 50.896545 | Y36: 51.036186 | Z36: 51.184166 | AA36: 51.303078 | AB36: 51.434132 | AC36: 51.549774 | AD36: 51.631973 | AE36: 51.718174 | AF36: 51.811989 | AG36: 0.005
A37: TKI000:ca_NewTwukCred | B37: New Light Truck 3/ | C37: 32.735344 | D37: 33.951099 | E37: 34.524212 | F37: 34.952869 | G37: 35.098633 | H37: 35.197926 | I37: 35.290627 | J37: 35.391632 | K37: 35.482613 | L37: 35.596081 | M37: 35.737183 | N37: 35.860985 | O37: 35.963947 | P37: 36.060459 | Q37: 36.155796 | R37: 36.262741 | S37: 36.372746 | T37: 36.4776 | U37: 36.543522 | V37: 36.62775 | W37: 36.700649 | X37: 36.755989 | Y37: 36.834328 | Z37: 36.913742 | AA37: 36.966965 | AB37: 37.033054 | AC37: 37.073078 | AD37: 37.095291 | AE37: 37.1208 | AF37: 37.147499 | AG37: 0.004
A38: TKI000:ca_TestedNewVeh | B38: Tested New Light-Duty Vehicle 4/ | C38: 36.097652 | D38: 36.890865 | E38: 37.16309 | F38: 37.471909 | G38: 37.548306 | H38: 37.693558 | I38: 37.730827 | J38: 37.779949 | K38: 37.82983 | L38: 37.92981 | M38: 38.074917 | N38: 38.1805 | O38: 38.265446 | P38: 38.343956 | Q38: 38.411659 | R38: 38.491077 | S38: 38.574333 | T38: 38.658054 | U38: 38.691067 | V38: 38.74736 | W38: 38.795506 | X38: 38.81963 | Y38: 38.873913 | Z38: 38.931656 | AA38: 38.959419 | AB38: 39.003712 | AC38: 39.018578 | AD38: 39.010792 | AE38: 39.006245 | AF38: 39.002537 | AG38: 0.003
A39: TKI000:ca_TestedNewCar | B39: New Car 4/ | C39: 45.096481 | D39: 45.979137 | E39: 46.313679 | F39: 46.990833 | G39: 47.515671 | H39: 48.291649 | I39: 48.344982 | J39: 48.315689 | K39: 48.322018 | L39: 48.394592 | M39: 48.506691 | N39: 48.606041 | O39: 48.697697 | P39: 48.801441 | Q39: 48.908657 | R39: 49.014748 | S39: 49.136864 | T39: 49.263721 | U39: 49.347969 | V39: 49.429173 | W39: 49.526897 | X39: 49.593983 | Y39: 49.683327 | Z39: 49.77837 | AA39: 49.849922 | AB39: 49.930515 | AC39: 50.000229 | AD39: 50.043533 | AE39: 50.089653 | AF39: 50.139729 | AG39: 0.004
A40: TKI000:ca_TestedNewTwuk | B40: New Light Truck 4/ | C40: 32.562687 | D40: 33.557835 | E40: 34.050751 | F40: 34.445057 | G40: 34.584492 | H40: 34.677776 | I40: 34.761444 | J40: 34.851055 | K40: 34.925472 | L40: 35.014309 | M40: 35.12392 | N40: 35.217022 | O40: 35.292133 | P40: 35.36097 | Q40: 35.429878 | R40: 35.509933 | S40: 35.593349 | T40: 35.669994 | U40: 35.715256 | V40: 35.775749 | W40: 35.826942 | X40: 35.864029 | Y40: 35.918907 | Z40: 35.974251 | AA40: 36.00901 | AB40: 36.053822 | AC40: 36.07869 | AD40: 36.090065 | AE40: 36.104107 | AF40: 36.118683 | AG40: 0.004
A41: TKI000:ca_OnRoadNewVeh | B41: On-Road New Light-Duty Vehicle 5/ | C41: 29.44529 | D41: 30.091688 | E41: 30.313065 | F41: 30.564369 | G41: 30.626116 | H41: 30.744225 | I41: 30.774488 | J41: 30.814499 | K41: 30.85515 | L41: 30.93675 | M41: 31.055231 | N41: 31.141388 | O41: 31.210691 | P41: 31.274731 | Q41: 31.329922 | R41: 31.394674 | S41: 31.462549 | T41: 31.530819 | U41: 31.557674 | V41: 31.603556 | W41: 31.642776 | X41: 31.662386 | Y41: 31.706629 | Z41: 31.753708 | AA41: 31.776299 | AB41: 31.812397 | AC41: 31.824455 | AD41: 31.818008 | AE41: 31.814219 | AF41: 31.8111 | AG41: 0.003
A42: TKI000:ca_OnRoadNewCar | B42: New Car 5/ | C42: 36.82645 | D42: 37.547241 | E42: 37.820435 | F42: 38.373409 | G42: 38.801998 | H42: 39.435673 | I42: 39.479225 | J42: 39.455303 | K42: 39.460472 | L42: 39.519737 | M42: 39.611279 | N42: 39.69241 | O42: 39.767258 | P42: 39.851978 | Q42: 39.939529 | R42: 40.026165 | S42: 40.125889 | T42: 40.229481 | U42: 40.298279 | V42: 40.36459 | W42: 40.444393 | X42: 40.499176 | Y42: 40.572136 | Z42: 40.64975 | AA42: 40.708183 | AB42: 40.773994 | AC42: 40.830925 | AD42: 40.866287 | AE42: 40.90395 | AF42: 40.944843 | AG42: 0.004
A43: TKI000:ca_OnRoadNewTwuk | B43: New Light Truck 5/ | C43: 26.550249 | D43: 27.36165 | E43: 27.763554 | F43: 28.085054 | G43: 28.198744 | H43: 28.274803 | I43: 28.343023 | J43: 28.416088 | K43: 28.476765 | L43: 28.549198 | M43: 28.638571 | N43: 28.714481 | O43: 28.775724 | P43: 28.83185 | Q43: 28.888037 | R43: 28.95331 | S43: 29.021324 | T43: 29.083817 | U43: 29.120722 | V43: 29.170044 | W43: 29.211786 | X43: 29.242025 | Y43: 29.28677 | Z43: 29.331894 | AA43: 29.360237 | AB43: 29.396774 | AC43: 29.417049 | AD43: 29.426325 | AE43: 29.437775 | AF43: 29.449659 | AG43: 0.004
... A47: TKI000:ca_FreightTruck | B47: Freight Truck | C47: 7.331892 | D47: 7.410312 | E47: 7.497923 | F47: 7.5963 | G47: 7.70782 | H47: 7.832913 | I47: 7.97052 | J47: 8.109589 | K47: 8.254834 | L47: 8.403061 | M47: 8.551556 | N47: 8.69581 | O47: 8.830752 | P47: 8.955747 | Q47: 9.070722 | R47: 9.177202 | S47: 9.275028 | T47: 9.363853 | U47: 9.444804 | V47: 9.51915 | W47: 9.58819 | X47: 9.649012 | Y47: 9.704254 | Z47: 9.754515 | AA47: 9.801952 | AB47: 9.848245 | AC47: 9.894052 | AD47: 9.940031 | AE47: 9.985973 | AF47: 10.031261 | AG47: 0.011
B48: (seat miles per gallon)
A49: TKI000:ca_Aircraft | B49: Aircraft | C49: 73.643883 | D49: 74.164284 | E49: 74.683517 | F49: 75.120308 | G49: 75.583763 | H49: 75.871498 | I49: 76.308502 | J49: 76.801476 | K49: 77.308174 | L49: 77.856262 | M49: 78.434464 | N49: 79.126999 | O49: 79.792549 | P49: 80.511719 | Q49: 81.242912 | R49: 81.987068 | S49: 82.759789 | T49: 83.544899 | U49: 84.319893 | V49: 85.114548 | W49: 85.926819 | X49: 86.77433 | Y49: 87.609406 | Z49: 88.41713 | AA49: 89.23912 | AB49: 90.056198 | AC49: 90.860878 | AD49: 91.651962 | AE49: 92.4216 | AF49: 93.179382 | AG49: 0.008
B50: (ton miles/thousand Btu)
A51: TKI000:ca_Rail | B51: Rail | C51: 3.512003 | D51: 3.534782 | E51: 3.55771 | F51: 3.580785 | G51: 3.60401 | H51: 3.627386 | I51: 3.650914 | J51: 3.674594 | K51: 3.698428 | L51: 3.722416 | M51: 3.74656 | N51: 3.77086 | O51: 3.795318 | P51: 3.819935 | Q51: 3.844712 | R51: 3.869649 | S51: 3.894748 | T51: 3.920009 | U51: 3.945435 | V51: 3.971025 | W51: 3.996782 | X51: 4.022705 | Y51: 4.048797 | Z51: 4.075058 | AA51: 4.101489 | AB51: 4.128091 | AC51: 4.154866 | AD51: 4.181815 | AE51: 4.208939 | AF51: 4.236238 | AG51: 0.006
A52: TKI000:ca_DomesticShipp | B52: Domestic Shipping | C52: 4.870726 | D52: 4.899663 | E52: 4.928772 | F52: 4.958054 | G52: 4.987509 | H52: 5.01714 | I52: 5.046947 | J52: 5.076931 | K52: 5.107092 | L52: 5.137434 | M52: 5.167955 | N52: 5.198658 | O52: 5.229543 | P52: 5.260611 | Q52: 5.291864 | R52: 5.323303 | S52: 5.354929 | T52: 5.386742 | U52: 5.418745 | V52: 5.450938 | W52: 5.483322 | X52: 5.515898 | Y52: 5.548667 | Z52: 5.581632 | AA52: 5.614792 | AB52: 5.64815 | AC52: 5.681705 | AD52: 5.71546 | AE52: 5.749416 | AF52: 5.783573 | AG52: 0.006
B54: Energy Use by Mode
B55: (quadrillion Btu)
A56: TKI000:da_Light-DutyVeh | B56: Light-Duty Vehicles | C56: 14.274495 | D56: 14.663075 | E56: 14.907382 | F56: 14.888803 | G56: 14.849199 | H56: 14.786862 | I56: 14.699437 | J56: 14.596199 | K56: 14.504814 | L56: 14.439389 | M56: 14.388906 | N56: 14.328156 | O56: 14.293911 | P56: 14.263883 | Q56: 14.229496 | R56: 14.203659 | S56: 14.192496 | T56: 14.188245 | U56: 14.197581 | V56: 14.217714 | W56: 14.239969 | X56: 14.268423 | Y56: 14.301932 | Z56: 14.345214 | AA56: 14.399622 | AB56: 14.468221 | AC56: 14.540375 | AD56: 14.616556 | AE56: 14.701982 | AF56: 14.799429 | AG56: 0.001
A57: TKI000:da_CommercialLig | B57: Commercial Light Trucks 1/ | C57: 0.888323 | D57: 0.90756 | E57: 0.915291 | F57: 0.914746 | G57: 0.917481 | H57: 0.917957 | I57: 0.914716 | J57: 0.913139 | K57: 0.912948 | L57: 0.913619 | M57: 0.914893 | N57: 0.917466 | O57: 0.921147 | P57: 0.925479 | Q57: 0.930151 | R57: 0.935853 | S57: 0.943343 | T57: 0.95109 | U57: 0.959005 | V57: 0.967115 | W57: 0.976328 | X57: 0.985922 | Y57: 0.996503 | Z57: 1.007049 | AA57: 1.017768 | AB57: 1.03064 | AC57: 1.041202 | AD57: 1.05052 | AE57: 1.061403 | AF57: 1.074768 | AG57: 0.007
A58: TKI000:da_BusTransporta | B58: Bus Transportation | C58: 0.175556 | D58: 0.199894 | E58: 0.211877 | F58: 0.218451 | G58: 0.222364 | H58: 0.224934 | I58: 0.226618 | J58: 0.227588 | K58: 0.228099 | L58: 0.228565 | M58: 0.229052 | N58: 0.229042 | O58: 0.228895 | P58: 0.228669 | Q58: 0.228265 | R58: 0.228023 | S58: 0.227888 | T58: 0.22772 | U58: 0.227019 | V58: 0.226432 | W58: 0.225723 | X58: 0.224894 | Y58: 0.224132 | Z58: 0.223359 | AA58: 0.222476 | AB58: 0.221673 | AC58: 0.220744 | AD58: 0.219683 | AE58: 0.218555 | AF58: 0.217454 | AG58: 0.007
A59: TKI000:da_FreightTrucks | B59: Freight Trucks | C59: 5.567438 | D59: 5.647416 | E59: 5.668759 | F59: 5.663161 | G59: 5.655948 | H59: 5.628574 | I59: 5.579707 | J59: 5.540802 | K59: 5.504025 | L59: 5.462724 | M59: 5.421764 | N59: 5.386013 | O59: 5.356112 | P59: 5.329699 | Q59: 5.312141 | R59: 5.300519 | S59: 5.299976 | T59: 5.304958 | U59: 5.312826 | V59: 5.324507 | W59: 5.344189 | X59: 5.371939 | Y59: 5.399783 | Z59: 5.429977 | AA59: 5.461901 | AB59: 5.498568 | AC59: 5.526202 | AD59: 5.545541 | AE59: 5.579021 | AF59: 5.62644 | AG59: 0
A60: TKI000:da_Rail,Passenge | B60: Rail, Passenger | C60: 0.035747 | D60: 0.040344 | E60: 0.043365 | F60: 0.045948 | G60: 0.047975 | H60: 0.049671 | I60: 0.050918 | J60: 0.051924 | K60: 0.052848 | L60: 0.053864 | M60: 0.054847 | N60: 0.05567 | O60: 0.056456 | P60: 0.057163 | Q60: 0.05777 | R60: 0.058395 | S60: 0.059068 | T60: 0.059723 | U60: 0.060305 | V60: 0.060996 | W60: 0.061573 | X60: 0.062161 | Y60: 0.062818 | Z60: 0.063486 | AA60: 0.064212 | AB60: 0.065028 | AC60: 0.065727 | AD60: 0.066388 | AE60: 0.067135 | AF60: 0.067961 | AG60: 0.022
A61: TKI000:da_Rail,Freight | B61: Rail, Freight | C61: 0.468249 | D61: 0.471079 | E61: 0.474241 | F61: 0.44252 | G61: 0.448957 | H61: 0.457648 | I61: 0.456704 | J61: 0.455449 | K61: 0.453944 | L61: 0.453611 | M61: 0.453718 | N61: 0.453838 | O61: 0.454424 | P61: 0.449777 | Q61: 0.447988 | R61: 0.443349 | S61: 0.443778 | T61: 0.443319 | U61: 0.442878 | V61: 0.441743 | W61: 0.441236 | X61: 0.441401 | Y61: 0.440002 | Z61: 0.438087 | AA61: 0.437033 | AB61: 0.436809 | AC61: 0.435689 | AD61: 0.435139 | AE61: 0.435125 | AF61: 0.437263 | AG61: -0.002
A62: TKI000:da_Shipping,Dome | B62: Shipping, Domestic | C62: 0.07517 | D62: 0.077553 | E62: 0.076938 | F62: 0.074884 | G62: 0.073009 | H62: 0.070952 | I62: 0.06864 | J62: 0.06646 | K62: 0.06422 | L62: 0.062007 | M62: 0.060829 | N62: 0.05965 | O62: 0.058555 | P62: 0.057363 | Q62: 0.056156 | R62: 0.054998 | S62: 0.053934 | T62: 0.05284 | U62: 0.051829 | V62: 0.050804 | W62: 0.050346 | X62: 0.04987 | Y62: 0.049359 | Z62: 0.048885 | AA62: 0.048413 | AB62: 0.047972 | AC62: 0.047419 | AD62: 0.046794 | AE62: 0.046349 | AF62: 0.046081 | AG62: -0.017
A63: TKI000:da_Shipping,Inte | B63: Shipping, International | C63: 0.927451 | D63: 0.990021 | E63: 0.88406 | F63: 0.884707 | G63: 0.887061 | H63: 0.885418 | I63: 0.881613 | J63: 0.880343 | K63: 0.880769 | L63: 0.87993 | M63: 0.884786 | N63: 0.884655 | O63: 0.885219 | P63: 0.886289 | Q63: 0.887352 | R63: 0.889095 | S63: 0.891039 | T63: 0.890647 | U63: 0.892274 | V63: 0.887781 | W63: 0.886336 | X63: 0.884984 | Y63: 0.881276 | Z63: 0.879002 | AA63: 0.879116 | AB63: 0.87801 | AC63: 0.877706 | AD63: 0.878744 | AE63: 0.879322 | AF63: 0.880516 | AG63: -0.002
A64: TKI000:da_RecreationalB | B64: Recreational Boats | C64: 0.204097 | D64: 0.207817 | E64: 0.208004 | F64: 0.208627 | G64: 0.208701 | H64: 0.208389 | I64: 0.207107 | J64: 0.205857 | K64: 0.204915 | L64: 0.204265 | M64: 0.203404 | N64: 0.202682 | O64: 0.202113 | P64: 0.201508 | Q64: 0.2008 | R64: 0.200075 | S64: 0.199646 | T64: 0.199111 | U64: 0.198526 | V64: 0.198077 | W64: 0.197288 | X64: 0.196608 | Y64: 0.195989 | Z64: 0.195343 | AA64: 0.194914 | AB64: 0.194549 | AC64: 0.193907 | AD64: 0.193255 | AE64: 0.192858 | AF64: 0.192572 | AG64: -0.002
A65: TKI000:da_Air | B65: Air | C65: 2.296161 | D65: 2.683651 | E65: 2.951118 | F65: 3.03471 | G65: 3.11169 | H65: 3.173993 | I65: 3.213956 | J65: 3.252055 | K65: 3.293846 | L65: 3.340357 | M65: 3.377276 | N65: 3.393485 | O65: 3.431159 | P65: 3.465197 | Q65: 3.501517 | R65: 3.538381 | S65: 3.580709 | T65: 3.619171 | U65: 3.663687 | V65: 3.712987 | W65: 3.753788 | X65: 3.799394 | Y65: 3.8472 | Z65: 3.892524 | AA65: 3.945747 | AB65: 3.999038 | AC65: 4.045661 | AD65: 4.090953 | AE65: 4.144071 | AF65: 4.203216 | AG65: 0.021
A66: TKI000:da_MilitaryUse | B66: Military Use | C66: 0.537703 | D66: 0.545349 | E66: 0.539672 | F66: 0.539224 | G66: 0.542587 | H66: 0.54515 | I66: 0.547037 | J66: 0.549198 | K66: 0.547834 | L66: 0.549644 | M66: 0.549119 | N66: 0.549319 | O66: 0.549484 | P66: 0.549623 | Q66: 0.549738 | R66: 0.549999 | S66: 0.550352 | T66: 0.550702 | U66: 0.55105 | V66: 0.551393 | W66: 0.551735 | X66: 0.552074 | Y66: 0.552409 | Z66: 0.552742 | AA66: 0.553074 | AB66: 0.553403 | AC66: 0.55373 | AD66: 0.554056 | AE66: 0.55438 | AF66: 0.554701 | AG66: 0.001
A67: TKI000:da_Lubricants | B67: Lubricants | C67: 0.125032 | D67: 0.126897 | E67: 0.127926 | F67: 0.1286 | G67: 0.129102 | H67: 0.12965 | I67: 0.129961 | J67: 0.130197 | K67: 0.130404 | L67: 0.130579 | M67: 0.130715 | N67: 0.130834 | O67: 0.130941 | P67: 0.131026 | Q67: 0.131091 | R67: 0.131164 | S67: 0.131261 | T67: 0.131365 | U67: 0.131484 | V67: 0.131631 | W67: 0.131762 | X67: 0.131876 | Y67: 0.131993 | Z67: 0.132102 | AA67: 0.13223 | AB67: 0.132369 | AC67: 0.132482 | AD67: 0.132586 | AE67: 0.132704 | AF67: 0.132831 | AG67: 0.002
... A69: TKI000:da_Total | B69: Total | C69: 26.323486 | D69: 27.261717 | E69: 27.691336 | F69: 27.713699 | G69: 27.751854 | H69: 27.725409 | I69: 27.604784 | J69: 27.501532 | K69: 27.406422 | L69: 27.33799 | M69: 27.28532 | N69: 27.210604 | O69: 27.188005 | P69: 27.162506 | Q69: 27.15077 | R69: 27.155056 | S69: 27.203161 | T69: 27.255516 | U69: 27.329729 | V69: 27.420429 | W69: 27.516987 | X69: 27.629517 | Y69: 27.752115 | Z69: 27.879595 | AA69: 28.032383 | AB69: 28.209902 | AC69: 28.372467 | AD69: 28.5296 | AE69: 28.716095 | AF69: 28.943384 | AG69: 0.003
B71: (million barrels per day oil equivalent)
A72: TKI000:ea_Light-DutyVeh | B72: Light-Duty Vehicles | C72: 7.742116 | D72: 7.952428 | E72: 8.08371 | F72: 8.072867 | G72: 8.052054 | H72: 8.01879 | I72: 7.971849 | J72: 7.916241 | K72: 7.867128 | L72: 7.832047 | M72: 7.804987 | N72: 7.772401 | O72: 7.754267 | P72: 7.738248 | Q72: 7.719971 | R72: 7.706108 | S72: 7.700164 | T72: 7.697928 | U72: 7.703142 | V72: 7.714182 | W72: 7.726223 | X72: 7.741686 | Y72: 7.759839 | Z72: 7.783333 | AA72: 7.812905 | AB72: 7.85021 | AC72: 7.889471 | AD72: 7.930946 | AE72: 7.977459 | AF72: 8.030522 | AG72: 0.001
A73: TKI000:ea_CommercialLig | B73: Commercial Light Trucks 1/ | C73: 0.464147 | D73: 0.474732 | E73: 0.479145 | F73: 0.479204 | G73: 0.481032 | H73: 0.481637 | I73: 0.48007 | J73: 0.479344 | K73: 0.479328 | L73: 0.479732 | M73: 0.480452 | N73: 0.481825 | O73: 0.483756 | P73: 0.486011 | Q73: 0.488466 | R73: 0.491464 | S73: 0.495405 | T73: 0.499485 | U73: 0.503656 | V73: 0.507948 | W73: 0.512819 | X73: 0.517899 | Y73: 0.523457 | Z73: 0.528974 | AA73: 0.534598 | AB73: 0.541335 | AC73: 0.546904 | AD73: 0.55184 | AE73: 0.557638 | AF73: 0.564761 | AG73: 0.007
A74: TKI000:ea_BusTransporta | B74: Bus Transportation | C74: 0.085859 | D74: 0.097947 | E74: 0.103826 | F74: 0.107033 | G74: 0.108947 | H74: 0.110241 | I74: 0.111054 | J74: 0.111527 | K74: 0.11177 | L74: 0.111989 | M74: 0.112246 | N74: 0.112238 | O74: 0.112155 | P74: 0.112047 | Q74: 0.11185 | R74: 0.111726 | S74: 0.111662 | T74: 0.111587 | U74: 0.111251 | V74: 0.110967 | W74: 0.11063 | X74: 0.110224 | Y74: 0.109848 | Z74: 0.109472 | AA74: 0.109043 | AB74: 0.108648 | AC74: 0.108193 | AD74: 0.107667 | AE74: 0.107116 | AF74: 0.106566 | AG74: 0.007
A75: TKI000:ea_FreightTrucks | B75: Freight Trucks | C75: 2.681122 | D75: 2.720326 | E75: 2.730281 | F75: 2.727139 | G75: 2.722948 | H75: 2.71029 | I75: 2.686574 | J75: 2.668368 | K75: 2.65138 | L75: 2.632008 | M75: 2.613121 | N75: 2.596792 | O75: 2.58329 | P75: 2.571543 | Q75: 2.564126 | R75: 2.559471 | S75: 2.560282 | T75: 2.563887 | U75: 2.568771 | V75: 2.575477 | W75: 2.586364 | X75: 2.601004 | Y75: 2.615732 | Z75: 2.631508 | AA75: 2.64829 | AB75: 2.667451 | AC75: 2.682264 | AD75: 2.693123 | AE75: 2.710997 | AF75: 2.735554 | AG75: 0.001
A76: TKI000:ea_Rail,Passenge | B76: Rail, Passenger | C76: 0.01693 | D76: 0.019111 | E76: 0.020543 | F76: 0.021765 | G76: 0.022722 | H76: 0.023527 | I76: 0.024115 | J76: 0.024591 | K76: 0.02503 | L76: 0.02551 | M76: 0.025975 | N76: 0.026365 | O76: 0.026737 | P76: 0.027073 | Q76: 0.02736 | R76: 0.027656 | S76: 0.027975 | T76: 0.028286 | U76: 0.028562 | V76: 0.028889 | W76: 0.029163 | X76: 0.029442 | Y76: 0.029753 | Z76: 0.030069 | AA76: 0.030413 | AB76: 0.030799 | AC76: 0.03113 | AD76: 0.031444 | AE76: 0.031799 | AF76: 0.032191 | AG76: 0.022
A77: TKI000:ea_Rail,Freight | B77: Rail, Freight | C77: 0.222397 | D77: 0.223843 | E77: 0.225339 | F77: 0.210235 | G77: 0.213218 | H77: 0.21736 | I77: 0.216847 | J77: 0.216229 | K77: 0.215496 | L77: 0.215296 | M77: 0.215329 | N77: 0.215365 | O77: 0.215621 | P77: 0.213397 | Q77: 0.212532 | R77: 0.210308 | S77: 0.210492 | T77: 0.210267 | U77: 0.210037 | V77: 0.209478 | W77: 0.209232 | X77: 0.209292 | Y77: 0.208613 | Z77: 0.20768 | AA77: 0.207164 | AB77: 0.207044 | AC77: 0.206499 | AD77: 0.206226 | AE77: 0.206214 | AF77: 0.207218 | AG77: -0.002
A78: TKI000:ea_Shipping,Dome | B78: Shipping, Domestic | C78: 0.035635 | D78: 0.036787 | E78: 0.036501 | F78: 0.035525 | G78: 0.034627 | H78: 0.033658 | I78: 0.032556 | J78: 0.031524 | K78: 0.030465 | L78: 0.029414 | M78: 0.028858 | N78: 0.028301 | O78: 0.027783 | P78: 0.02722 | Q78: 0.02665 | R78: 0.026101 | S78: 0.025598 | T78: 0.025082 | U78: 0.024604 | V78: 0.024118 | W78: 0.023903 | X78: 0.023677 | Y78: 0.023435 | Z78: 0.023208 | AA78: 0.022984 | AB78: 0.022775 | AC78: 0.022513 | AD78: 0.022216 | AE78: 0.022007 | AF78: 0.02188 | AG78: -0.017
A79: TKI000:ea_Shipping,Inte | B79: Shipping, International | C79: 0.4194 | D79: 0.441706 | E79: 0.400143 | F79: 0.400442 | G79: 0.401336 | H79: 0.400814 | I79: 0.399428 | J79: 0.399022 | K79: 0.399253 | L79: 0.398995 | M79: 0.40087 | N79: 0.400882 | O79: 0.401152 | P79: 0.401613 | Q79: 0.402068 | R79: 0.402766 | S79: 0.403541 | T79: 0.403462 | U79: 0.40412 | V79: 0.402499 | W79: 0.402031 | X79: 0.401587 | Y79: 0.400267 | Z79: 0.399465 | AA79: 0.399566 | AB79: 0.399214 | AC79: 0.399164 | AD79: 0.399617 | AE79: 0.399909 | AF79: 0.400431 | AG79: -0.002
A80: TKI000:ea_RecreationalB | B80: Recreational Boats | C80: 0.110663 | D80: 0.112683 | E80: 0.112789 | F80: 0.11313 | G80: 0.113195 | H80: 0.113051 | I80: 0.112379 | J80: 0.111725 | K80: 0.111239 | L80: 0.11091 | M80: 0.110467 | N80: 0.110098 | O80: 0.109813 | P80: 0.109508 | Q80: 0.109147 | R80: 0.108771 | S80: 0.108556 | T80: 0.108284 | U80: 0.107984 | V80: 0.107758 | W80: 0.107344 | X80: 0.10699 | Y80: 0.106669 | Z80: 0.106332 | AA80: 0.106114 | AB80: 0.105931 | AC80: 0.105597 | AD80: 0.105257 | AE80: 0.105056 | AF80: 0.104915 | AG80: -0.002
A81: TKI000:ea_Air | B81: Air | C81: 1.110822 | D81: 1.298055 | E81: 1.427294 | F81: 1.467685 | G81: 1.504884 | H81: 1.534991 | I81: 1.554303 | J81: 1.572715 | K81: 1.59291 | L81: 1.615387 | M81: 1.633229 | N81: 1.641063 | O81: 1.65927 | P81: 1.675719 | Q81: 1.693272 | R81: 1.711086 | S81: 1.731541 | T81: 1.750128 | U81: 1.77164 | V81: 1.795463 | W81: 1.81518 | X81: 1.837219 | Y81: 1.86032 | Z81: 1.882222 | AA81: 1.907941 | AB81: 1.933693 | AC81: 1.956223 | AD81: 1.97811 | AE81: 2.003777 | AF81: 2.032358 | AG81: 0.021
A82: TKI000:ea_MilitaryUse | B82: Military Use | C82: 0.257898 | D82: 0.261636 | E82: 0.258958 | F82: 0.258736 | G82: 0.260333 | H82: 0.26157 | I82: 0.262463 | J82: 0.2635 | K82: 0.262847 | L82: 0.26371 | M82: 0.26346 | N82: 0.263557 | O82: 0.263636 | P82: 0.263704 | Q82: 0.263761 | R82: 0.263885 | S82: 0.264055 | T82: 0.264227 | U82: 0.264394 | V82: 0.264558 | W82: 0.264727 | X82: 0.26489 | Y82: 0.265051 | Z82: 0.265208 | AA82: 0.265368 | AB82: 0.265527 | AC82: 0.265685 | AD82: 0.265843 | AE82: 0.266003 | AF82: 0.26616 | AG82: 0.001
A83: TKI000:ea_Lubricants | B83: Lubricants | C83: 0.059061 | D83: 0.059942 | E83: 0.060428 | F83: 0.060746 | G83: 0.060983 | H83: 0.061242 | I83: 0.061389 | J83: 0.061501 | K83: 0.061598 | L83: 0.061681 | M83: 0.061745 | N83: 0.061802 | O83: 0.061852 | P83: 0.061893 | Q83: 0.061923 | R83: 0.061958 | S83: 0.062003 | T83: 0.062053 | U83: 0.062109 | V83: 0.062178 | W83: 0.06224 | X83: 0.062294 | Y83: 0.062349 | Z83: 0.0624 | AA83: 0.062461 | AB83: 0.062527 | AC83: 0.06258 | AD83: 0.062629 | AE83: 0.062685 | AF83: 0.062745 | AG83: 0.002
... A85: TKI000:ea_Total | B85: Total | C85: 13.559407 | D85: 14.030354 | E85: 14.261442 | F85: 14.270667 | G85: 14.286991 | H85: 14.27242 | I85: 14.20985 | J85: 14.154975 | K85: 14.104977 | L85: 14.069279 | M85: 14.041723 | N85: 14.003458 | O85: 13.992006 | P85: 13.979344 | Q85: 13.973192 | R85: 13.974897 | S85: 13.99871 | T85: 14.025396 | U85: 14.063182 | V85: 14.110198 | W85: 14.160066 | X85: 14.217953 | Y85: 14.281213 | Z85: 14.347218 | AA85: 14.426109 | AB85: 14.518073 | AC85: 14.602921 | AD85: 14.685284 | AE85: 14.782825 | AF85: 14.900753 | AG85: 0.003
B87: 1/ Commercial trucks 8,501 to 10,000 pounds gross vehicle weight rating.
B88: 2/ CAFE standard based on projected new vehicle sales.
B89: 3/ Includes CAFE credits for alternative fueled vehicle sales and credit banking.
B90: 4/ Environmental Protection Agency rated miles per gallon.
B91: 5/ Tested new vehicle efficiency revised for on-road performance.
B92: 6/ Combined "on-the-road" estimate for all cars and light trucks.
B93: CAFE = Corporate average fuel economy.
B94: Btu = British thermal unit.
B95: Note: Totals may not equal sum of components due to independent rounding.
B96: Sources: 2020: U.S. Energy Information Administration (EIA), Short-Term Energy Outlook, October 2020 and EIA,
B97: AEO2021 National Energy Modeling System run highogs.d120120a. Projections: EIA, AEO2021 National Energy Modeling System run highogs.d120120a.

Sheet AEO 2021 Table 7
B1: highogs.d120120a | C1: 2020 | D1: 2021 | E1: 2022 | F1: 2023 | G1: 2024 | H1: 2025 | I1: 2026 | J1: 2027 | K1: 2028 | L1: 2029 | M1: 2030 | N1: 2031 | O1: 2032 | P1: 2033 | Q1: 2034 | R1: 2035 | S1: 2036 | T1: 2037 | U1: 2038 | V1: 2039 | W1: 2040 | X1: 2041 | Y1: 2042 | Z1: 2043 | AA1: 2044 | AB1: 2045 | AC1: 2046 | AD1: 2047 | AE1: 2048 | AF1: 2049 | AG1: 2050
C3: Report | D3: Annual Energy Outlook 2021
C4: Scenario | D4: ref2021 | G4: Reference case
C5: Datekey | D5: d113020a
C6: Release Date | E6: January 2021
A10: TKI000 | B10: 7. Transportation Sector Key Indicators and Delivered Energy Consumption | AH10: Compound
AH11: Growth
AH12: 2020-2050
B13: Key Indicators and Consumption | C13: 2020 | D13: 2021 | E13: 2022 | F13: 2023 | G13: 2024 | H13: 2025 | I13: 2026 | J13: 2027 | K13: 2028 | L13: 2029 | M13: 2030 | N13: 2031 | O13: 2032 | P13: 2033 | Q13: 2034 | R13: 2035 | S13: 2036 | T13: 2037 | U13: 2038 | V13: 2039 | W13: 2040 | X13: 2041 | Y13: 2042 | Z13: 2043 | AA13: 2044 | AB13: 2045 | AC13: 2046 | AD13: 2047 | AE13: 2048 | AF13: 2049 | AG13: 2050 | AH13: (percent)
B15: Key Indicators
B16: Travel Indicators
B17: (billion vehicle miles traveled)
A18: TKI000:ba_Light-DutyVeh | B18: Light-Duty Vehicles less than 8,501 pounds | C18: 2628.8213 | D18: 2807.2766 | E18: 2862.5334 | F18: 2927.623 | G18: 2985.1787 | H18: 3035.5583 | I18: 3076.646 | J18: 3107.3425 | K18: 3133.9348 | L18: 3153.6963 | M18: 3170.1406 | N18: 3182.3604 | O18: 3194.3308 | P18: 3208.3691 | Q18: 3223.0125 | R18: 3240.585 | S18: 3258.4961 | T18: 3274.8767 | U18: 3290.0166 | V18: 3306.9768 | W18: 3326.3066 | X18: 3344.3862 | Y18: 3362.8257 | Z18: 3380.6958 | AA18: 3396.752 | AB18: 3412.0305 | AC18: 3428.1084 | AD18: 3442.5149 | AE18: 3458.3401 | AF18: 3474.7087 | AG18: 3490.9399 | AH18: 0.009499
A19: TKI000:ba_CommercialLig | B19: Commercial Light Trucks 1/ | C19: 89.884674 | D19: 93.705605 | E19: 96.386086 | F19: 98.338295 | G19: 100.59341 | H19: 102.85941 | I19: 104.50481 | J19: 105.69051 | K19: 106.73648 | L19: 107.65262 | M19: 108.58299 | N19: 109.54169 | O19: 110.61884 | P19: 111.70705 | Q19: 112.95861 | R19: 114.4644 | S19: 115.90713 | T19: 117.2149 | U19: 118.58162 | V19: 120.04366 | W19: 121.52813 | X19: 123.15266 | Y19: 124.79562 | Z19: 126.54729 | AA19: 128.13809 | AB19: 129.78653 | AC19: 131.39938 | AD19: 132.81888 | AE19: 134.41592 | AF19: 136.18376 | AG19: 138.01 | AH19: 0.014396
A20: TKI000:ba_FreightTrucks | B20: Freight Trucks greater than 10,000 pounds | C20: 274.54938 | D20: 282.81525 | E20: 293.31253 | F20: 299.26825 | G20: 306.24057 | H20: 313.39252 | I20: 318.20425 | J20: 321.86676 | K20: 325.49912 | L20: 328.91818 | M20: 332.87759 | N20: 337.04804 | O20: 341.41943 | P20: 345.24298 | Q20: 349.75104 | R20: 355.3486 | S20: 360.47449 | T20: 365.30786 | U20: 370.46982 | V20: 375.98251 | W20: 381.01727 | X20: 386.70856 | Y20: 392.7948 | Z20: 399.70087 | AA20: 405.64847 | AB20: 411.79804 | AC20: 417.07053 | AD20: 422.22894 | AE20: 428.00507 | AF20: 434.11798 | AG20: 440.79153 | AH20: 0.015907
B21: (billion passenger miles traveled)
A22: TKI000:buspassmiles | B22: Bus Transportation | C22: 108.32251 | D22: 134.82925 | E22: 154.71742 | F22: 169.65283 | G22: 180.92081 | H22: 189.4493 | I22: 195.91775 | J22: 200.87158 | K22: 204.4294 | L22: 207.17819 | M22: 209.42627 | N22: 211.01544 | O22: 212.35484 | P22: 213.3685 | Q22: 214.16457 | R22: 214.70816 | S22: 215.16942 | T22: 215.53513 | U22: 215.80548 | V22: 215.98587 | W22: 216.16197 | X22: 216.26544 | Y22: 216.33122 | Z22: 216.37845 | AA22: 216.40999 | AB22: 216.44157 | AC22: 216.45151 | AD22: 216.46837 | AE22: 216.483 | AF22: 216.55254 | AG22: 216.64348 | AH22: 0.023374
A23: TKI000:railpassmiles | B23: Passenger Rail | C23: 24.970692 | D23: 29.653244 | E23: 33.486446 | F23: 36.386101 | G23: 38.577961 | H23: 40.222988 | I23: 41.396164 | J23: 42.264778 | K23: 42.515728 | L23: 42.713291 | M23: 43.137005 | N23: 43.343742 | O23: 43.818241 | P23: 44.274139 | Q23: 44.835865 | R23: 45.310886 | S23: 45.831734 | T23: 46.32793 | U23: 46.816154 | V23: 47.317448 | W23: 47.980492 | X23: 48.58215 | Y23: 49.164021 | Z23: 49.763081 | AA23: 50.334721 | AB23: 50.97802 | AC23: 51.558666 | AD23: 52.079247 | AE23: 52.647175 | AF23: 53.282265 | AG23: 53.912506 | AH23: 0.025987
B24: (billion seat miles available)
A25: TKI000:ba_Air | B25: Air | C25: 738.85895 | D25: 1081.6603 | E25: 1215.7373 | F25: 1284.3009 | G25: 1340.2419 | H25: 1397.254 | I25: 1430.9814 | J25: 1455.4497 | K25: 1476.5328 | L25: 1495.9988 | M25: 1516.3666 | N25: 1539.9563 | O25: 1569.8956 | P25: 1600.4498 | Q25: 1634.8596 | R25: 1672.6685 | S25: 1707.1351 | T25: 1738.4458 | U25: 1770.8867 | V25: 1807.5973 | W25: 1848.892 | X25: 1889.7706 | Y25: 1930.5969 | Z25: 1971.072 | AA25: 2010.4889 | AB25: 2052.9485 | AC25: 2092.6599 | AD25: 2129.1379 | AE25: 2171.0725 | AF25: 2213.2192 | AG25: 2256.3169 | AH25: 0.037914
B26: (billion ton miles traveled)
A27: TKI000:ba_Rail | B27: Rail | C27: 1508.557 | D27: 1600.7733 | E27: 1616.5277 | F27: 1618.1086 | G27: 1617.9658 | H27: 1567.8839 | I27: 1587.1537 | J27: 1586.3214 | K27: 1606.0509 | L27: 1623.5897 | M27: 1641.5112 | N27: 1654.2195 | O27: 1664.4609 | P27: 1678.1671 | Q27: 1686.5093 | R27: 1700.8228 | S27: 1714.3484 | T27: 1725.9465 | U27: 1730.047 | V27: 1747.595 | W27: 1753.4669 | X27: 1765.8125 | Y27: 1783.1677 | Z27: 1804.6465 | AA27: 1808.4172 | AB27: 1822.5868 | AC27: 1832.4125 | AD27: 1846.7275 | AE27: 1860.8992 | AF27: 1876.0131 | AG27: 1898.7479 | AH27: 0.007697
A28: TKI000:ba_DomesticShipp | B28: Domestic Shipping | C28: 347.68133 | D28: 359.32346 | E28: 357.10059 | F28: 354.90668 | G28: 352.6954 | H28: 348.07819 | I28: 341.28058 | J28: 333.10046 | K28: 325.25259 | L28: 316.86505 | M28: 308.73145 | N28: 305.11627 | O28: 301.85187 | P28: 298.30835 | Q28: 295.38019 | R28: 292.62634 | S28: 289.63 | T28: 286.27258 | U28: 282.6651 | V28: 279.71716 | W28: 276.01688 | X28: 275.42545 | Y28: 275.00784 | Z28: 275.36859 | AA28: 274.91849 | AB28: 274.56326 | AC28: 273.54471 | AD28: 272.61859 | AE28: 271.43494 | AF28: 270.55728 | AG28: 270.13117 | AH28: -0.008377
B30: Energy Efficiency Indicators
B31: (miles per gallon)
A32: TKI000:ca_AvgCAFEStand | B32: New Light-Duty Vehicle CAFE Standard 2/ | C32: 34.471165 | D32: 35.386478 | E32: 36.015511 | F32: 36.532135 | G32: 36.999756 | H32: 37.485561 | I32: 38.067947 | J32: 38.072563 | K32: 38.080814 | L32: 38.095245 | M32: 38.18074 | N32: 38.191765 | O32: 38.206318 | P32: 38.220623 | Q32: 38.249493 | R32: 38.23008 | S32: 38.209507 | T32: 38.204479 | U32: 38.204224 | V32: 38.187893 | W32: 38.180141 | X32: 38.173969 | Y32: 38.160957 | Z32: 38.151768 | AA32: 38.148342 | AB32: 38.153297 | AC32: 38.143864 | AD32: 38.134365 | AE32: 38.120548 | AF32: 38.116928 | AG32: 38.114223 | AH32: 0.003354
A33: TKI000:ca_CarCAFEStand | B33: New Car 2/ | C33: 42.096588 | D33: 44.275085 | E33: 44.804096 | F33: 45.431927 | G33: 46.163593 | H33: 46.83271 | I33: 47.617275 | J33: 47.640335 | K33: 47.640335 | L33: 47.644814 | M33: 47.681995 | N33: 47.681995 | O33: 47.681995 | P33: 47.681995 | Q33: 47.681995 | R33: 47.681995 | S33: 47.681995 | T33: 47.681995 | U33: 47.681995 | V33: 47.681995 | W33: 47.681995 | X33: 47.681995 | Y33: 47.681995 | Z33: 47.683205 | AA33: 47.684814 | AB33: 47.687138 | AC33: 47.687138 | AD33: 47.687138 | AE33: 47.687138 | AF33: 47.689449 | AG33: 47.689449 | AH33: 0.004167
A34: TKI000:ca_TwukCAFEStand | B34: New Light Truck 2/ | C34: 30.906752 | D34: 31.515783 | E34: 31.942911 | F34: 32.461285 | G34: 32.91795 | H34: 33.400791 | I34: 33.955074 | J34: 33.955074 | K34: 33.955074 | L34: 33.955074 | M34: 33.955074 | N34: 33.955093 | O34: 33.955093 | P34: 33.955093 | Q34: 33.955093 | R34: 33.955128 | S34: 33.955128 | T34: 33.955128 | U34: 33.955128 | V34: 33.955128 | W34: 33.955128 | X34: 33.955128 | Y34: 33.955128 | Z34: 33.955128 | AA34: 33.955128 | AB34: 33.955128 | AC34: 33.955128 | AD34: 33.955128 | AE34: 33.955128 | AF34: 33.955128 | AG34: 33.955128 | AH34: 0.00314
A35: TKI000:ca_NewVehCred | B35: Compliance New Light-Duty Vehicle 3/ | C35: 35.428043 | D35: 36.588161 | E35: 37.27243 | F35: 37.693687 | G35: 38.000156 | H35: 38.414772 | I35: 38.930225 | J35: 39.067493 | K35: 39.131561 | L35: 39.187084 | M35: 39.367001 | N35: 39.458767 | O35: 39.570412 | P35: 39.688381 | Q35: 39.842903 | R35: 39.925739 | S35: 40.007633 | T35: 40.122059 | U35: 40.263226 | V35: 40.363659 | W35: 40.483315 | X35: 40.567554 | Y35: 40.636898 | Z35: 40.715225 | AA35: 40.813824 | AB35: 40.933929 | AC35: 41.032745 | AD35: 41.136253 | AE35: 41.233734 | AF35: 41.366283 | AG35: 41.510693 | AH35: 0.005296
A36: TKI000:ca_NewCarCred | B36: New Car 3/ | C36: 43.264011 | D36: 45.133469 | E36: 45.638382 | F36: 46.329559 | G36: 46.974045 | H36: 47.544498 | I36: 48.288284 | J36: 48.41925 | K36: 48.519196 | L36: 48.602192 | M36: 48.75803 | N36: 48.944359 | O36: 49.116051 | P36: 49.343533 | Q36: 49.588879 | R36: 49.838387 | S36: 50.062164 | T36: 50.324268 | U36: 50.609341 | V36: 50.887779 | W36: 51.161552 | X36: 51.375084 | Y36: 51.577618 | Z36: 51.784939 | AA36: 52.021469 | AB36: 52.278286 | AC36: 52.554256 | AD36: 52.823685 | AE36: 53.105881 | AF36: 53.415283 | AG36: 53.766708 | AH36: 0.007271
A37: TKI000:ca_NewTwukCred | B37: New Light Truck 3/ | C37: 31.76507 | D37: 32.790131 | E37: 33.304337 | F37: 33.675228 | G37: 33.948895 | H37: 34.370636 | I37: 34.850887 | J37: 34.987331 | K37: 35.027725 | L37: 35.055889 | M37: 35.139996 | N37: 35.184067 | O37: 35.253815 | P37: 35.313755 | Q37: 35.395432 | R37: 35.447819 | S37: 35.509632 | T37: 35.58049 | U37: 35.672146 | V37: 35.736599 | W37: 35.81567 | X37: 35.86631 | Y37: 35.911537 | Z37: 35.962078 | AA37: 36.021683 | AB37: 36.09063 | AC37: 36.147751 | AD37: 36.213341 | AE37: 36.274784 | AF37: 36.358318 | AG37: 36.442936 | AH37: 0.00459
A38: TKI000:ca_TestedNewVeh | B38: Tested New Light-Duty Vehicle 4/ | C38: 35.306622 | D38: 36.467899 | E38: 37.145805 | F38: 37.564754 | G38: 37.869587 | H38: 38.261166 | I38: 38.678329 | J38: 38.78212 | K38: 38.833714 | L38: 38.876083 | M38: 39.031017 | N38: 39.097122 | O38: 39.178814 | P38: 39.263397 | Q38: 39.380604 | R38: 39.428646 | S38: 39.476784 | T38: 39.553841 | U38: 39.655148 | V38: 39.718605 | W38: 39.800255 | X38: 39.857685 | Y38: 39.902508 | Z38: 39.954895 | AA38: 40.024872 | AB38: 40.112934 | AC38: 40.181061 | AD38: 40.254047 | AE38: 40.320404 | AF38: 40.416508 | AG38: 40.5215 | AH38: 0.004603
A39: TKI000:ca_TestedNewCar | B39: New Car 4/ | C39: 42.996372 | D39: 44.88583 | E39: 45.388092 | F39: 46.068283 | G39: 46.702301 | H39: 47.265957 | I39: 47.99147 | J39: 48.105293 | K39: 48.179577 | L39: 48.231701 | M39: 48.343479 | N39: 48.473526 | O39: 48.589264 | P39: 48.747791 | Q39: 48.918312 | R39: 49.08532 | S39: 49.232788 | T39: 49.410698 | U39: 49.605431 | V39: 49.791992 | W39: 49.975594 | X39: 50.118858 | Y39: 50.253036 | Z39: 50.390747 | AA39: 50.551331 | AB39: 50.726044 | AC39: 50.913406 | AD39: 51.097149 | AE39: 51.287189 | AF39: 51.498287 | AG39: 51.738174 | AH39: 0.006188
A40: TKI000:ca_TestedNewTwuk | B40: New Light Truck 4/ | C40: 31.69734 | D40: 32.714512 | E40: 33.224262 | F40: 33.594929 | G40: 33.868374 | H40: 34.261593 | I40: 34.620468 | J40: 34.71925 | K40: 34.751755 | L40: 34.772854 | M40: 34.839573 | N40: 34.86882 | O40: 34.918171 | P40: 34.957504 | Q40: 35.015827 | R40: 35.049236 | S40: 35.091114 | T40: 35.140182 | U40: 35.208858 | V40: 35.253445 | W40: 35.311043 | X40: 35.348305 | Y40: 35.381889 | Z40: 35.41943 | AA40: 35.464706 | AB40: 35.517353 | AC40: 35.560341 | AD40: 35.610996 | AE40: 35.657856 | AF40: 35.722626 | AG40: 35.788242 | AH40: 0.004054
A41: TKI000:ca_OnRoadNewVeh | B41: On-Road New Light-Duty Vehicle 5/ | C41: 28.801699 | D41: 29.748508 | E41: 30.302168 | F41: 30.643736 | G41: 30.892097 | H41: 31.211321 | I41: 31.551422 | J41: 31.636091 | K41: 31.678196 | L41: 31.712803 | M41: 31.839462 | N41: 31.893412 | O41: 31.960094 | P41: 32.029114 | Q41: 32.124813 | R41: 32.16391 | S41: 32.203083 | T41: 32.2659 | U41: 32.348515 | V41: 32.400196 | W41: 32.466755 | X41: 32.513561 | Y41: 32.550056 | Z41: 32.592743 | AA41: 32.649788 | AB41: 32.721619 | AC41: 32.77713 | AD41: 32.836617 | AE41: 32.890667 | AF41: 32.969021 | AG41: 33.054626 | AH41: 0.004601
A42: TKI000:ca_OnRoadNewCar | B42: New Car 5/ | C42: 35.111473 | D42: 36.65443 | E42: 37.064587 | F42: 37.620041 | G42: 38.137787 | H42: 38.598076 | I42: 39.190544 | J42: 39.283493 | K42: 39.344154 | L42: 39.386719 | M42: 39.477997 | N42: 39.584198 | O42: 39.678711 | P42: 39.808167 | Q42: 39.947414 | R42: 40.083797 | S42: 40.20422 | T42: 40.349506 | U42: 40.508526 | V42: 40.660873 | W42: 40.810806 | X42: 40.927799 | Y42: 41.037373 | Z42: 41.149826 | AA42: 41.280964 | AB42: 41.423634 | AC42: 41.576637 | AD42: 41.726685 | AE42: 41.881874 | AF42: 42.05426 | AG42: 42.250156 | AH42: 0.006188
A43: TKI000:ca_OnRoadNewTwuk | B43: New Light Truck 5/ | C43: 25.844681 | D43: 26.67404 | E43: 27.08967 | F43: 27.391895 | G43: 27.614851 | H43: 27.935465 | I43: 28.228077 | J43: 28.30862 | K43: 28.335123 | L43: 28.352325 | M43: 28.406727 | N43: 28.430573 | O43: 28.470812 | P43: 28.502882 | Q43: 28.550436 | R43: 28.577677 | S43: 28.611822 | T43: 28.651831 | U43: 28.707827 | V43: 28.744179 | W43: 28.791143 | X43: 28.821524 | Y43: 28.848907 | Z43: 28.879517 | AA43: 28.916433 | AB43: 28.95936 | AC43: 28.99441 | AD43: 29.035711 | AE43: 29.073919 | AF43: 29.12673 | AG43: 29.180231 | AH43: 0.004054
... A47: TKI000:ca_FreightTruck | B47: Freight Truck | C47: 7.238182 | D47: 7.310616 | E47: 7.389947 | F47: 7.476684 | G47: 7.574702 | H47: 7.686319 | I47: 7.80973 | J47: 7.944551 | K47: 8.083447 | L47: 8.230841 | M47: 8.382581 | N47: 8.536425 | O47: 8.686997 | P47: 8.827357 | Q47: 8.956337 | R47: 9.073474 | S47: 9.178899 | T47: 9.273054 | U47: 9.358724 | V47: 9.437573 | W47: 9.508476 | X47: 9.572987 | Y47: 9.62975 | Z47: 9.67997 | AA47: 9.724974 | AB47: 9.767028 | AC47: 9.806892 | AD47: 9.846315 | AE47: 9.885777 | AF47: 9.92395 | AG47: 9.961658 | AH47: 0.010703
B48: (seat miles per gallon)
A49: TKI000:ca_Aircraft | B49: Aircraft | C49: 71.028343 | D49: 72.22039 | E49: 72.564766 | F49: 73.078918 | G49: 73.855469 | H49: 74.440651 | I49: 74.946922 | J49: 75.432518 | K49: 75.920792 | L49: 76.399239 | M49: 76.903839 | N49: 77.42765 | O49: 77.983635 | P49: 78.569893 | Q49: 79.171509 | R49: 79.79718 | S49: 80.421959 | T49: 81.046387 | U49: 81.662766 | V49: 82.260727 | W49: 82.849083 | X49: 83.43293 | Y49: 84.016846 | Z49: 84.607124 | AA49: 85.178467 | AB49: 85.733246 | AC49: 86.278442 | AD49: 86.813042 | AE49: 87.369904 | AF49: 87.921379 | AG49: 88.469986 | AH49: 0.007346
B50: (ton miles/thousand Btu)
A51: TKI000:ca_Rail | B51: Rail | C51: 3.489371 | D51: 3.512003 | E51: 3.534782 | F51: 3.55771 | G51: 3.580785 | H51: 3.60401 | I51: 3.627386 | J51: 3.650914 | K51: 3.674594 | L51: 3.698428 | M51: 3.722416 | N51: 3.74656 | O51: 3.77086 | P51: 3.795318 | Q51: 3.819935 | R51: 3.844712 | S51: 3.869649 | T51: 3.894748 | U51: 3.920009 | V51: 3.945435 | W51: 3.971025 | X51: 3.996782 | Y51: 4.022705 | Z51: 4.048797 | AA51: 4.075058 | AB51: 4.101489 | AC51: 4.128091 | AD51: 4.154866 | AE51: 4.181815 | AF51: 4.208939 | AG51: 4.236238 | AH51: 0.006486
A52: TKI000:ca_DomesticShipp | B52: Domestic Shipping | C52: 4.84196 | D52: 4.870726 | E52: 4.899663 | F52: 4.928772 | G52: 4.958054 | H52: 4.987509 | I52: 5.01714 | J52: 5.046947 | K52: 5.076931 | L52: 5.107092 | M52: 5.137434 | N52: 5.167955 | O52: 5.198658 | P52: 5.229543 | Q52: 5.260611 | R52: 5.291864 | S52: 5.323303 | T52: 5.354929 | U52: 5.386742 | V52: 5.418745 | W52: 5.450938 | X52: 5.483322 | Y52: 5.515898 | Z52: 5.548667 | AA52: 5.581632 | AB52: 5.614792 | AC52: 5.64815 | AD52: 5.681705 | AE52: 5.71546 | AF52: 5.749416 | AG52: 5.783573 | AH52: 0.005941
B54: Energy Use by Mode
B55: (quadrillion Btu)
A56: TKI000:da_Light-DutyVeh | B56: Light-Duty Vehicles | C56: 13.684958 | D56: 14.333231 | E56: 14.327022 | F56: 14.365352 | G56: 14.366455 | H56: 14.341867 | I56: 14.287132 | J56: 14.207239 | K56: 14.125376 | L56: 14.028779 | M56: 13.931946 | N56: 13.831038 | O56: 13.740598 | P56: 13.671222 | Q56: 13.614177 | R56: 13.578903 | S56: 13.555063 | T56: 13.533011 | U56: 13.512934 | V56: 13.507698 | W56: 13.519425 | X56: 13.531686 | Y56: 13.55102 | Z56: 13.573046 | AA56: 13.591692 | AB56: 13.608699 | AC56: 13.631719 | AD56: 13.65046 | AE56: 13.676695 | AF56: 13.70651 | AG56: 13.736445 | AH56: 0.000125
A57: TKI000:da_CommercialLig | B57: Commercial Light Trucks 1/ | C57: 0.800598 | D57: 0.824583 | E57: 0.83718 | F57: 0.842737 | G57: 0.851008 | H57: 0.861964 | I57: 0.867177 | J57: 0.868256 | K57: 0.868721 | L57: 0.868144 | M57: 0.86827 | N57: 0.869091 | O57: 0.871659 | P57: 0.875056 | Q57: 0.880524 | R57: 0.888546 | S57: 0.896605 | T57: 0.904579 | U57: 0.913077 | V57: 0.922396 | W57: 0.932011 | X57: 0.942835 | Y57: 0.95338 | Z57: 0.965235 | AA57: 0.976007 | AB57: 0.987214 | AC57: 0.999347 | AD57: 1.008795 | AE57: 1.01946 | AF57: 1.031487 | AG57: 1.044088 | AH57: 0.008891
A58: TKI000:da_BusTransporta | B58: Bus Transportation | C58: 0.123601 | D58: 0.155229 | E58: 0.178087 | F58: 0.194794 | G58: 0.207087 | H58: 0.215933 | I58: 0.222447 | J58: 0.227387 | K58: 0.229827 | L58: 0.231575 | M58: 0.233385 | N58: 0.233909 | O58: 0.234577 | P58: 0.234898 | Q58: 0.235117 | R58: 0.234732 | S58: 0.234535 | T58: 0.234329 | U58: 0.233979 | V58: 0.23339 | W58: 0.232922 | X58: 0.232252 | Y58: 0.231514 | Z58: 0.230767 | AA58: 0.230025 | AB58: 0.229276 | AC58: 0.228442 | AD58: 0.227697 | AE58: 0.226858 | AF58: 0.226287 | AG58: 0.225795 | AH58: 0.020289
A59: TKI000:da_FreightTrucks | B59: Freight Trucks | C59: 5.215993 | D59: 5.320461 | E59: 5.459595 | F59: 5.506526 | G59: 5.562604 | H59: 5.610408 | I59: 5.606836 | J59: 5.575173 | K59: 5.54105 | L59: 5.498658 | M59: 5.463652 | N59: 5.431874 | O59: 5.406318 | P59: 5.379243 | Q59: 5.370211 | R59: 5.384785 | S59: 5.398619 | T59: 5.414024 | U59: 5.438496 | V59: 5.471154 | W59: 5.50076 | X59: 5.54297 | Y59: 5.59491 | Z59: 5.661906 | AA59: 5.718006 | AB59: 5.778462 | AC59: 5.827639 | AD59: 5.875145 | AE59: 5.930928 | AF59: 5.991611 | AG59: 6.059749 | AH59: 0.00501
A60: TKI000:da_Rail,Passenge | B60: Rail, Passenger | C60: 0.029437 | D60: 0.035251 | E60: 0.039934 | F60: 0.043478 | G60: 0.046156 | H60: 0.048166 | I60: 0.049615 | J60: 0.050695 | K60: 0.051001 | L60: 0.05125 | M60: 0.051752 | N60: 0.052019 | O60: 0.052574 | P60: 0.053111 | Q60: 0.053765 | R60: 0.05433 | S60: 0.054952 | T60: 0.05555 | U60: 0.056141 | V60: 0.056752 | W60: 0.057542 | X60: 0.058268 | Y60: 0.058979 | Z60: 0.059712 | AA60: 0.060418 | AB60: 0.061203 | AC60: 0.061918 | AD60: 0.062563 | AE60: 0.063254 | AF60: 0.064012 | AG60: 0.064756 | AH60: 0.026627
A61: TKI000:da_Rail,Freight | B61: Rail, Freight | C61: 0.432329 | D61: 0.455801 | E61: 0.45732 | F61: 0.454818 | G61: 0.451847 | H61: 0.435039 | I61: 0.437548 | J61: 0.4345 | K61: 0.437069 | L61: 0.438995 | M61: 0.44098 | N61: 0.44153 | O61: 0.441401 | P61: 0.442168 | Q61: 0.441502 | R61: 0.44238 | S61: 0.443024 | T61: 0.443147 | U61: 0.441338 | V61: 0.442941 | W61: 0.441565 | X61: 0.441809 | Y61: 0.443276 | Z61: 0.445724 | AA61: 0.443777 | AB61: 0.444372 | AC61: 0.443889 | AD61: 0.444473 | AE61: 0.444998 | AF61: 0.445721 | AG61: 0.448216 | AH61: 0.001204
A62: TKI000:da_Shipping,Dome | B62: Shipping, Domestic | C62: 0.077343 | D62: 0.079141 | E62: 0.078228 | F62: 0.07735 | G62: 0.076447 | H62: 0.075056 | I62: 0.073205 | J62: 0.071058 | K62: 0.068995 | L62: 0.066834 | M62: 0.064753 | N62: 0.063638 | O62: 0.062605 | P62: 0.061511 | Q62: 0.060562 | R62: 0.059665 | S62: 0.058721 | T62: 0.057711 | U62: 0.056659 | V62: 0.055745 | W62: 0.054692 | X62: 0.054265 | Y62: 0.053874 | Z62: 0.053634 | AA62: 0.05324 | AB62: 0.052873 | AC62: 0.052373 | AD62: 0.051891 | AE62: 0.05137 | AF62: 0.05091 | AG62: 0.050533 | AH62: -0.014087
A63: TKI000:da_Shipping,Inte | B63: Shipping, International | C63: 0.855887 | D63: 0.881465 | E63: 0.973998 | F63: 0.992193 | G63: 0.941402 | H63: 0.944552 | I63: 0.956481 | J63: 0.933812 | K63: 0.934805 | L63: 0.926796 | M63: 0.92926 | N63: 0.946328 | O63: 0.931566 | P63: 0.932016 | Q63: 0.929677 | R63: 0.944409 | S63: 0.930073 | T63: 0.929561 | U63: 0.939661 | V63: 0.926163 | W63: 0.924429 | X63: 0.937035 | Y63: 0.921133 | Z63: 0.92034 | AA63: 0.913829 | AB63: 0.914233 | AC63: 0.910465 | AD63: 0.908206 | AE63: 0.908689 | AF63: 0.907332 | AG63: 0.904865 | AH63: 0.001857
A64: TKI000:da_RecreationalB | B64: Recreational Boats | C64: 0.195878 | D64: 0.196657 | E64: 0.199716 | F64: 0.201514 | G64: 0.202257 | H64: 0.202574 | I64: 0.201854 | J64: 0.200378 | K64: 0.198674 | L64: 0.19683 | M64: 0.195069 | N64: 0.193556 | O64: 0.192489 | P64: 0.191383 | Q64: 0.190484 | R64: 0.189818 | S64: 0.18891 | T64: 0.187759 | U64: 0.186658 | V64: 0.185802 | W64: 0.185223 | X64: 0.184588 | Y64: 0.183882 | Z64: 0.183175 | AA64: 0.182329 | AB64: 0.18168 | AC64: 0.180906 | AD64: 0.17988 | AE64: 0.17914 | AF64: 0.178366 | AG64: 0.177572 | AH64: -0.003265
A65: TKI000:da_Air | B65: Air | C65: 1.860485 | D65: 2.530984 | E65: 2.826346 | F65: 2.963305 | G65: 3.051768 | H65: 3.120219 | I65: 3.144242 | J65: 3.161629 | K65: 3.182792 | L65: 3.201851 | M65: 3.222472 | N65: 3.248707 | O65: 3.287299 | P65: 3.325297 | Q65: 3.36779 | R65: 3.416815 | S65: 3.457473 | T65: 3.492202 | U65: 3.528905 | V65: 3.570296 | W65: 3.622022 | X65: 3.669847 | Y65: 3.719 | Z65: 3.765759 | AA65: 3.814193 | AB65: 3.866814 | AC65: 3.914752 | AD65: 3.951365 | AE65: 3.990626 | AF65: 4.026413 | AG65: 4.062809 | AH65: 0.026376
A66: TKI000:da_MilitaryUse | B66: Military Use | C66: 0.535966 | D66: 0.545011 | E66: 0.545749 | F66: 0.53257 | G66: 0.52388 | H66: 0.523357 | I66: 0.5221 | J66: 0.52193 | K66: 0.524808 | L66: 0.52365 | M66: 0.521666 | N66: 0.521585 | O66: 0.52242 | P66: 0.523287 | Q66: 0.524164 | R66: 0.525042 | S66: 0.525958 | T66: 0.526906 | U66: 0.527867 | V66: 0.528832 | W66: 0.529807 | X66: 0.530791 | Y66: 0.531775 | Z66: 0.532766 | AA66: 0.533758 | AB66: 0.534753 | AC66: 0.535749 | AD66: 0.536745 | AE66: 0.53774 | AF66: 0.538735 | AG66: 0.539727 | AH66: 0.000233
A67: TKI000:da_Lubricants | B67: Lubricants | C67: 0.121224 | D67: 0.1234 | E67: 0.124821 | F67: 0.125915 | G67: 0.126656 | H67: 0.127041 | I67: 0.127207 | J67: 0.126854 | K67: 0.126597 | L67: 0.126378 | M67: 0.126074 | N67: 0.125802 | O67: 0.125585 | P67: 0.125401 | Q67: 0.125289 | R67: 0.125205 | S67: 0.125084 | T67: 0.124934 | U67: 0.12483 | V67: 0.124758 | W67: 0.124673 | X67: 0.124589 | Y67: 0.124522 | Z67: 0.12444 | AA67: 0.124423 | AB67: 0.124498 | AC67: 0.124516 | AD67: 0.124474 | AE67: 0.124496 | AF67: 0.12447 | AG67: 0.124386 | AH67: 0.000858
... A69: TKI000:da_Total | B69: Total | C69: 24.63995 | D69: 26.246357 | E69: 26.803347 | F69: 27.032192 | G69: 27.130775 | H69: 27.230783 | I69: 27.186893 | J69: 27.080057 | K69: 26.990782 | L69: 26.860777 | M69: 26.742741 | N69: 26.653553 | O69: 26.566212 | P69: 26.51256 | Q69: 26.490156 | R69: 26.545183 | S69: 26.577869 | T69: 26.62192 | U69: 26.686522 | V69: 26.75659 | W69: 26.859634 | X69: 26.988043 | Y69: 27.108532 | Z69: 27.264854 | AA69: 27.401077 | AB69: 27.549936 | AC69: 27.685604 | AD69: 27.804758 | AE69: 27.932571 | AF69: 28.069273 | AG69: 28.223778 | AH69: 0.004537
B71: (million barrels per day oil equivalent)
A72: TKI000:ea_Light-DutyVeh | B72: Light-Duty Vehicles | C72: 7.422104 | D72: 7.773714 | E72: 7.769763 | F72: 7.790549 | G72: 7.790876 | H72: 7.778635 | I72: 7.749986 | J72: 7.707629 | K72: 7.66415 | L72: 7.612647 | M72: 7.560986 | N72: 7.507026 | O72: 7.458717 | P72: 7.421792 | Q72: 7.391498 | R72: 7.373047 | S72: 7.360369 | T72: 7.34863 | U72: 7.337916 | V72: 7.33523 | W72: 7.341699 | X72: 7.348314 | Y72: 7.358773 | Z72: 7.37068 | AA72: 7.380744 | AB72: 7.389912 | AC72: 7.40236 | AD72: 7.412508 | AE72: 7.426698 | AF72: 7.442851 | AG72: 7.459049 | AH72: 0.000166
A73: TKI000:ea_CommercialLig | B73: Commercial Light Trucks 1/ | C73: 0.417402 | D73: 0.429752 | E73: 0.4361 | F73: 0.438805 | G73: 0.442896 | H73: 0.448514 | I73: 0.451192 | J73: 0.451773 | K73: 0.452056 | L73: 0.451855 | M73: 0.452067 | N73: 0.452658 | O73: 0.454179 | P73: 0.456158 | Q73: 0.459232 | R73: 0.463664 | S73: 0.46811 | T73: 0.472552 | U73: 0.477285 | V73: 0.48244 | W73: 0.487753 | X73: 0.493671 | Y73: 0.499459 | Z73: 0.505901 | AA73: 0.511755 | AB73: 0.517801 | AC73: 0.524376 | AD73: 0.529585 | AE73: 0.535473 | AF73: 0.542111 | AG73: 0.549078 | AH73: 0.009181
A74: TKI000:ea_BusTransporta | B74: Bus Transportation | C74: 0.059765 | D74: 0.07508 | E74: 0.08616 | F74: 0.094233 | G74: 0.100171 | H74: 0.104438 | I74: 0.107584 | J74: 0.109979 | K74: 0.111142 | L74: 0.111985 | M74: 0.112868 | N74: 0.113118 | O74: 0.113448 | P74: 0.113605 | Q74: 0.113716 | R74: 0.11353 | S74: 0.113436 | T74: 0.113336 | U74: 0.113171 | V74: 0.112886 | W74: 0.112663 | X74: 0.112337 | Y74: 0.11198 | Z74: 0.11162 | AA74: 0.111264 | AB74: 0.110882 | AC74: 0.110487 | AD74: 0.110127 | AE74: 0.109734 | AF74: 0.109462 | AG74: 0.109221 | AH74: 0.020302
A75: TKI000:ea_FreightTrucks | B75: Freight Trucks | C75: 2.511301 | D75: 2.562341 | E75: 2.62972 | F75: 2.651934 | G75: 2.678503 | H75: 2.701084 | I75: 2.699315 | J75: 2.684517 | K75: 2.668267 | L75: 2.648567 | M75: 2.632661 | N75: 2.618124 | O75: 2.60683 | P75: 2.594657 | Q75: 2.591201 | R75: 2.599064 | S75: 2.606463 | T75: 2.614655 | U75: 2.627334 | V75: 2.643946 | W75: 2.65917 | X75: 2.680398 | Y75: 2.706399 | Z75: 2.73978 | AA75: 2.767942 | AB75: 2.797641 | AC75: 2.822753 | AD75: 2.846913 | AE75: 2.875512 | AF75: 2.906283 | AG75: 2.940435 | AH75: 0.005272
A76: TKI000:ea_Rail,Passenge | B76: Rail, Passenger | C76: 0.013936 | D76: 0.016692 | E76: 0.018912 | F76: 0.02059 | G76: 0.021857 | H76: 0.022807 | I76: 0.023493 | J76: 0.024005 | K76: 0.024148 | L76: 0.024265 | M76: 0.024503 | N76: 0.02463 | O76: 0.024893 | P76: 0.025147 | Q76: 0.025457 | R76: 0.025725 | S76: 0.026019 | T76: 0.026302 | U76: 0.026582 | V76: 0.026871 | W76: 0.027246 | X76: 0.027589 | Y76: 0.027926 | Z76: 0.028273 | AA76: 0.028608 | AB76: 0.028976 | AC76: 0.029316 | AD76: 0.029622 | AE76: 0.029951 | AF76: 0.030311 | AG76: 0.030663 | AH76: 0.026634
A77: TKI000:ea_Rail,Freight | B77: Rail, Freight | C77: 0.2052 | D77: 0.216413 | E77: 0.217179 | F77: 0.215971 | G77: 0.214533 | H77: 0.206519 | I77: 0.207688 | J77: 0.206239 | K77: 0.20741 | L77: 0.208304 | M77: 0.209237 | N77: 0.209471 | O77: 0.2094 | P77: 0.209744 | Q77: 0.209412 | R77: 0.20981 | S77: 0.210093 | T77: 0.210129 | U77: 0.209256 | V77: 0.209996 | W77: 0.209331 | X77: 0.209426 | Y77: 0.210104 | Z77: 0.211251 | AA77: 0.210315 | AB77: 0.210549 | AC77: 0.210321 | AD77: 0.210586 | AE77: 0.210842 | AF77: 0.21118 | AG77: 0.212342 | AH77: 0.001141
A78: TKI000:ea_Shipping,Dome | B78: Shipping, Domestic | C78: 0.036641 | D78: 0.037508 | E78: 0.037086 | F78: 0.03667 | G78: 0.03624 | H78: 0.035579 | I78: 0.034701 | J78: 0.033688 | K78: 0.032706 | L78: 0.031683 | M78: 0.030701 | N78: 0.030174 | O78: 0.029688 | P78: 0.029171 | Q78: 0.028723 | R78: 0.0283 | S78: 0.027854 | T78: 0.027376 | U78: 0.026879 | V78: 0.026447 | W78: 0.02595 | X78: 0.025747 | Y78: 0.025561 | Z78: 0.025448 | AA78: 0.025261 | AB78: 0.025081 | AC78: 0.024846 | AD78: 0.024618 | AE78: 0.024375 | AF78: 0.024158 | AG78: 0.023978 | AH78: -0.014035
A79: TKI000:ea_Shipping,Inte | B79: Shipping, International | C79: 0.390127 | D79: 0.399914 | E79: 0.434956 | F79: 0.441884 | G79: 0.422805 | H79: 0.424046 | I79: 0.428597 | J79: 0.420109 | K79: 0.420515 | L79: 0.417549 | M79: 0.418554 | N79: 0.425043 | O79: 0.419537 | P79: 0.41976 | Q79: 0.418936 | R79: 0.424556 | S79: 0.419202 | T79: 0.419055 | U79: 0.422916 | V79: 0.417875 | W79: 0.417271 | X79: 0.422074 | Y79: 0.416121 | Z79: 0.415873 | AA79: 0.413463 | AB79: 0.413624 | AC79: 0.412266 | AD79: 0.41146 | AE79: 0.411718 | AF79: 0.411262 | AG79: 0.410365 | AH79: 0.001687
A80: TKI000:ea_RecreationalB | B80: Recreational Boats | C80: 0.106203 | D80: 0.106628 | E80: 0.108291 | F80: 0.10927 | G80: 0.109676 | H80: 0.109872 | I80: 0.109505 | J80: 0.108728 | K80: 0.107827 | L80: 0.10685 | M80: 0.105917 | N80: 0.105118 | O80: 0.104561 | P80: 0.103983 | Q80: 0.103517 | R80: 0.103178 | S80: 0.102702 | T80: 0.102093 | U80: 0.101512 | V80: 0.101063 | W80: 0.100765 | X80: 0.100435 | Y80: 0.100065 | Z80: 0.099694 | AA80: 0.099248 | AB80: 0.098909 | AC80: 0.098502 | AD80: 0.097958 | AE80: 0.097569 | AF80: 0.097161 | AG80: 0.096743 | AH80: -0.003105
A81: TKI000:ea_Air | B81: Air | C81: 0.900305 | D81: 1.224288 | E81: 1.367005 | F81: 1.433183 | G81: 1.475928 | H81: 1.509005 | I81: 1.520615 | J81: 1.529019 | K81: 1.539247 | L81: 1.548459 | M81: 1.558426 | N81: 1.571105 | O81: 1.589755 | P81: 1.608117 | Q81: 1.628653 | R81: 1.652344 | S81: 1.671992 | T81: 1.688775 | U81: 1.706511 | V81: 1.726514 | W81: 1.75151 | X81: 1.77462 | Y81: 1.798373 | Z81: 1.820968 | AA81: 1.844373 | AB81: 1.869801 | AC81: 1.892966 | AD81: 1.910659 | AE81: 1.929632 | AF81: 1.946926 | AG81: 1.964514 | AH81: 0.02635
A82: TKI000:ea_MilitaryUse | B82: Military Use | C82: 0.257081 | D82: 0.261438 | E82: 0.261803 | F82: 0.255477 | G82: 0.251303 | H82: 0.251044 | I82: 0.250438 | J82: 0.25036 | K82: 0.251731 | L82: 0.251176 | M82: 0.250227 | N82: 0.250187 | O82: 0.250591 | P82: 0.251006 | Q82: 0.251428 | R82: 0.25185 | S82: 0.252288 | T82: 0.252742 | U82: 0.253204 | V82: 0.253666 | W82: 0.254136 | X82: 0.254607 | Y82: 0.255078 | Z82: 0.255554 | AA82: 0.256032 | AB82: 0.256496 | AC82: 0.25698 | AD82: 0.257459 | AE82: 0.257947 | AF82: 0.258428 | AG82: 0.258902 | AH82: 0.000235
A83: TKI000:ea_Lubricants | B83: Lubricants | C83: 0.057262 | D83: 0.05829 | E83: 0.058961 | F83: 0.059478 | G83: 0.059828 | H83: 0.06001 | I83: 0.060088 | J83: 0.059921 | K83: 0.0598 | L83: 0.059697 | M83: 0.059553 | N83: 0.059424 | O83: 0.059322 | P83: 0.059235 | Q83: 0.059183 | R83: 0.059143 | S83: 0.059086 | T83: 0.059015 | U83: 0.058966 | V83: 0.058931 | W83: 0.058892 | X83: 0.058852 | Y83: 0.05882 | Z83: 0.058781 | AA83: 0.058773 | AB83: 0.058809 | AC83: 0.058817 | AD83: 0.058797 | AE83: 0.058808 | AF83: 0.058795 | AG83: 0.058756 | AH83: 0.000858
... A85: TKI000:ea_Total | B85: Total | C85: 12.710937 | D85: 13.523485 | E85: 13.782738 | F85: 13.893643 | G85: 13.946235 | H85: 13.993832 | I85: 13.969633 | J85: 13.917164 | K85: 13.870161 | L85: 13.804184 | M85: 13.743266 | N85: 13.694123 | O85: 13.650218 | P85: 13.62207 | Q85: 13.610144 | R85: 13.63513 | S85: 13.652452 | T85: 13.673915 | U85: 13.704461 | V85: 13.741007 | W85: 13.793367 | X85: 13.856253 | Y85: 13.918808 | Z85: 13.997322 | AA85: 14.066484 | AB85: 14.140247 | AC85: 14.209555 | AD85: 14.270186 | AE85: 14.335911 | AF85: 14.406158 | AG85: 14.484777 | AH85: 0.004364
B87: 1/ Commercial trucks 8,501 to 10,000 pounds gross vehicle weight rating.
B88: 2/ CAFE standard based on projected new vehicle sales.
B89: 3/ Includes CAFE credits for alternative fueled vehicle sales and credit banking.
B90: 4/ Environmental Protection Agency rated miles per gallon.
B91: 5/ Tested new vehicle efficiency revised for on-road performance.
B92: 6/ Combined "on-the-road" estimate for all cars and light trucks.
B93: CAFE = Corporate average fuel economy.
B94: Btu = British thermal unit.
B95: Note: Totals may not equal sum of components due to independent rounding.
B96: Sources: 2020: U.S. Energy Information Administration (EIA), Short-Term Energy Outlook, October 2020 and EIA,
B97: AEO2021 National Energy Modeling System run highogs.d120120a. Projections: EIA, AEO2021 National Energy Modeling System run highogs.d120120a.

Sheet AEO 2020 Table 7
B1: highogs.d112619a | C1: 2019 | D1: 2020 | E1: 2021 | F1: 2022 | G1: 2023 | H1: 2024 | I1: 2025 | J1: 2026 | K1: 2027 | L1: 2028 | M1: 2029 | N1: 2030 | O1: 2031 | P1: 2032 | Q1: 2033 | R1: 2034 | S1: 2035 | T1: 2036 | U1: 2037 | V1: 2038 | W1: 2039 | X1: 2040 | Y1: 2041 | Z1: 2042 | AA1: 2043 | AB1: 2044 | AC1: 2045 | AD1: 2046 | AE1: 2047 | AF1: 2048 | AG1: 2049 | AH1: 2050
C3: Report | D3: Annual Energy Outlook 2020
C4: Scenario | D4: highogs | G4: High oil and gas supply
C5: Datekey | D5: d112619a
C6: Release Date | E6: January 2020
A10: TKI000 | B10: 7. Transportation Sector Key Indicators and Delivered Energy Consumption
AI12: 2019-
B13: Key Indicators and Consumption | C13: 2019 | D13: 2020 | E13: 2021 | F13: 2022 | G13: 2023 | H13: 2024 | I13: 2025 | J13: 2026 | K13: 2027 | L13: 2028 | M13: 2029 | N13: 2030 | O13: 2031 | P13: 2032 | Q13: 2033 | R13: 2034 | S13: 2035 | T13: 2036 | U13: 2037 | V13: 2038 | W13: 2039 | X13: 2040 | Y13: 2041 | Z13: 2042 | AA13: 2043 | AB13: 2044 | AC13: 2045 | AD13: 2046 | AE13: 2047 | AF13: 2048 | AG13: 2049 | AH13: 2050 | AI13: 2050
B15: Key Indicators
B16: Travel Indicators
B17: (billion vehicle miles traveled)
A18: TKI000:ba_Light-DutyVeh | B18: Light-Duty Vehicles less than 8,501 pounds | C18: 2917.2534 | D18: 2975.1255 | E18: 3025.3584 | F18: 3062.7468 | G18: 3083.9775 | H18: 3096.5911 | I18: 3105.9812 | J18: 3125.592 | K18: 3146.8806 | L18: 3167.6331 | M18: 3188.2371 | N18: 3209.8457 | O18: 3233.3459 | P18: 3252.6282 | Q18: 3271.1394 | R18: 3285.1404 | S18: 3295.6909 | T18: 3311.9399 | U18: 3327.9958 | V18: 3344.2627 | W18: 3361.5449 | X18: 3379.7544 | Y18: 3396.2571 | Z18: 3413.8406 | AA18: 3432.0298 | AB18: 3451.1577 | AC18: 3472.0923 | AD18: 3496.9058 | AE18: 3524.3184 | AF18: 3555.4368 | AG18: 3588.8325 | AH18: 3624.4036 | AI18: 0.007026
A19: TKI000:ba_CommercialLig | B19: Commercial Light Trucks 1/ | C19: 99.321114 | D19: 100.61537 | E19: 102.27555 | F19: 103.79449 | G19: 104.99791 | H19: 105.84502 | I19: 106.78965 | J19: 107.83586 | K19: 109.08619 | L19: 110.31479 | M19: 111.61692 | N19: 112.77087 | O19: 114.26243 | P19: 115.52301 | Q19: 116.87927 | R19: 118.14617 | S19: 119.40303 | T19: 120.80527 | U19: 122.15245 | V19: 123.49687 | W19: 124.85643 | X19: 126.2754 | Y19: 127.71654 | Z19: 129.18462 | AA19: 130.707 | AB19: 132.37408 | AC19: 134.19019 | AD19: 136.27534 | AE19: 138.1423 | AF19: 140.20346 | AG19: 142.3405 | AH19: 144.47952 | AI19: 0.012163
A20: TKI000:ba_FreightTrucks | B20: Freight Trucks greater than 10,000 pounds | C20: 299.98956 | D20: 302.9967 | E20: 307.86118 | F20: 312.26749 | G20: 316.85519 | H20: 319.63693 | I20: 322.73798 | J20: 325.80005 | K20: 329.40594 | L20: 332.56686 | M20: 335.87531 | N20: 338.36066 | O20: 342.56183 | P20: 345.99631 | Q20: 349.88959 | R20: 353.1503 | S20: 356.89838 | T20: 360.95453 | U20: 364.40631 | V20: 367.98541 | W20: 371.4613 | X20: 375.17526 | Y20: 378.96576 | Z20: 382.97611 | AA20: 386.86951 | AB20: 391.47946 | AC20: 396.5683 | AD20: 402.70737 | AE20: 407.39862 | AF20: 413.09305 | AG20: 419.04983 | AH20: 425.07648 | AI20: 0.011306
B21: (billion passenger miles traveled)
A22: TKI000:buspassmiles | B22: Bus Transportation | C22: 210.1385 | D22: 211.1262 | E22: 212.11616 | F22: 213.08595 | G22: 214.01353 | H22: 214.96095 | I22: 215.98413 | J22: 216.98978 | K22: 217.98006 | L22: 218.98109 | M22: 219.96805 | N22: 220.90674 | O22: 221.80705 | P22: 222.67883 | Q22: 223.45596 | R22: 224.19052 | S22: 224.88495 | T22: 225.5426 | U22: 226.16771 | V22: 226.76289 | W22: 227.33022 | X22: 227.87238 | Y22: 228.39172 | Z22: 228.89146 | AA22: 229.37672 | AB22: 229.85208 | AC22: 230.32323 | AD22: 230.79691 | AE22: 231.28061 | AF22: 231.78067 | AG22: 232.30583 | AH22: 232.85057 | AI22: 0.003316
A23: TKI000:railpassmiles | B23: Passenger Rail | C23: 41.270718 | D23: 41.874931 | E23: 42.455513 | F23: 42.941441 | G23: 43.403492 | H23: 43.866783 | I23: 44.310471 | J23: 44.75193 | K23: 45.177658 | L23: 45.617382 | M23: 46.05724 | N23: 46.402245 | O23: 46.841446 | P23: 47.267838 | Q23: 47.680485 | R23: 48.055225 | S23: 48.435219 | T23: 48.803921 | U23: 49.166313 | V23: 49.530781 | W23: 49.890511 | X23: 50.244217 | Y23: 50.573273 | Z23: 50.897018 | AA23: 51.222713 | AB23: 51.549355 | AC23: 51.873222 | AD23: 52.227497 | AE23: 52.585468 | AF23: 52.972961 | AG23: 53.355492 | AH23: 53.757782 | AI23: 0.008563
B24: (billion seat miles available)
A25: TKI000:ba_Air | B25: Air | C25: 1222.9934 | D25: 1245.385 | E25: 1270.2579 | F25: 1290.4578 | G25: 1307.1332 | H25: 1325.8835 | I25: 1346.3998 | J25: 1366.3947 | K25: 1386.9773 | L25: 1409.3759 | M25: 1434.0159 | N25: 1459.4762 | O25: 1485.5172 | P25: 1512.3081 | Q25: 1538.871 | R25: 1563.6233 | S25: 1587.829 | T25: 1613.7333 | U25: 1640.1089 | V25: 1667.4398 | W25: 1695.8134 | X25: 1724.8636 | Y25: 1752.9756 | Z25: 1781.3413 | AA25: 1810.3131 | AB25: 1840.631 | AC25: 1874.0067 | AD25: 1909.9596 | AE25: 1947.4512 | AF25: 1987.4026 | AG25: 2028.574 | AH25: 2071.0894 | AI25: 0.017138
B26: (billion ton miles traveled)
A27: TKI000:ba_Rail | B27: Rail | C27: 1807.9623 | D27: 1730.8405 | E27: 1660.0334 | F27: 1651.2594 | G27: 1652.7242 | H27: 1638.4692 | I27: 1604.7769 | J27: 1643.9995 | K27: 1652.7871 | L27: 1662.7437 | M27: 1655.604 | N27: 1648.3021 | O27: 1654.8008 | P27: 1663.8508 | Q27: 1673.921 | R27: 1684.4979 | S27: 1686.808 | T27: 1698.2738 | U27: 1704.6904 | V27: 1701.2555 | W27: 1711.9681 | X27: 1715.1283 | Y27: 1722.2583 | Z27: 1735.2404 | AA27: 1747.2886 | AB27: 1760.9611 | AC27: 1777.2797 | AD27: 1802.0692 | AE27: 1818.0815 | AF27: 1839.249 | AG27: 1861.9969 | AH27: 1888.5421 | AI27: 0.001408
A28: TKI000:ba_DomesticShipp | B28: Domestic Shipping | C28: 416.68076 | D28: 409.15491 | E28: 404.52988 | F28: 396.47797 | G28: 388.98981 | H28: 379.45697 | I28: 370.07324 | J28: 361.44611 | K28: 352.76407 | L28: 343.56067 | M28: 333.81879 | N28: 323.79498 | O28: 320.25205 | P28: 316.14533 | Q28: 312.6521 | R28: 308.38547 | S28: 304.23715 | T28: 300.63773 | U28: 296.55325 | V28: 292.41882 | W28: 288.76395 | X28: 284.95685 | Y28: 283.66168 | Z28: 282.64859 | AA28: 281.33289 | AB28: 280.51184 | AC28: 279.8728 | AD28: 280.18787 | AE28: 279.40164 | AF28: 279.35028 | AG28: 279.69217 | AH28: 280.25092 | AI28: -0.012713
B30: Energy Efficiency Indicators
B31: (miles per gallon)
A32: TKI000:ca_AvgCAFEStand | B32: New Light-Duty Vehicle CAFE Standard 2/ | C32: 34.359936 | D32: 35.284824 | E32: 36.831001 | F32: 38.399506 | G32: 40.110416 | H32: 41.695168 | I32: 43.801582 | J32: 43.785816 | K32: 43.851311 | L32: 43.92421 | M32: 44.014652 | N32: 44.196796 | O32: 44.303349 | P32: 44.390171 | Q32: 44.493732 | R32: 44.60854 | S32: 44.698715 | T32: 44.789574 | U32: 44.882374 | V32: 44.963428 | W32: 45.039089 | X32: 45.11404 | Y32: 45.19231 | Z32: 45.25729 | AA32: 45.303879 | AB32: 45.340485 | AC32: 45.390274 | AD32: 45.422104 | AE32: 45.456978 | AF32: 45.47982 | AG32: 45.506924 | AH32: 45.514236 | AI32: 0.00911
A33: TKI000:ca_CarCAFEStand | B33: New Car 2/ | C33: 40.551155 | D33: 42.338371 | E33: 44.294533 | F33: 46.414017 | G33: 48.711933 | H33: 50.082985 | I33: 52.773457 | J33: 52.773731 | K33: 52.786339 | L33: 52.786339 | M33: 52.798622 | N33: 52.841564 | O33: 52.841564 | P33: 52.841564 | Q33: 52.841564 | R33: 52.841564 | S33: 52.841564 | T33: 52.841564 | U33: 52.841564 | V33: 52.841564 | W33: 52.841564 | X33: 52.842728 | Y33: 52.844788 | Z33: 52.844788 | AA33: 52.844788 | AB33: 52.844788 | AC33: 52.84753 | AD33: 52.84753 | AE33: 52.848724 | AF33: 52.848724 | AG33: 52.84988 | AH33: 52.84988 | AI33: 0.008582
A34: TKI000:ca_TwukCAFEStand | B34: New Light Truck 2/ | C34: 30.2997 | D34: 30.889185 | E34: 32.380001 | F34: 33.7799 | G34: 35.309071 | H34: 36.976479 | I34: 38.765255 | J34: 38.772991 | K34: 38.772991 | L34: 38.772991 | M34: 38.772991 | N34: 38.772991 | O34: 38.772991 | P34: 38.772991 | Q34: 38.772991 | R34: 38.772991 | S34: 38.772991 | T34: 38.772991 | U34: 38.772991 | V34: 38.772991 | W34: 38.772991 | X34: 38.772991 | Y34: 38.772991 | Z34: 38.772991 | AA34: 38.772991 | AB34: 38.772991 | AC34: 38.772991 | AD34: 38.772991 | AE34: 38.772991 | AF34: 38.772991 | AG34: 38.772991 | AH34: 38.773014 | AI34: 0.007986
A35: TKI000:ca_NewVehCred | B35: Compliance New Light-Duty Vehicle 3/ | C35: 35.348213 | D35: 36.238525 | E35: 37.596539 | F35: 39.37933 | G35: 40.901978 | H35: 42.360344 | I35: 44.567291 | J35: 44.831284 | K35: 44.934002 | L35: 45.040806 | M35: 45.183762 | N35: 45.495754 | O35: 45.787571 | P35: 46.034676 | Q35: 46.317448 | R35: 46.60257 | S35: 46.849384 | T35: 47.060444 | U35: 47.280041 | V35: 47.481697 | W35: 47.659729 | X35: 47.83065 | Y35: 47.980515 | Z35: 48.108444 | AA35: 48.197189 | AB35: 48.262737 | AC35: 48.3549 | AD35: 48.425739 | AE35: 48.504185 | AF35: 48.562855 | AG35: 48.634819 | AH35: 48.674248 | AI35: 0.010373
A36: TKI000:ca_NewCarCred | B36: New Car 3/ | C36: 42.356316 | D36: 43.482601 | E36: 45.545635 | F36: 47.835651 | G36: 49.962463 | H36: 51.477432 | I36: 54.131187 | J36: 54.288181 | K36: 54.274036 | L36: 54.345482 | M36: 54.476521 | N36: 54.755726 | O36: 55.19865 | P36: 55.546597 | Q36: 55.91061 | R36: 56.268238 | S36: 56.616009 | T36: 56.875309 | U36: 57.153564 | V36: 57.42186 | W36: 57.643833 | X36: 57.841148 | Y36: 57.984364 | Z36: 58.118862 | AA36: 58.223202 | AB36: 58.303883 | AC36: 58.397022 | AD36: 58.51268 | AE36: 58.621887 | AF36: 58.738182 | AG36: 58.859608 | AH36: 58.987617 | AI36: 0.010741
A37: TKI000:ca_NewTwukCred | B37: New Light Truck 3/ | C37: 30.865908 | D37: 31.724129 | E37: 32.910633 | F37: 34.543072 | G37: 35.889904 | H37: 37.32349 | I37: 39.26572 | J37: 39.595291 | K37: 39.653728 | L37: 39.666462 | M37: 39.683132 | N37: 39.748066 | O37: 39.797894 | P37: 39.852974 | Q37: 39.920296 | R37: 39.970135 | S37: 40.005047 | T37: 40.02647 | U37: 40.043442 | V37: 40.056137 | W37: 40.064693 | X37: 40.075218 | Y37: 40.075615 | Z37: 40.069695 | AA37: 40.055481 | AB37: 40.038029 | AC37: 40.029408 | AD37: 40.008018 | AE37: 39.996075 | AF37: 39.972542 | AG37: 39.958122 | AH37: 39.929474 | AI37: 0.00834
A38: TKI000:ca_TestedNewVeh | B38: Tested New Light-Duty Vehicle 4/ | C38: 34.962322 | D38: 35.991081 | E38: 37.288235 | F38: 39.051094 | G38: 40.553646 | H38: 41.976017 | I38: 44.120575 | J38: 44.336227 | K38: 44.414066 | L38: 44.500385 | M38: 44.615799 | N38: 44.876507 | O38: 45.111603 | P38: 45.306648 | Q38: 45.531082 | R38: 45.75457 | S38: 45.942371 | T38: 46.09964 | U38: 46.263412 | V38: 46.41185 | W38: 46.541386 | X38: 46.666012 | Y38: 46.777721 | Z38: 46.871037 | AA38: 46.931049 | AB38: 46.971848 | AC38: 47.034363 | AD38: 47.077263 | AE38: 47.126358 | AF38: 47.158012 | AG38: 47.200371 | AH38: 47.214767 | AI38: 0.009739
A39: TKI000:ca_TestedNewCar | B39: New Car 4/ | C39: 41.715885 | D39: 42.872379 | E39: 44.733494 | F39: 46.957069 | G39: 49.003487 | H39: 50.41568 | I39: 52.908669 | J39: 53.035347 | K39: 53.002815 | L39: 53.031281 | M39: 53.101597 | N39: 53.283951 | O39: 53.59354 | P39: 53.82737 | Q39: 54.068119 | R39: 54.300163 | S39: 54.521736 | T39: 54.675041 | U39: 54.843937 | V39: 55.006741 | W39: 55.136219 | X39: 55.248566 | Y39: 55.326115 | Z39: 55.397579 | AA39: 55.445976 | AB39: 55.477283 | AC39: 55.516716 | AD39: 55.571735 | AE39: 55.621513 | AF39: 55.67548 | AG39: 55.732971 | AH39: 55.794552 | AI39: 0.009425
A40: TKI000:ca_TestedNewTwuk | B40: New Light Truck 4/ | C40: 30.612513 | D40: 31.651661 | E40: 32.830524 | F40: 34.456524 | G40: 35.799854 | H40: 37.22747 | I40: 39.151051 | J40: 39.426971 | K40: 39.465645 | L40: 39.475208 | M40: 39.488102 | N40: 39.541683 | O40: 39.581787 | P40: 39.624954 | Q40: 39.679688 | R40: 39.716709 | S40: 39.740402 | T40: 39.750675 | U40: 39.756599 | V40: 39.759041 | W40: 39.758137 | X40: 39.759655 | Y40: 39.75499 | Z40: 39.745636 | AA40: 39.729229 | AB40: 39.710049 | AC40: 39.698334 | AD40: 39.675388 | AE40: 39.66048 | AF40: 39.635681 | AG40: 39.61845 | AH40: 39.589142 | AI40: 0.00833
A41: TKI000:ca_OnRoadNewVeh | B41: On-Road New Light-Duty Vehicle 5/ | C41: 28.524006 | D41: 29.363092 | E41: 30.420794 | F41: 31.858644 | G41: 33.084072 | H41: 34.244457 | I41: 35.994076 | J41: 36.169979 | K41: 36.233746 | L41: 36.304462 | M41: 36.398952 | N41: 36.612297 | O41: 36.804462 | P41: 36.963898 | Q41: 37.147385 | R41: 37.330143 | S41: 37.483685 | T41: 37.612339 | U41: 37.7463 | V41: 37.867699 | W41: 37.973671 | X41: 38.075638 | Y41: 38.16708 | Z41: 38.243473 | AA41: 38.292618 | AB41: 38.326035 | AC41: 38.377235 | AD41: 38.412346 | AE41: 38.45253 | AF41: 38.478436 | AG41: 38.513092 | AH41: 38.524834 | AI41: 0.009742
A42: TKI000:ca_OnRoadNewCar | B42: New Car 5/ | C42: 34.065807 | D42: 35.010216 | E42: 36.530029 | F42: 38.345837 | G42: 40.016972 | H42: 41.170189 | I42: 43.205997 | J42: 43.309448 | K42: 43.282879 | L42: 43.306126 | M42: 43.363548 | N42: 43.512459 | O42: 43.765274 | P42: 43.956223 | Q42: 44.152824 | R42: 44.342316 | S42: 44.523254 | T42: 44.648445 | U42: 44.786369 | V42: 44.919315 | W42: 45.025051 | X42: 45.116795 | Y42: 45.180122 | Z42: 45.23848 | AA42: 45.278004 | AB42: 45.303566 | AC42: 45.33577 | AD42: 45.380699 | AE42: 45.421349 | AF42: 45.46542 | AG42: 45.512367 | AH42: 45.562653 | AI42: 0.009425
A43: TKI000:ca_OnRoadNewTwuk | B43: New Light Truck 5/ | C43: 24.960157 | D43: 25.807436 | E43: 26.768633 | F43: 28.094404 | G43: 29.189699 | H43: 30.353718 | I43: 31.922125 | J43: 32.147099 | K43: 32.178631 | L43: 32.186428 | M43: 32.196941 | N43: 32.240631 | O43: 32.273327 | P43: 32.308525 | Q43: 32.353153 | R43: 32.383339 | S43: 32.402657 | T43: 32.411034 | U43: 32.415863 | V43: 32.417854 | W43: 32.417118 | X43: 32.418354 | Y43: 32.414551 | Z43: 32.406925 | AA43: 32.393547 | AB43: 32.377907 | AC43: 32.368355 | AD43: 32.349648 | AE43: 32.33749 | AF43: 32.317272 | AG43: 32.303223 | AH43: 32.279324 | AI43: 0.00833
... A47: TKI000:ca_FreightTruck | B47: Freight Truck | C47: 7.119165 | D47: 7.17094 | E47: 7.235986 | F47: 7.3073 | G47: 7.388516 | H47: 7.48128 | I47: 7.586367 | J47: 7.703835 | K47: 7.834221 | L47: 7.967885 | M47: 8.108215 | N47: 8.251791 | O47: 8.396469 | P47: 8.537745 | Q47: 8.669586 | R47: 8.791187 | S47: 8.902438 | T47: 9.004374 | U47: 9.096915 | V47: 9.181 | W47: 9.258368 | X47: 9.327685 | Y47: 9.391495 | Z47: 9.448672 | AA47: 9.500283 | AB47: 9.547491 | AC47: 9.591628 | AD47: 9.634123 | AE47: 9.675597 | AF47: 9.716289 | AG47: 9.756433 | AH47: 9.797481 | AI47: 0.010354
B48: (seat miles per gallon)
A49: TKI000:ca_Aircraft | B49: Aircraft | C49: 69.061409 | D49: 69.384445 | E49: 69.706734 | F49: 70.035477 | G49: 70.376755 | H49: 70.734436 | I49: 71.082642 | J49: 71.464615 | K49: 71.895363 | L49: 72.350365 | M49: 72.824806 | N49: 73.293343 | O49: 73.757736 | P49: 74.234024 | Q49: 74.700493 | R49: 75.177055 | S49: 75.653641 | T49: 76.137352 | U49: 76.621902 | V49: 77.107964 | W49: 77.601532 | X49: 78.09996 | Y49: 78.56591 | Z49: 79.031158 | AA49: 79.489037 | AB49: 79.918777 | AC49: 80.345123 | AD49: 80.761703 | AE49: 81.17762 | AF49: 81.591446 | AG49: 81.990547 | AH49: 82.372414 | AI49: 0.005702
B50: (ton miles/thousand Btu)
A51: TKI000:ca_Rail | B51: Rail | C51: 3.466884 | D51: 3.489371 | E51: 3.512003 | F51: 3.534782 | G51: 3.55771 | H51: 3.580785 | I51: 3.60401 | J51: 3.627386 | K51: 3.650914 | L51: 3.674594 | M51: 3.698428 | N51: 3.722416 | O51: 3.74656 | P51: 3.77086 | Q51: 3.795318 | R51: 3.819935 | S51: 3.844712 | T51: 3.869649 | U51: 3.894748 | V51: 3.920009 | W51: 3.945435 | X51: 3.971025 | Y51: 3.996782 | Z51: 4.022705 | AA51: 4.048797 | AB51: 4.075058 | AC51: 4.101489 | AD51: 4.128091 | AE51: 4.154866 | AF51: 4.181815 | AG51: 4.208939 | AH51: 4.236238 | AI51: 0.006486
A52: TKI000:ca_DomesticShipp | B52: Domestic Shipping | C52: 4.813365 | D52: 4.84196 | E52: 4.870726 | F52: 4.899663 | G52: 4.928772 | H52: 4.958054 | I52: 4.987509 | J52: 5.01714 | K52: 5.046947 | L52: 5.076931 | M52: 5.107092 | N52: 5.137434 | O52: 5.167955 | P52: 5.198658 | Q52: 5.229543 | R52: 5.260611 | S52: 5.291864 | T52: 5.323303 | U52: 5.354929 | V52: 5.386742 | W52: 5.418745 | X52: 5.450938 | Y52: 5.483322 | Z52: 5.515898 | AA52: 5.548667 | AB52: 5.581632 | AC52: 5.614792 | AD52: 5.64815 | AE52: 5.681705 | AF52: 5.71546 | AG52: 5.749416 | AH52: 5.783573 | AI52: 0.005941
B54: Energy Use by Mode
B55: (quadrillion Btu)
A56: TKI000:da_Light-DutyVeh | B56: Light-Duty Vehicles | C56: 15.312445 | D56: 15.30714 | E56: 15.236718 | F56: 15.068806 | G56: 14.804813 | H56: 14.499307 | I56: 14.167157 | J56: 13.909196 | K56: 13.685458 | L56: 13.482776 | M56: 13.299863 | N56: 13.139069 | O56: 13.002687 | P56: 12.863337 | Q56: 12.735183 | R56: 12.602709 | S56: 12.470579 | T56: 12.372916 | U56: 12.287333 | V56: 12.215109 | W56: 12.15875 | X56: 12.118073 | Y56: 12.081137 | Z56: 12.057517 | AA56: 12.045367 | AB56: 12.044356 | AC56: 12.055041 | AD56: 12.085419 | AE56: 12.129275 | AF56: 12.190246 | AG56: 12.262823 | AH56: 12.346762 | AI56: -0.00692
A57: TKI000:da_CommercialLig | B57: Commercial Light Trucks 1/ | C57: 0.891028 | D57: 0.891903 | E57: 0.895889 | F57: 0.89787 | G57: 0.89709 | H57: 0.89318 | I57: 0.892636 | J57: 0.892015 | K57: 0.892606 | L57: 0.893648 | M57: 0.895486 | N57: 0.896713 | O57: 0.901317 | P57: 0.904846 | Q57: 0.909857 | R57: 0.914968 | S57: 0.920246 | T57: 0.927079 | U57: 0.934283 | V57: 0.94158 | W57: 0.949261 | X57: 0.957789 | Y57: 0.966845 | Z57: 0.975906 | AA57: 0.98611 | AB57: 0.997791 | AC57: 1.010687 | AD57: 1.027074 | AE57: 1.040264 | AF57: 1.054572 | AG57: 1.069246 | AH57: 1.083799 | AI57: 0.006338
A58: TKI000:da_BusTransporta | B58: Bus Transportation | C58: 0.238531 | D58: 0.23989 | E58: 0.241259 | F58: 0.242609 | G58: 0.243913 | H58: 0.245252 | I58: 0.246684 | J58: 0.248104 | K58: 0.249516 | L58: 0.250953 | M58: 0.252383 | N58: 0.253717 | O58: 0.25501 | P58: 0.256269 | Q58: 0.257406 | R58: 0.258486 | S58: 0.259508 | T58: 0.26047 | U58: 0.261377 | V58: 0.262223 | W58: 0.263003 | X58: 0.263714 | Y58: 0.264353 | Z58: 0.264925 | AA58: 0.265439 | AB58: 0.265904 | AC58: 0.266333 | AD58: 0.266748 | AE58: 0.267177 | AF58: 0.267648 | AG58: 0.268208 | AH58: 0.268877 | AI58: 0.00387
A59: TKI000:da_FreightTrucks | B59: Freight Trucks | C59: 5.880958 | D59: 5.904005 | E59: 5.951757 | F59: 5.983958 | G59: 6.010647 | H59: 5.993482 | I59: 5.972905 | J59: 5.942755 | K59: 5.913831 | L59: 5.875737 | M59: 5.836956 | N59: 5.783237 | O59: 5.760028 | P59: 5.727354 | Q59: 5.709549 | R59: 5.688765 | S59: 5.682989 | T59: 5.688041 | U59: 5.689445 | V59: 5.697817 | W59: 5.709255 | X59: 5.729411 | Y59: 5.754163 | Z59: 5.786846 | AA59: 5.821076 | AB59: 5.869198 | AC59: 5.927293 | AD59: 6.001935 | AE59: 6.05612 | AF59: 6.125846 | AG59: 6.200032 | AH59: 6.275017 | AI59: 0.002094
A60: TKI000:da_Rail,Passenge | B60: Rail, Passenger | C60: 0.049125 | D60: 0.050002 | E60: 0.050829 | F60: 0.051513 | G60: 0.052173 | H60: 0.05283 | I60: 0.053461 | J60: 0.054088 | K60: 0.054688 | L60: 0.055315 | M60: 0.05594 | N60: 0.056411 | O60: 0.057057 | P60: 0.057683 | Q60: 0.058288 | R60: 0.058841 | S60: 0.059417 | T60: 0.059977 | U60: 0.060532 | V60: 0.061099 | W60: 0.061667 | X60: 0.062234 | Y60: 0.062772 | Z60: 0.063311 | AA60: 0.063864 | AB60: 0.064422 | AC60: 0.064971 | AD60: 0.065568 | AE60: 0.066151 | AF60: 0.066765 | AG60: 0.067348 | AH60: 0.067945 | AI60: 0.010517
A61: TKI000:da_Rail,Freight | B61: Rail, Freight | C61: 0.521495 | D61: 0.496032 | E61: 0.472674 | F61: 0.467146 | G61: 0.464547 | H61: 0.457573 | I61: 0.445275 | J61: 0.453219 | K61: 0.452705 | L61: 0.452497 | M61: 0.447651 | N61: 0.442804 | O61: 0.441685 | P61: 0.441239 | Q61: 0.441049 | R61: 0.440976 | S61: 0.438735 | T61: 0.43887 | U61: 0.43769 | V61: 0.433993 | W61: 0.433911 | X61: 0.431911 | Y61: 0.430911 | Z61: 0.431362 | AA61: 0.431558 | AB61: 0.432132 | AC61: 0.433326 | AD61: 0.436538 | AE61: 0.437579 | AF61: 0.439821 | AG61: 0.442391 | AH61: 0.445806 | AI61: -0.005046
A62: TKI000:da_Shipping,Dome | B62: Shipping, Domestic | C62: 0.089409 | D62: 0.087947 | E62: 0.085825 | F62: 0.083144 | G62: 0.081043 | H62: 0.07854 | I62: 0.076103 | J62: 0.073851 | K62: 0.071606 | L62: 0.069278 | M62: 0.066865 | N62: 0.064421 | O62: 0.063281 | P62: 0.062044 | Q62: 0.060933 | R62: 0.059681 | S62: 0.058471 | T62: 0.057385 | U62: 0.056209 | V62: 0.055025 | W62: 0.053933 | X62: 0.052831 | Y62: 0.052283 | Z62: 0.051792 | AA62: 0.051248 | AB62: 0.050799 | AC62: 0.050387 | AD62: 0.050149 | AE62: 0.049715 | AF62: 0.049415 | AG62: 0.049187 | AH62: 0.048997 | AI62: -0.019215
A63: TKI000:da_Shipping,Inte | B63: Shipping, International | C63: 0.927327 | D63: 1.008838 | E63: 0.971116 | F63: 0.886972 | G63: 0.891949 | H63: 0.875923 | I63: 0.889297 | J63: 0.864365 | K63: 0.875667 | L63: 0.876735 | M63: 0.862752 | N63: 0.876611 | O63: 0.877461 | P63: 0.865944 | Q63: 0.876064 | R63: 0.876109 | S63: 0.872912 | T63: 0.862727 | U63: 0.869371 | V63: 0.858956 | W63: 0.858436 | X63: 0.864699 | Y63: 0.853751 | Z63: 0.852309 | AA63: 0.849807 | AB63: 0.846604 | AC63: 0.844515 | AD63: 0.843746 | AE63: 0.841557 | AF63: 0.840549 | AG63: 0.839989 | AH63: 0.840091 | AI63: -0.003182
A64: TKI000:da_RecreationalB | B64: Recreational Boats | C64: 0.245487 | D64: 0.246247 | E64: 0.246891 | F64: 0.247228 | G64: 0.247401 | H64: 0.247561 | I64: 0.247747 | J64: 0.247872 | K64: 0.247948 | L64: 0.248034 | M64: 0.248119 | N64: 0.248128 | O64: 0.248119 | P64: 0.248079 | Q64: 0.247943 | R64: 0.247704 | S64: 0.247382 | T64: 0.247051 | U64: 0.246672 | V64: 0.246271 | W64: 0.245845 | X64: 0.245364 | Y64: 0.244837 | Z64: 0.244243 | AA64: 0.243636 | AB64: 0.243037 | AC64: 0.242467 | AD64: 0.241926 | AE64: 0.241387 | AF64: 0.240858 | AG64: 0.240316 | AH64: 0.23976 | AI64: -0.000761
A65: TKI000:da_Air | B65: Air | C65: 2.640944 | D65: 2.673067 | E65: 2.70635 | F65: 2.732191 | G65: 2.752433 | H65: 2.776094 | I65: 2.803131 | J65: 2.82868 | K65: 2.853517 | L65: 2.879811 | M65: 2.908522 | N65: 2.937199 | O65: 2.967398 | P65: 2.997719 | Q65: 3.0276 | R65: 3.053208 | S65: 3.077652 | T65: 3.104426 | U65: 3.132126 | V65: 3.160325 | W65: 3.189834 | X65: 3.220148 | Y65: 3.250173 | Z65: 3.279953 | AA65: 3.310731 | AB65: 3.34457 | AC65: 3.383125 | AD65: 3.426044 | AE65: 3.471181 | AF65: 3.520372 | AG65: 3.571743 | AH65: 3.624813 | AI65: 0.010267
A66: TKI000:da_MilitaryUse | B66: Military Use | C66: 0.512501 | D66: 0.526369 | E66: 0.515977 | F66: 0.504054 | G66: 0.488973 | H66: 0.47893 | I66: 0.47706 | J66: 0.475186 | K66: 0.474613 | L66: 0.477166 | M66: 0.476099 | N66: 0.47539 | O66: 0.475478 | P66: 0.475588 | Q66: 0.475726 | R66: 0.475885 | S66: 0.476065 | T66: 0.476268 | U66: 0.476499 | V66: 0.476747 | W66: 0.477015 | X66: 0.477302 | Y66: 0.4776 | Z66: 0.477913 | AA66: 0.478237 | AB66: 0.478571 | AC66: 0.478915 | AD66: 0.479268 | AE66: 0.479627 | AF66: 0.479993 | AG66: 0.480364 | AH66: 0.480741 | AI66: -0.002062
A67: TKI000:da_Lubricants | B67: Lubricants | C67: 0.131469 | D67: 0.130998 | E67: 0.130617 | F67: 0.130166 | G67: 0.129716 | H67: 0.129236 | I67: 0.128717 | J67: 0.12821 | K67: 0.127738 | L67: 0.127329 | M67: 0.126997 | N67: 0.126676 | O67: 0.126395 | P67: 0.126142 | Q67: 0.125896 | R67: 0.125704 | S67: 0.12555 | T67: 0.12549 | U67: 0.125464 | V67: 0.125469 | W67: 0.125512 | X67: 0.125529 | Y67: 0.125533 | Z67: 0.125612 | AA67: 0.125667 | AB67: 0.125765 | AC67: 0.12594 | AD67: 0.126144 | AE67: 0.126361 | AF67: 0.126627 | AG67: 0.126863 | AH67: 0.127078 | AI67: -0.001095
... A69: TKI000:da_Total | B69: Total | C69: 28.112638 | D69: 28.229656 | E69: 28.207281 | F69: 28.00946 | G69: 27.785589 | H69: 27.463036 | I69: 27.152018 | J69: 26.878296 | K69: 26.655809 | L69: 26.445753 | M69: 26.240934 | N69: 26.065762 | O69: 25.948496 | P69: 25.80217 | Q69: 25.701551 | R69: 25.580608 | S69: 25.470058 | T69: 25.412188 | U69: 25.37376 | V69: 25.339329 | W69: 25.342278 | X69: 25.372105 | Y69: 25.393759 | Z69: 25.455908 | AA69: 25.525803 | AB69: 25.624594 | AC69: 25.752531 | AD69: 25.930012 | AE69: 26.094328 | AF69: 26.300638 | AG69: 26.523647 | AH69: 26.762129 | AI69: -0.001587
B71: (million barrels per day oil equivalent)
A72: TKI000:ea_Light-DutyVeh | B72: Light-Duty Vehicles | C72: 8.299458 | D72: 8.297431 | E72: 8.258867 | F72: 8.167576 | G72: 8.024354 | H72: 7.858614 | I72: 7.680162 | J72: 7.54128 | K72: 7.420378 | L72: 7.311098 | M72: 7.21259 | N72: 7.126847 | O72: 7.05311 | P72: 6.977902 | Q72: 6.908753 | R72: 6.837132 | S72: 6.765776 | T72: 6.712733 | U72: 6.666179 | V72: 6.626825 | W72: 6.595639 | X72: 6.572973 | Y72: 6.552473 | Z72: 6.538953 | AA72: 6.532093 | AB72: 6.531311 | AC72: 6.536314 | AD72: 6.552357 | AE72: 6.575637 | AF72: 6.60852 | AG72: 6.647728 | AH72: 6.693235 | AI72: -0.006914
A73: TKI000:ea_CommercialLig | B73: Commercial Light Trucks 1/ | C73: 0.463645 | D73: 0.463938 | E73: 0.465786 | F73: 0.466659 | G73: 0.466108 | H73: 0.464014 | I73: 0.463842 | J73: 0.463561 | K73: 0.463877 | L73: 0.46449 | M73: 0.465553 | N73: 0.466452 | O73: 0.468995 | P73: 0.470979 | Q73: 0.473754 | R73: 0.476574 | S73: 0.479564 | T73: 0.483356 | U73: 0.487438 | V73: 0.491518 | W73: 0.495649 | X73: 0.500162 | Y73: 0.505092 | Z73: 0.509883 | AA73: 0.515413 | AB73: 0.521692 | AC73: 0.528346 | AD73: 0.53696 | AE73: 0.543866 | AF73: 0.551526 | AG73: 0.559404 | AH73: 0.567315 | AI73: 0.006531
A74: TKI000:ea_BusTransporta | B74: Bus Transportation | C74: 0.115227 | D74: 0.115901 | E74: 0.116581 | F74: 0.117251 | G74: 0.117882 | H74: 0.118551 | I74: 0.11926 | J74: 0.11995 | K74: 0.120641 | L74: 0.12134 | M74: 0.122028 | N74: 0.122645 | O74: 0.12329 | P74: 0.123892 | Q74: 0.124421 | R74: 0.124924 | S74: 0.125429 | T74: 0.125889 | U74: 0.126375 | V74: 0.126791 | W74: 0.127173 | X74: 0.127473 | Y74: 0.127798 | Z74: 0.128063 | AA74: 0.128311 | AB74: 0.128539 | AC74: 0.128753 | AD74: 0.128956 | AE74: 0.12916 | AF74: 0.129386 | AG74: 0.129657 | AH74: 0.129983 | AI74: 0.003895
A75: TKI000:ea_FreightTrucks | B75: Freight Trucks | C75: 2.827296 | D75: 2.838177 | E75: 2.861533 | F75: 2.877479 | G75: 2.89041 | H75: 2.883003 | I75: 2.873901 | J75: 2.859937 | K75: 2.846777 | L75: 2.829164 | M75: 2.811116 | N75: 2.785219 | O75: 2.775341 | P75: 2.760258 | Q75: 2.752032 | R75: 2.742399 | S75: 2.740685 | T75: 2.743816 | U75: 2.746544 | V75: 2.751515 | W75: 2.757982 | X75: 2.767448 | Y75: 2.780638 | Z75: 2.797015 | AA75: 2.814377 | AB75: 2.838605 | AC75: 2.867797 | AD75: 2.904866 | AE75: 2.931931 | AF75: 2.966593 | AG75: 3.003496 | AH75: 3.040895 | AI75: 0.002352
A76: TKI000:ea_Rail,Passenge | B76: Rail, Passenger | C76: 0.023255 | D76: 0.023671 | E76: 0.024065 | F76: 0.02439 | G76: 0.024703 | H76: 0.025016 | I76: 0.025317 | J76: 0.025614 | K76: 0.025899 | L76: 0.026196 | M76: 0.026491 | N76: 0.026709 | O76: 0.027018 | P76: 0.027313 | Q76: 0.027597 | R76: 0.027856 | S76: 0.02813 | T76: 0.028393 | U76: 0.028663 | V76: 0.028932 | W76: 0.029202 | X76: 0.029463 | Y76: 0.02972 | Z76: 0.029973 | AA76: 0.030235 | AB76: 0.030499 | AC76: 0.030761 | AD76: 0.031043 | AE76: 0.031319 | AF76: 0.031609 | AG76: 0.031885 | AH76: 0.032168 | AI76: 0.010521
A77: TKI000:ea_Rail,Freight | B77: Rail, Freight | C77: 0.247425 | D77: 0.235349 | E77: 0.224294 | F77: 0.221703 | G77: 0.220458 | H77: 0.217186 | I77: 0.211368 | J77: 0.215123 | K77: 0.214871 | L77: 0.214751 | M77: 0.212415 | N77: 0.21003 | O77: 0.209515 | P77: 0.209267 | Q77: 0.209119 | R77: 0.209029 | S77: 0.207961 | T77: 0.207993 | U77: 0.207494 | V77: 0.205728 | W77: 0.205676 | X77: 0.20464 | Y77: 0.204172 | Z77: 0.204352 | AA77: 0.204426 | AB77: 0.204688 | AC77: 0.205248 | AD77: 0.206758 | AE77: 0.207232 | AF77: 0.208277 | AG77: 0.209481 | AH77: 0.211086 | AI77: -0.005111
A78: TKI000:ea_Shipping,Dome | B78: Shipping, Domestic | C78: 0.042333 | D78: 0.041603 | E78: 0.040635 | F78: 0.0394 | G78: 0.038405 | H78: 0.037229 | I78: 0.03608 | J78: 0.035014 | K78: 0.033953 | L78: 0.032851 | M78: 0.031707 | N78: 0.030539 | O78: 0.030006 | P78: 0.029419 | Q78: 0.028888 | R78: 0.02829 | S78: 0.02772 | T78: 0.027204 | U78: 0.02666 | V78: 0.026101 | W78: 0.025585 | X78: 0.025052 | Y78: 0.024795 | Z78: 0.024559 | AA78: 0.0243 | AB78: 0.024088 | AC78: 0.023893 | AD78: 0.023781 | AE78: 0.023574 | AF78: 0.02343 | AG78: 0.023322 | AH78: 0.023231 | AI78: -0.019171
A79: TKI000:ea_Shipping,Inte | B79: Shipping, International | C79: 0.419044 | D79: 0.459324 | E79: 0.440255 | F79: 0.398147 | G79: 0.4 | H79: 0.394394 | I79: 0.399222 | J79: 0.390425 | K79: 0.394511 | L79: 0.39495 | M79: 0.390033 | N79: 0.394978 | O79: 0.395364 | P79: 0.391307 | Q79: 0.394931 | R79: 0.394969 | S79: 0.393888 | T79: 0.390292 | U79: 0.392778 | V79: 0.389117 | W79: 0.38898 | X79: 0.391189 | Y79: 0.387353 | Z79: 0.386861 | AA79: 0.386008 | AB79: 0.384915 | AC79: 0.384226 | AD79: 0.384005 | AE79: 0.383269 | AF79: 0.382965 | AG79: 0.382823 | AH79: 0.382909 | AI79: -0.002905
A80: TKI000:ea_RecreationalB | B80: Recreational Boats | C80: 0.13308 | D80: 0.1335 | E80: 0.133858 | F80: 0.134049 | G80: 0.134152 | H80: 0.134247 | I80: 0.134378 | J80: 0.134477 | K80: 0.134548 | L80: 0.134625 | M80: 0.134701 | N80: 0.134737 | O80: 0.134762 | P80: 0.134771 | Q80: 0.134727 | R80: 0.134629 | S80: 0.134484 | T80: 0.134326 | U80: 0.134143 | V80: 0.133947 | W80: 0.133738 | X80: 0.133498 | Y80: 0.13323 | Z80: 0.132925 | AA80: 0.132613 | AB80: 0.132305 | AC80: 0.132013 | AD80: 0.131737 | AE80: 0.131461 | AF80: 0.131191 | AG80: 0.130914 | AH80: 0.130629 | AI80: -0.0006
A81: TKI000:ea_Air | B81: Air | C81: 1.277419 | D81: 1.292941 | E81: 1.309023 | F81: 1.321509 | G81: 1.33129 | H81: 1.342723 | I81: 1.35579 | J81: 1.368137 | K81: 1.380141 | L81: 1.392848 | M81: 1.406724 | N81: 1.420583 | O81: 1.435178 | P81: 1.449832 | Q81: 1.464272 | R81: 1.476649 | S81: 1.488463 | T81: 1.501402 | U81: 1.514789 | V81: 1.528416 | W81: 1.542677 | X81: 1.557327 | Y81: 1.571836 | Z81: 1.586228 | AA81: 1.601101 | AB81: 1.617454 | AC81: 1.636085 | AD81: 1.656825 | AE81: 1.678637 | AF81: 1.702407 | AG81: 1.727231 | AH81: 1.752876 | AI81: 0.010259
A82: TKI000:ea_MilitaryUse | B82: Military Use | C82: 0.245757 | D82: 0.251956 | E82: 0.247274 | F82: 0.241855 | G82: 0.234618 | H82: 0.229808 | I82: 0.228918 | J82: 0.228018 | K82: 0.227745 | L82: 0.22897 | M82: 0.228454 | N82: 0.228098 | O82: 0.228149 | P82: 0.228197 | Q82: 0.228253 | R82: 0.228318 | S82: 0.228408 | T82: 0.228501 | U82: 0.228635 | V82: 0.228755 | W82: 0.228885 | X82: 0.228999 | Y82: 0.229148 | Z82: 0.229291 | AA82: 0.229445 | AB82: 0.229607 | AC82: 0.229775 | AD82: 0.229945 | AE82: 0.230114 | AF82: 0.230288 | AG82: 0.230466 | AH82: 0.230647 | AI82: -0.002045
A83: TKI000:ea_Lubricants | B83: Lubricants | C83: 0.062101 | D83: 0.061879 | E83: 0.061699 | F83: 0.061486 | G83: 0.061273 | H83: 0.061047 | I83: 0.060801 | J83: 0.060562 | K83: 0.060339 | L83: 0.060146 | M83: 0.059989 | N83: 0.059838 | O83: 0.059705 | P83: 0.059585 | Q83: 0.059469 | R83: 0.059378 | S83: 0.059306 | T83: 0.059277 | U83: 0.059265 | V83: 0.059268 | W83: 0.059288 | X83: 0.059296 | Y83: 0.059298 | Z83: 0.059335 | AA83: 0.059361 | AB83: 0.059407 | AC83: 0.05949 | AD83: 0.059586 | AE83: 0.059688 | AF83: 0.059814 | AG83: 0.059926 | AH83: 0.060027 | AI83: -0.001095
... A85: TKI000:ea_Total | B85: Total | C85: 14.473433 | D85: 14.53084 | E85: 14.515177 | F85: 14.408682 | G85: 14.284176 | H85: 14.113085 | I85: 13.944188 | J85: 13.801455 | K85: 13.680749 | L85: 13.568763 | M85: 13.462358 | N85: 13.368217 | O85: 13.305375 | P85: 13.229243 | Q85: 13.172801 | R85: 13.107446 | S85: 13.048519 | T85: 13.017055 | U85: 12.995325 | V85: 12.977034 | W85: 12.975856 | X85: 12.986323 | Y85: 12.997333 | Z85: 13.026218 | AA85: 13.060641 | AB85: 13.110025 | AC85: 13.173438 | AD85: 13.26224 | AE85: 13.34532 | AF85: 13.450161 | AG85: 13.563889 | AH85: 13.686009 | AI85: -0.001803
B87: 1/ Commercial trucks 8,501 to 10,000 pounds gross vehicle weight rating.
B88: 2/ CAFE standard based on projected new vehicle sales.
B89: 3/ Includes CAFE credits for alternative fueled vehicle sales and credit banking.
B90: 4/ Environmental Protection Agency rated miles per gallon.
B91: 5/ Tested new vehicle efficiency revised for on-road performance.
B92: 6/ Combined "on-the-road" estimate for all cars and light trucks.
B93: CAFE = Corporate average fuel economy.
B94: Btu = British thermal unit.
B95: Note: Totals may not equal sum of components due to independent rounding.
B96: Sources: 2019: U.S. Energy Information Administration (EIA), Short-Term Energy Outlook, October 2019 and EIA, AEO2020 National
B97: Energy Modeling System run highogs.d112619a. Projections: EIA, AEO2020 National Energy Modeling System run highogs.d112619a.

Sheet AEO 2026 Table 7
A1: Table 7. Transportation Sector Key Indicators and Delivered Energy Consumption
A2: https://www.eia.gov/outlooks/aeo/data/browser/#/?id=7-AEO2026&cases=electrnp&sourcekey=0
A3: Thu Apr 23 2026 14:58:03 GMT-0700 (Pacific Daylight Time)
A4: Source: U.S. Energy Information Administration
B5: full name | C5: api key | D5: units | E5: 2025 | F5: 2026 | G5: 2027 | H5: 2028 | I5: 2029 | J5: 2030 | K5: 2031 | L5: 2032 | M5: 2033 | N5: 2034 | O5: 2035 | P5: 2036 | Q5: 2037 | R5: 2038 | S5: 2039 | T5: 2040 | U5: 2041 | V5: 2042 | W5: 2043 | X5: 2044 | Y5: 2045 | Z5: 2046 | AA5: 2047 | AB5: 2048 | AC5: 2049 | AD5: 2050 | AE5: Growth (2025-2050)
A6: Key Indicators
A7: Travel Indicators
A8: (billion vehicle miles traveled)
A9: Light-Duty Vehicles less than 8 | B9: 501 pounds | C9: Transportation: Travel Indicators: Light-Duty Vehicles <= 8,500 lbs: Alternative Electricity and Transportation | D9: AEO.2026.ELECTRNP.KEI_TRV_TRN_NA_LDV_NA_NA_BLNVEHMLS.A | E9: 2843.0325 | F9: 2863.5686 | G9: 2888.1982 | H9: 2904.0779 | I9: 2918.8098 | J9: 2931.437 | K9: 2942.6047 | L9: 2954.2515 | M9: 2961.9026 | N9: 2971.2754 | O9: 2978.2134 | P9: 2987.1594 | Q9: 2997.3567 | R9: 3007.7212 | S9: 3016.3496 | T9: 3025.5615 | U9: 3032.3416 | V9: 3038.7627 | W9: 3044.1992 | X9: 3050.2915 | Y9: 3055.739 | Z9: 3060.4001 | AA9: 3062.7534 | AB9: 3065.4651 | AC9: 3067.4841 | AD9: 3070.6538 | AE9: 0.3% | AF9: 0.3%
A10: Commercial Light Trucks | B10: Transportation: Travel Indicators: Commercial Light Trucks: Alternative Electricity and Transportation | C10: AEO.2026.ELECTRNP.KEI_TRV_TRN_NA_CML_NA_NA_BLNVEHMLS.A | D10: billion vehicle miles | E10: 91.39814 | F10: 91.778992 | G10: 93.221344 | H10: 94.140221 | I10: 95.009811 | J10: 96.166199 | K10: 97.196953 | L10: 98.315582 | M10: 99.238602 | N10: 100.24353 | O10: 101.30189 | P10: 102.37856 | Q10: 103.55357 | R10: 104.84109 | S10: 106.09736 | T10: 107.28613 | U10: 108.35976 | V10: 109.37235 | W10: 110.00733 | X10: 110.59621 | Y10: 111.26623 | Z10: 111.90553 | AA10: 112.50388 | AB10: 112.94838 | AC10: 113.49313 | AD10: 114.03658 | AE10: 0.9%
A11: Freight Trucks greater than 10 | B11: 000 pounds | C11: Transportation: Travel Indicators: Freight Trucks > 10,000 lbs.: Alternative Electricity and Transportation | D11: AEO.2026.ELECTRNP.KEI_TRV_TRN_NA_FGHT_NA_NA_BLNVEHMLS.A | E11: 341.04395 | F11: 342.36896 | G11: 344.61603 | H11: 347.24554 | I11: 349.67584 | J11: 353.39606 | K11: 356.18082 | L11: 359.42282 | M11: 362.12158 | N11: 365.4989 | O11: 368.98001 | P11: 372.37122 | Q11: 375.85315 | R11: 379.34448 | S11: 382.8548 | T11: 386.62579 | U11: 390.24112 | V11: 393.69708 | W11: 396.7334 | X11: 399.79425 | Y11: 403.50803 | Z11: 407.4259 | AA11: 411.55572 | AB11: 415.12537 | AC11: 418.81107 | AD11: 422.20337 | AE11: 0.9% | AF11: 0.9%
A12: (billion passenger miles traveled)
A13: Bus Transportation | B13: Transportation: Travel Indicators: Bus: Alternative Electricity and Transportation | C13: AEO.2026.ELECTRNP.KEI_TRV_TRN_NA_BST_NA_NA_BPM.A | D13: billion passenger miles | E13: 174.64743 | F13: 177.97359 | G13: 180.29126 | H13: 182.00543 | I13: 183.50909 | J13: 184.76764 | K13: 185.75305 | L13: 186.66608 | M13: 187.66562 | N13: 188.58444 | O13: 189.56187 | P13: 190.40323 | Q13: 191.26894 | R13: 192.04758 | S13: 192.82349 | T13: 193.59111 | U13: 194.2251 | V13: 194.85152 | W13: 195.41945 | X13: 195.96668 | Y13: 196.49443 | Z13: 196.9539 | AA13: 197.39342 | AB13: 197.76532 | AC13: 198.10574 | AD13: 198.4333 | AE13: 0.5%
A14: Passenger Rail | B14: Transportation: Travel Indicators: Passenger Rail: Alternative Electricity and Transportation | C14: AEO.2026.ELECTRNP.KEI_TRV_TRN_NA_RLP_NA_NA_BPM.A | D14: billion passenger miles | E14: 32.872635 | F14: 35.005196 | G14: 36.603188 | H14: 37.824776 | I14: 38.890263 | J14: 39.805248 | K14: 40.582108 | L14: 41.288425 | M14: 42.025204 | N14: 42.596252 | O14: 43.167667 | P14: 43.616798 | Q14: 44.095943 | R14: 44.532913 | S14: 44.880611 | T14: 45.240986 | U14: 45.551727 | V14: 45.864059 | W14: 46.124859 | X14: 46.413586 | Y14: 46.725052 | Z14: 46.982159 | AA14: 47.264282 | AB14: 47.468819 | AC14: 47.659672 | AD14: 47.840454 | AE14: 1.5%
A15: (billion seat miles available)
A16: Air | B16: Transportation: Travel Indicators: Air: Alternative Electricity and Transportation | C16: AEO.2026.ELECTRNP.KEI_TRV_TRN_NA_AIR_NA_NA_BLNSEATMLS.A | D16: billion seat miles | E16: 1422.0488 | F16: 1468.2333 | G16: 1496.5778 | H16: 1509.5959 | I16: 1529.527 | J16: 1555.4132 | K16: 1580.1011 | L16: 1611.1228 | M16: 1644.9456 | N16: 1682.2456 | O16: 1723.3199 | P16: 1754.5062 | Q16: 1785.8877 | R16: 1816.9982 | S16: 1846.7632 | T16: 1877.2617 | U16: 1905.856 | V16: 1936.1079 | W16: 1968.3762 | X16: 2000.6152 | Y16: 2033.1368 | Z16: 2064.2654 | AA16: 2092.603 | AB16: 2121.2827 | AC16: 2148.4807 | AD16: 2176.4729 | AE16: 1.7%
A17: (billion ton miles traveled)
A18: Rail | B18: Transportation: Travel Indicators: Rail: Alternative Electricity and Transportation | C18: AEO.2026.ELECTRNP.KEI_TRV_TRN_NA_RAIL_NA_NA_BLNTNMLS.A | D18: billion ton miles | E18: 1583.5666 | F18: 1549.2188 | G18: 1600.8337 | H18: 1569.6238 | I18: 1558.8303 | J18: 1570.807 | K18: 1532.1603 | L18: 1540.2323 | M18: 1548.5546 | N18: 1545.7983 | O18: 1552.4879 | P18: 1557.807 | Q18: 1565.3473 | R18: 1567.623 | S18: 1572.4233 | T18: 1575.6237 | U18: 1575.8467 | V18: 1572.6245 | W18: 1570.4214 | X18: 1572.225 | Y18: 1573.0564 | Z18: 1577.9888 | AA18: 1588.9343 | AB18: 1595.6223 | AC18: 1592.7251 | AD18: 1590.9067 | AE18: 0.0%
A19: Domestic Shipping | B19: Transportation: Travel Indicators: Domestic Shipping: Alternative Electricity and Transportation | C19: AEO.2026.ELECTRNP.KEI_TRV_TRN_NA_DMT_NA_NA_BLNTNMLS.A | D19: billion ton miles | E19: 481.83203 | F19: 486.21576 | G19: 483.39911 | H19: 481.59879 | I19: 478.7478 | J19: 479.17053 | K19: 477.21216 | L19: 476.96957 | M19: 475.51331 | N19: 475.26553 | O19: 474.7663 | P19: 473.51059 | Q19: 471.99933 | R19: 470.332 | S19: 469.49695 | T19: 468.92212 | U19: 468.94193 | V19: 468.05917 | W19: 466.67508 | X19: 465.00937 | Y19: 463.46417 | Z19: 462.65805 | AA19: 462.24152 | AB19: 460.68478 | AC19: 458.80084 | AD19: 456.8977 | AE19: -0.2%
A20: Energy Efficiency Indicators
A21: (miles per gallon)
A22: New Light-Duty Vehicle CAFE Standard | B22: Transportation: Energy Efficiency Indicators: CAFE Standard: New Light-Duty Vehicle: Alternative Electricity and Transportation | C22: AEO.2026.ELECTRNP.EFI_CAFES_TRN_HWY_LDTY_NEW_NA_MLSPGLN.A | D22: mpg | E22: 42.62487 | F22: 47.118061 | G22: 46.975002 | H22: 46.846443 | I22: 46.820732 | J22: 46.790005 | K22: 46.78952 | L22: 46.77977 | M22: 46.836681 | N22: 46.82415 | O22: 46.854034 | P22: 46.84911 | Q22: 46.861477 | R22: 46.858719 | S22: 46.856064 | T22: 46.852253 | U22: 46.836327 | V22: 46.826286 | W22: 46.802784 | X22: 46.785305 | Y22: 46.782948 | Z22: 46.75737 | AA22: 46.764141 | AB22: 46.749928 | AC22: 46.754528 | AD22: 46.744186 | AE22: 0.4%
A23: New Car | B23: Transportation: Energy Efficiency Indicators: CAFE Standard: New Car: Alternative Electricity and Transportation | C23: AEO.2026.ELECTRNP.EFI_CAFES_TRN_HWY_CAR_NEW_NA_MLSPGLN.A | D23: mpg | E23: 53.017715 | F23: 58.859119 | G23: 58.819542 | H23: 58.797932 | I23: 58.770973 | J23: 58.746857 | K23: 58.732121 | L23: 58.719112 | M23: 58.709141 | N23: 58.694 | O23: 58.690979 | P23: 58.681435 | Q23: 58.67659 | R23: 58.669403 | S23: 58.66399 | T23: 58.661999 | U23: 58.654724 | V23: 58.64856 | W23: 58.642673 | X23: 58.638657 | Y23: 58.637306 | Z23: 58.628986 | AA23: 58.625721 | AB23: 58.618374 | AC23: 58.616493 | AD23: 58.61145 | AE23: 0.4%
A24: New Light Truck | B24: Transportation: Energy Efficiency Indicators: CAFE Standard: New Light Truck: Alternative Electricity and Transportation | C24: AEO.2026.ELECTRNP.EFI_CAFES_TRN_HWY_LTRT_NEW_NA_MLSPGLN.A | D24: mpg | E24: 38.539085 | F24: 42.807068 | G24: 42.82156 | H24: 42.85144 | I24: 42.842434 | J24: 42.836998 | K24: 42.843082 | L24: 42.843014 | M24: 42.850456 | N24: 42.838711 | O24: 42.853836 | P24: 42.85487 | Q24: 42.865612 | R24: 42.866203 | S24: 42.873158 | T24: 42.889515 | U24: 42.886684 | V24: 42.887196 | W24: 42.886971 | X24: 42.891811 | Y24: 42.90353 | Z24: 42.893913 | AA24: 42.898521 | AB24: 42.890472 | AC24: 42.898075 | AD24: 42.896168 | AE24: 0.4%
A25: Compliance New Light-Duty Vehicle | B25: Transportation: Energy Efficiency Indicators: Compliance: New Light-Duty Vehicle: Alternative Electricity and Transportation | C25: AEO.2026.ELECTRNP.EFI_CAFEC_TRN_HWY_LDTY_NEW_NA_MLSPGLN.A | D25: mpg | E25: 41.120598 | F25: 43.50288 | G25: 45.394035 | H25: 46.047642 | I25: 45.540356 | J25: 45.070381 | K25: 45.189423 | L25: 45.253139 | M25: 45.964664 | N25: 46.418068 | O25: 47.036304 | P25: 47.522537 | Q25: 48.049854 | R25: 48.504993 | S25: 48.980587 | T25: 49.364521 | U25: 49.652382 | V25: 49.959145 | W25: 50.211224 | X25: 50.455971 | Y25: 50.752567 | Z25: 50.909824 | AA25: 51.186619 | AB25: 51.369267 | AC25: 51.613762 | AD25: 51.786064 | AE25: 0.9%
A26: New Car | B26: Transportation: Energy Efficiency Indicators: Compliance: New Car: Alternative Electricity and Transportation | C26: AEO.2026.ELECTRNP.EFI_CAFEC_TRN_HWY_CAR_NEW_NA_MLSPGLN.A | D26: mpg | E26: 54.000961 | F26: 56.055962 | G26: 59.182526 | H26: 58.581886 | I26: 58.580784 | J26: 58.559364 | K26: 59.716927 | L26: 60.620895 | M26: 61.614532 | N26: 62.431854 | O26: 63.384079 | P26: 64.214333 | Q26: 64.992035 | R26: 65.560905 | S26: 66.094299 | T26: 66.597168 | U26: 67.073395 | V26: 67.551796 | W26: 67.984055 | X26: 68.363754 | Y26: 68.707748 | Z26: 69.049065 | AA26: 69.406235 | AB26: 69.724709 | AC26: 70.033211 | AD26: 70.326408 | AE26: 1.1%
A27: New Light Truck | B27: Transportation: Energy Efficiency Indicators: Compliance: New Light Truck: Alternative Electricity and Transportation | C27: AEO.2026.ELECTRNP.EFI_CAFEC_TRN_HWY_LTRT_NEW_NA_MLSPGLN.A | D27: mpg | E27: 36.422165 | F27: 39.084152 | G27: 40.813885 | H27: 41.932571 | I27: 41.337978 | J27: 40.808418 | K27: 40.703747 | L27: 40.601673 | M27: 41.15593 | N27: 41.518898 | O27: 42.020275 | P27: 42.425022 | Q27: 42.875587 | R27: 43.293945 | S27: 43.751919 | T27: 44.124466 | U27: 44.383434 | V27: 44.659653 | W27: 44.902576 | X27: 45.145439 | Y27: 45.441231 | Z27: 45.583241 | AA27: 45.828648 | AB27: 45.988628 | AC27: 46.214172 | AD27: 46.369961 | AE27: 1.0%
A28: Tested New Light-Duty Vehicle | B28: Transportation: Energy Efficiency Indicators: Tested: New Light-Duty Vehicle: Alternative Electricity and Transportation | C28: AEO.2026.ELECTRNP.EFI_CAFET_TRN_HWY_LDTY_NEW_NA_MLSPGLN.A | D28: mpg | E28: 37.928226 | F28: 39.647724 | G28: 41.105446 | H28: 42.182793 | I28: 42.193748 | J28: 42.276684 | K28: 42.375996 | L28: 42.432007 | M28: 43.088806 | N28: 43.508045 | O28: 44.079277 | P28: 44.526707 | Q28: 45.012192 | R28: 45.432915 | S28: 45.867981 | T28: 46.221058 | U28: 46.489483 | V28: 46.775105 | W28: 47.009304 | X28: 47.23616 | Y28: 47.510242 | Z28: 47.658443 | AA28: 47.917152 | AB28: 48.08897 | AC28: 48.316952 | AD28: 48.478035 | AE28: 1.0%
A29: New Car | B29: Transportation: Energy Efficiency Indicators: Tested: New Car: Alternative Electricity and Transportation | C29: AEO.2026.ELECTRNP.EFI_CAFET_TRN_HWY_CAR_NEW_NA_MLSPGLN.A | D29: mpg | E29: 49.590649 | F29: 51.215469 | G29: 53.608128 | H29: 54.096859 | I29: 54.943535 | J29: 55.999603 | K29: 57.098698 | L29: 57.95953 | M29: 58.912979 | N29: 59.698708 | O29: 60.617741 | P29: 61.414299 | Q29: 62.16518 | R29: 62.723667 | S29: 63.247803 | T29: 63.73801 | U29: 64.206818 | V29: 64.676704 | W29: 65.102783 | X29: 65.478195 | Y29: 65.817009 | Z29: 66.156799 | AA29: 66.510269 | AB29: 66.825684 | AC29: 67.132545 | AD29: 67.423073 | AE29: 1.2%
A30: New Light Truck | B30: Transportation: Energy Efficiency Indicators: Tested: New Light Truck: Alternative Electricity and Transportation | C30: AEO.2026.ELECTRNP.EFI_CAFET_TRN_HWY_LTRT_NEW_NA_MLSPGLN.A | D30: mpg | E30: 33.648506 | F30: 35.589489 | G30: 36.95414 | H30: 38.312691 | I30: 38.150814 | J30: 38.049187 | K30: 37.943958 | L30: 37.849594 | M30: 38.35022 | N30: 38.681946 | O30: 39.137226 | P30: 39.505383 | Q30: 39.913685 | R30: 40.293804 | S30: 40.705418 | T30: 41.044151 | U30: 41.28273 | V30: 41.536674 | W30: 41.76059 | X30: 41.983673 | Y30: 42.253582 | Z30: 42.386532 | AA30: 42.611763 | AB30: 42.760551 | AC30: 42.967159 | AD30: 43.111107 | AE30: 1.0%
A31: On-Road New Light-Duty Vehicle | B31: Transportation: Energy Efficiency Indicators: On-Road New Light-Duty Vehicle: Alternative Electricity and Transportation | C31: AEO.2026.ELECTRNP.EFI_CAFEO_TRN_HWY_LDTY_NEW_NA_MLSPGLN.A | D31: mpg | E31: 28.107073 | F31: 29.329748 | G31: 30.373533 | H31: 31.130093 | I31: 31.173235 | J31: 31.242207 | K31: 31.322233 | L31: 31.374786 | M31: 31.84487 | N31: 32.146076 | O31: 32.552986 | P31: 32.873623 | Q31: 33.219925 | R31: 33.519707 | S31: 33.824932 | T31: 34.074589 | U31: 34.265041 | V31: 34.467197 | W31: 34.632568 | X31: 34.792171 | Y31: 34.984497 | Z31: 35.089149 | AA31: 35.270767 | AB31: 35.3918 | AC31: 35.551125 | AD31: 35.663898 | AE31: 1.0%
A32: New Car | B32: Transportation: Energy Efficiency Indicators: On-Road New Car: Alternative Electricity and Transportation | C32: AEO.2026.ELECTRNP.EFI_CAFEO_TRN_HWY_CAR_NEW_NA_MLSPGLN.A | D32: mpg | E32: 36.199902 | F32: 37.373344 | G32: 39.080997 | H32: 39.436958 | I32: 40.070713 | J32: 40.811344 | K32: 41.597332 | L32: 42.21357 | M32: 42.898159 | N32: 43.462482 | O32: 44.119152 | P32: 44.69249 | Q32: 45.231426 | R32: 45.631031 | S32: 46.006317 | T32: 46.357426 | U32: 46.693378 | V32: 47.029873 | W32: 47.334881 | X32: 47.603088 | Y32: 47.844738 | Z32: 48.087399 | AA32: 48.339058 | AB32: 48.563984 | AC32: 48.781982 | AD32: 48.988636 | AE32: 1.2%
A33: New Light Truck | B33: Transportation: Energy Efficiency Indicators: On-Road New Light Truck: Alternative Electricity and Transportation | C33: AEO.2026.ELECTRNP.EFI_CAFEO_TRN_HWY_LTRT_NEW_NA_MLSPGLN.A | D33: mpg | E33: 25.075277 | F33: 26.455212 | G33: 27.429825 | H33: 28.387552 | I33: 28.303217 | J33: 28.24004 | K33: 28.170067 | L33: 28.11274 | M33: 28.47032 | N33: 28.707502 | O33: 29.030571 | P33: 29.292917 | Q33: 29.58305 | R33: 29.853666 | S33: 30.141468 | T33: 30.380302 | U33: 30.548571 | V33: 30.727316 | W33: 30.884512 | X33: 31.04084 | Y33: 31.229944 | Z33: 31.32299 | AA33: 31.480368 | AB33: 31.584442 | AC33: 31.728251 | AD33: 31.828354 | AE33: 1.0%
... A37: Freight Truck | B37: Transportation: Energy Efficiency Indicators: Freight Truck: Alternative Electricity and Transportation | C37: AEO.2026.ELECTRNP.EFI_NA_TRN_HWY_FRTT_STK_NA_MLSPGLN.A | D37: mpg | E37: 8.027692 | F37: 8.077957 | G37: 8.140326 | H37: 8.2117 | I37: 8.288628 | J37: 8.370771 | K37: 8.455252 | L37: 8.555115 | M37: 8.65646 | N37: 8.753675 | O37: 8.844593 | P37: 8.926902 | Q37: 9.002301 | R37: 9.072346 | S37: 9.137053 | T37: 9.198642 | U37: 9.255984 | V37: 9.310497 | W37: 9.362345 | X37: 9.413412 | Y37: 9.464914 | Z37: 9.516226 | AA37: 9.568115 | AB37: 9.620857 | AC37: 9.673317 | AD37: 9.72301 | AE37: 0.8%
A38: (seat miles per gallon)
A39: Aircraft | B39: Transportation: Energy Efficiency Indicators: Aircraft: Alternative Electricity and Transportation | C39: AEO.2026.ELECTRNP.EFI_NA_TRN_NA_AIRC_NA_NA_SEATMPG.A | D39: seat mpg | E39: 85.781158 | F39: 86.455711 | G39: 87.136612 | H39: 87.833656 | I39: 88.507484 | J39: 89.191338 | K39: 89.89196 | L39: 90.644943 | M39: 91.405495 | N39: 92.163765 | O39: 92.924316 | P39: 93.685585 | Q39: 94.442947 | R39: 95.21875 | S39: 95.984337 | T39: 96.767494 | U39: 97.562447 | V39: 98.387817 | W39: 99.210266 | X39: 100.03344 | Y39: 100.8617 | Z39: 101.69355 | AA39: 102.529 | AB39: 103.37109 | AC39: 104.21042 | AD39: 105.05081 | AE39: 0.8%
A40: (ton miles/thousand Btu)
A41: Rail | B41: Transportation: Energy Efficiency Indicators: Rail: Alternative Electricity and Transportation | C41: AEO.2026.ELECTRNP.EFI_NA_TRN_NA_RAIL_NA_NA_TONMLPTHBTU.A | D41: ton miles/thousand Btu | E41: 3.37701 | F41: 3.380574 | G41: 3.384142 | H41: 3.387713 | I41: 3.391289 | J41: 3.394868 | K41: 3.398451 | L41: 3.402037 | M41: 3.405628 | N41: 3.409222 | O41: 3.41282 | P41: 3.416422 | Q41: 3.420027 | R41: 3.423637 | S41: 3.42725 | T41: 3.430867 | U41: 3.434488 | V41: 3.438113 | W41: 3.441741 | X41: 3.445373 | Y41: 3.44901 | Z41: 3.452649 | AA41: 3.456293 | AB41: 3.459941 | AC41: 3.463593 | AD41: 3.467248 | AE41: 0.1%
A42: Domestic Shipping | B42: Transportation: Energy Efficiency Indicators: Domestic Shipping: Alternative Electricity and Transportation | C42: AEO.2026.ELECTRNP.EFI_NA_TRN_NA_DMT_NA_NA_TONMLPTHBTU.A | D42: ton miles/thousand Btu | E42: 4.876665 | F42: 4.895624 | G42: 4.914657 | H42: 4.933764 | I42: 4.952945 | J42: 4.9722 | K42: 4.991531 | L42: 5.010937 | M42: 5.030418 | N42: 5.049975 | O42: 5.069608 | P42: 5.089317 | Q42: 5.109103 | R42: 5.128966 | S42: 5.148906 | T42: 5.168923 | U42: 5.189019 | V42: 5.209192 | W42: 5.229445 | X42: 5.249775 | Y42: 5.270185 | Z42: 5.290674 | AA42: 5.311243 | AB42: 5.331892 | AC42: 5.352621 | AD42: 5.37343 | AE42: 0.4%
A43: Energy Use by Mode
A44: (quadrillion Btu)
A45: Light-Duty Vehicles | B45: Transportation: Energy Use by Mode: Light-Duty Vehicles: Alternative Electricity and Transportation | C45: AEO.2026.ELECTRNP.CNSM_NA_TRN_LDV_USE_NA_NA_QBTU.A | D45: quads | E45: 14.782653 | F45: 14.672787 | G45: 14.55257 | H45: 14.378154 | I45: 14.166835 | J45: 13.936758 | K45: 13.713143 | L45: 13.5211 | M45: 13.320393 | N45: 13.191331 | O45: 13.049684 | P45: 12.877705 | Q45: 12.704929 | R45: 12.556595 | S45: 12.411376 | T45: 12.293764 | U45: 12.185322 | V45: 12.056223 | W45: 11.972279 | X45: 11.877881 | Y45: 11.796014 | Z45: 11.703431 | AA45: 11.626832 | AB45: 11.521401 | AC45: 11.413983 | AD45: 11.339188 | AE45: -1.1%
A46: Commercial Light Trucks | B46: Transportation: Energy Use by Mode: Commercial Light Trucks: Alternative Electricity and Transportation | C46: AEO.2026.ELECTRNP.CNSM_NA_TRN_CML_USE_NA_NA_QBTU.A | D46: quads | E46: 0.871738 | F46: 0.870931 | G46: 0.878188 | H46: 0.87664 | I46: 0.877498 | J46: 0.883066 | K46: 0.889113 | L46: 0.896205 | M46: 0.899513 | N46: 0.902266 | O46: 0.904878 | P46: 0.908145 | Q46: 0.911624 | R46: 0.915686 | S46: 0.92017 | T46: 0.923987 | U46: 0.924614 | V46: 0.925101 | W46: 0.921748 | X46: 0.918246 | Y46: 0.914856 | Z46: 0.911689 | AA46: 0.91008 | AB46: 0.90757 | AC46: 0.906507 | AD46: 0.904855 | AE46: 0.1%
A47: Bus Transportation | B47: Transportation: Energy Use by Mode: Bus Transportation: Alternative Electricity and Transportation | C47: AEO.2026.ELECTRNP.CNSM_NA_TRN_BST_USE_NA_NA_QBTU.A | D47: quads | E47: 0.211253 | F47: 0.212578 | G47: 0.213112 | H47: 0.213566 | I47: 0.213721 | J47: 0.213305 | K47: 0.212526 | L47: 0.211386 | M47: 0.21053 | N47: 0.209219 | O47: 0.207978 | P47: 0.20681 | Q47: 0.205795 | R47: 0.20467 | S47: 0.203497 | T47: 0.202422 | U47: 0.201168 | V47: 0.199892 | W47: 0.198414 | X47: 0.196954 | Y47: 0.19552 | Z47: 0.193973 | AA47: 0.192578 | AB47: 0.190986 | AC47: 0.189412 | AD47: 0.187759 | AE47: -0.5%
A48: Freight Trucks | B48: Transportation: Energy Use by Mode: Freight Trucks: Alternative Electricity and Transportation | C48: AEO.2026.ELECTRNP.CNSM_NA_TRN_FGHT_USE_NA_NA_QBTU.A | D48: quads | E48: 5.766912 | F48: 5.753704 | G48: 5.746598 | H48: 5.7388 | I48: 5.723918 | J48: 5.726193 | K48: 5.711863 | L48: 5.694184 | M48: 5.667161 | N48: 5.653565 | O48: 5.645734 | P48: 5.641738 | Q48: 5.643165 | R48: 5.647539 | S48: 5.65498 | T48: 5.667878 | U48: 5.681262 | V48: 5.694604 | W48: 5.704225 | X48: 5.715442 | Y48: 5.736444 | Z48: 5.760567 | AA48: 5.787274 | AB48: 5.805713 | AC48: 5.825782 | AD48: 5.843337 | AE48: 0.1%
